Workbook
Name _vena_1_B1_C_FV_134399665b374008851e5b8c04b5ee44: '609 IS Var'!$M$6
Name _vena_1_B1_C_FV_134399665b374008851e5b8c04b5ee44_1: '609 IS Var'!$O$6
Name _vena_1_B1_C_FV_134399665b374008851e5b8c04b5ee44_10: '609 IS Var'!$AQ$6
Name _vena_1_B1_C_FV_134399665b374008851e5b8c04b5ee44_11: '609 IS Var'!$BA$6
Name _vena_1_B1_C_FV_134399665b374008851e5b8c04b5ee44_12: '609 IS Var'!$BC$6
Name _vena_1_B1_C_FV_134399665b374008851e5b8c04b5ee44_13: '609 IS Var'!$BE$6
Name _vena_1_B1_C_FV_134399665b374008851e5b8c04b5ee44_2: '609 IS Var'!$Q$6
Name _vena_1_B1_C_FV_134399665b374008851e5b8c04b5ee44_3: '609 IS Var'!$S$6
Name _vena_1_B1_C_FV_134399665b374008851e5b8c04b5ee44_4: '609 IS Var'!$AC$6
Name _vena_1_B1_C_FV_134399665b374008851e5b8c04b5ee44_5: '609 IS Var'!$AD$6
Name _vena_1_B1_C_FV_134399665b374008851e5b8c04b5ee44_6: '609 IS Var'!$AE$6
Name _vena_1_B1_C_FV_134399665b374008851e5b8c04b5ee44_7: '609 IS Var'!$AK$6
Name _vena_1_B1_C_FV_134399665b374008851e5b8c04b5ee44_8: '609 IS Var'!$AM$6
Name _vena_1_B1_C_FV_134399665b374008851e5b8c04b5ee44_9: '609 IS Var'!$AO$6
Name _vena_1_B1_C_FV_7cc8369c0b744816a17486bee792b4d5: '609 IS Var'!$M$4
Name _vena_1_B1_C_FV_7cc8369c0b744816a17486bee792b4d5_1: '609 IS Var'!$O$4
Name _vena_1_B1_C_FV_7cc8369c0b744816a17486bee792b4d5_10: '609 IS Var'!$AQ$4
Name _vena_1_B1_C_FV_7cc8369c0b744816a17486bee792b4d5_11: '609 IS Var'!$BA$4
Name _vena_1_B1_C_FV_7cc8369c0b744816a17486bee792b4d5_12: '609 IS Var'!$BC$4
Name _vena_1_B1_C_FV_7cc8369c0b744816a17486bee792b4d5_13: '609 IS Var'!$BE$4
Name _vena_1_B1_C_FV_7cc8369c0b744816a17486bee792b4d5_2: '609 IS Var'!$Q$4
Name _vena_1_B1_C_FV_7cc8369c0b744816a17486bee792b4d5_3: '609 IS Var'!$S$4
Name _vena_1_B1_C_FV_7cc8369c0b744816a17486bee792b4d5_4: '609 IS Var'!$AC$4
Name _vena_1_B1_C_FV_7cc8369c0b744816a17486bee792b4d5_5: '609 IS Var'!$AD$4
Name _vena_1_B1_C_FV_7cc8369c0b744816a17486bee792b4d5_6: '609 IS Var'!$AE$4
Name _vena_1_B1_C_FV_7cc8369c0b744816a17486bee792b4d5_7: '609 IS Var'!$AK$4
Name _vena_1_B1_C_FV_7cc8369c0b744816a17486bee792b4d5_8: '609 IS Var'!$AM$4
Name _vena_1_B1_C_FV_7cc8369c0b744816a17486bee792b4d5_9: '609 IS Var'!$AO$4
Name _vena_1_B1_C_FV_f4ddf33ff6224574ba096b1a5435ea67: '609 IS Var'!$M$5
Name _vena_1_B1_C_FV_f4ddf33ff6224574ba096b1a5435ea67_1: '609 IS Var'!$O$5
Name _vena_1_B1_C_FV_f4ddf33ff6224574ba096b1a5435ea67_10: '609 IS Var'!$AQ$5
Name _vena_1_B1_C_FV_f4ddf33ff6224574ba096b1a5435ea67_11: '609 IS Var'!$BA$5
Name _vena_1_B1_C_FV_f4ddf33ff6224574ba096b1a5435ea67_12: '609 IS Var'!$BC$5
Name _vena_1_B1_C_FV_f4ddf33ff6224574ba096b1a5435ea67_13: '609 IS Var'!$BE$5
Name _vena_1_B1_C_FV_f4ddf33ff6224574ba096b1a5435ea67_2: '609 IS Var'!$Q$5
Name _vena_1_B1_C_FV_f4ddf33ff6224574ba096b1a5435ea67_3: '609 IS Var'!$S$5
Name _vena_1_B1_C_FV_f4ddf33ff6224574ba096b1a5435ea67_4: '609 IS Var'!$AC$5
Name _vena_1_B1_C_FV_f4ddf33ff6224574ba096b1a5435ea67_5: '609 IS Var'!$AD$5
Name _vena_1_B1_C_FV_f4ddf33ff6224574ba096b1a5435ea67_6: '609 IS Var'!$AE$5
Name _vena_1_B1_C_FV_f4ddf33ff6224574ba096b1a5435ea67_7: '609 IS Var'!$AK$5
Name _vena_1_B1_C_FV_f4ddf33ff6224574ba096b1a5435ea67_8: '609 IS Var'!$AM$5
Name _vena_1_B1_C_FV_f4ddf33ff6224574ba096b1a5435ea67_9: '609 IS Var'!$AO$5
Name _vena_1_B1_R_1_1126333519640395796: '609 IS Var'!$H$44
Name _vena_1_B1_R_1_1126333519686533120: '609 IS Var'!$H$54
Name _vena_1_B1_R_1_1126333519715893262: '609 IS Var'!$H$59
Name _vena_1_B1_R_1_1126333519736864780: '609 IS Var'!$H$95
Name _vena_1_B1_R_1_1126333519762030608: '609 IS Var'!$H$114
Name _vena_1_B1_R_1_1126333519778807820: '609 IS Var'!$H$104
Name _vena_1_B1_R_1_1126333519787196446: '609 IS Var'!$H$126
Name _vena_1_B1_R_1_1126333519808167948: '609 IS Var'!$H$121
Name _vena_1_B1_R_1_1126333519854305298: '609 IS Var'!$H$67
Name _vena_1_B1_R_1_1126333519871082529: '609 IS Var'!$H$132
Name _vena_1_B1_R_1_1126333519883665426: '609 IS Var'!$H$91
Name _vena_1_B1_R_1_1126333519900442631: '609 IS Var'!$H$75
Name _vena_1_B1_R_1_1126333519925608473: '609 IS Var'!$H$142
Name _vena_1_B1_R_1_1126333519963357190: '609 IS Var'!$H$144
Name _vena_1_B1_R_1_1176989022519558144: '609 IS Var'!$H$32
Name _vena_1_B1_R_1_1177034623004573696: '609 IS Var'!$H$129
Name _vena_1_B1_R_1_1177042009963233280: '609 IS Var'!$H$38
Name _vena_1_B1_R_1_1177042321444044802: '609 IS Var'!$H$36

Sheet Month Name
A1: All Years | B1: All Years | E1: Actual
A2: Frederic Media
A4: MultiDynamic: Period | C4: #VALUE! | D4: #VALUE!
A5: 10 (Oct) | C5: Oct | D5: 10 | E5: -1784526.2
A6: 11 (Nov) | C6: Nov | D6: 11 | E6: -906306.35
A7: 5 (May) | C7: May | D7: 5 | E7: -685198.88
A8: 4 (Apr) | C8: Apr | D8: 4 | E8: -824143.47
A9: 7 (Jul) | C9: Jul | D9: 7 | E9: -782743.01
A10: 1 (Jan) | C10: Jan | D10: 1 | E10: -253866.64
A11: 6 (Jun) | C11: Jun | D11: 6 | E11: -97948.1
A12: 9 (Sep) | C12: Sep | D12: 9 | E12: -128603.02
A13: 12 (Dec) | C13: Dec | D13: 12 | E13: -1164650.9
A14: 8 (Aug) | C14: Aug | D14: 8 | E14: -1098019.5
A15: 2 (Feb) | C15: Feb | D15: 2 | E15: -842818.59
A16: 3 (Mar) | C16: Mar | D16: 3 | E16: -769144.77
C17: #VALUE! | D17: #VALUE!

Sheet Scenario
A1: 2026 | C1: Local
A2: Plan | C2: Net Income
A3: All Departments | C3: Undefined (Not Placeholder 1 Specific)
A4: 1 (Jan) | C4: Undefined (Not Placeholder 2 Specific)
C5: Undefined (Not Placeholder 3 Specific)
C6: Undefined (Not Placeholder 4 Specific)
C7: Undefined (Not Entity Specific)
A12: Value | C12: -9768.2966

Sheet Sheet1
B1: #hidecolumn
B2: #hiderow | C2: #hidecolumn | D2: #hidecolumn | E2: #hidecolumn | F2: #hidecolumn | G2: #hidecolumn | I2: #hidecolumn | J2: #hidecolumn | L2: #hidecolumn | O2: =IF(VALUE(TRIM(LEFT(Scenario!$A$4,2)))<4, "#hidecolumn", "#showcolumn") -> #hidecolumn | P2: =O2 -> #hidecolumn | Q2: =IF(VALUE(TRIM(LEFT(Scenario!$A$4,2)))<4, "#showcolumn", "#hidecolumn") -> #showcolumn | R2: =Q2 -> #showcolumn | U2: =V2 -> #hidecolumn | V2: =IF(VALUE(TRIM(LEFT(Scenario!$A$4,2)))<4, "#hidecolumn", "#showcolumn") -> #hidecolumn | W2: =X2 -> #showcolumn | X2: =IF(VALUE(TRIM(LEFT(Scenario!$A$4,2)))<4, "#showcolumn", "#hidecolumn") -> #showcolumn | AB2: #hidecolumn | AC2: #hidecolumn | AD2: #hidecolumn | AE2: #hidecolumn | AF2: #hidecolumn | AG2: #hidecolumn | AH2: #hidecolumn | AI2: #hidecolumn | AM2: =IF(VALUE(TRIM(LEFT(Scenario!$A$4,2)))<4, "#hidecolumn", "#showcolumn") -> #hidecolumn | AN2: =AM2 -> #hidecolumn | AO2: =IF(VALUE(TRIM(LEFT(Scenario!$A$4,2)))<4, "#showcolumn", "#hidecolumn") -> #showcolumn | AP2: =AO2 -> #showcolumn | AS2: =AT2 -> #hidecolumn | AT2: =IF(VALUE(TRIM(LEFT(Scenario!$A$4,2)))<4, "#hidecolumn", "#showcolumn") -> #hidecolumn | AU2: =AV2 -> #showcolumn | AV2: =IF(VALUE(TRIM(LEFT(Scenario!$A$4,2)))<4, "#showcolumn", "#hidecolumn") -> #showcolumn | BC2: =IF(VALUE(TRIM(LEFT(Scenario!$A$4,2)))<4, "#showcolumn", "#hidecolumn") -> #showcolumn | BD2: =BC2 -> #showcolumn | BG2: =BH2 -> #showcolumn | BH2: =IF(VALUE(TRIM(LEFT(Scenario!$A$4,2)))<4, "#showcolumn", "#hidecolumn") -> #showcolumn | BK2: #hidecolumn
B3: #hiderow | C3: =_xlfn.CONCAT("Section: ", LEFT(E6,3)) -> Section: 954
B4: #hiderow | C4: Dimension | D4: Position | L4: =VALUE(TRIM(LEFT(Scenario!$A$4,2))) -> 1 | M4: =Scenario!$A$1 -> 2026 | O4: =Scenario!$A$1 -> 2026 | Q4: =Scenario!$A$1 -> 2026 | S4: =Scenario!$A$1-1 -> 2025 | AC4: =Scenario!$A$1 -> 2026 | AD4: =Scenario!$A$1-1 -> 2025 | AE4: =Scenario!$A$1 -> 2026 | AK4: =Scenario!$A$1 -> 2026 | AM4: =Scenario!$A$1 -> 2026 | AO4: =Scenario!$A$1 -> 2026 | AQ4: =Scenario!$A$1-1 -> 2025 | BA4: 2025 | BC4: 2025 | BE4: =BA4-1 -> 2024
B5: #hiderow | C5: Account | D5: Row | M5: =VALUE(TRIM(LEFT(Scenario!$A$4,2))) -> 1 | O5: =VALUE(TRIM(LEFT(Scenario!$A$4,2))) -> 1 | Q5: =VALUE(TRIM(LEFT(Scenario!$A$4,2))) -> 1 | S5: =VALUE(TRIM(LEFT(Scenario!$A$4,2))) -> 1 | AC5: =VALUE(TRIM(LEFT(Scenario!$A$4,2)))&" QTD" -> 1 QTD | AD5: =VALUE(TRIM(LEFT(Scenario!$A$4,2)))&" QTD" -> 1 QTD | AE5: =VALUE(TRIM(LEFT(Scenario!$A$4,2)))&" QTD" -> 1 QTD | AK5: =VALUE(TRIM(LEFT(Scenario!$A$4,2)))&" YTD" -> 1 YTD | AM5: =VALUE(TRIM(LEFT(Scenario!$A$4,2)))&" YTD" -> 1 YTD | AO5: =VALUE(TRIM(LEFT(Scenario!$A$4,2)))&" YTD" -> 1 YTD | AQ5: =VALUE(TRIM(LEFT(Scenario!$A$4,2)))&" YTD" -> 1 YTD | BA5: 12 YTD | BC5: 12 YTD | BE5: 12 YTD
B6: #hiderow | C6: Department | D6: Page | E6: 954 (Frederic Media Business Development) | M6: ="Actual" -> Actual | O6: =[2]Scenario!$A$2 -> Forecast 3+9 | Q6: Plan | S6: ="Actual" -> Actual | AC6: ="Actual" -> Actual | AD6: ="Actual" -> Actual | AE6: Plan | AK6: ="Actual" -> Actual | AM6: =[2]Scenario!$A$2 -> Forecast 3+9 | AO6: Plan | AQ6: ="Actual" -> Actual | BA6: =IF(VALUE(TRIM(LEFT(Scenario!$A$4,2)))<4, "Plan", [2]Scenario!$A$2) -> Plan | BC6: Plan | BE6: ="Actual" -> Actual
B7: #hiderow | C7: Year | D7: Column
B8: #hiderow | C8: Period | D8: Column
B9: #hiderow | C9: Scenario | D9: Column
B10: #hiderow | C10: Currency | D10: Page | E10: Local
B11: #hiderow | C11: Measure | D11: Page | E11: Value
E12: Undefined (Not Entity Specific)
E13: Undefined (Not Placeholder 1 Specific)
E14: Undefined (Not Placeholder 2 Specific)
E15: Undefined (Not Placeholder 3 Specific)
E16: Undefined (Not Placeholder 4 Specific)
B17: #hiderow
H18: Income Statement Variance
H19: =E6 -> 954 (Frederic Media Business Development) | M19: =_xlfn.XLOOKUP(M$5,'[2]Month Name'!$D:$D, '[2]Month Name'!$C:$C)&" "&RIGHT(M4,2) -> Jan 26 | N19: Actual | P19: Forecast | R19: Plan | T19: Prior Year | AF19: =_xlfn.CONCAT(TEXT((TRIM(MID(M5,4,3))),"mmm")," QTD ",RIGHT(M4,2)) -> QTD 26 | AK19: =_xlfn.XLOOKUP(M$5,'[2]Month Name'!$D:$D, '[2]Month Name'!$C:$C)&" YTD "&RIGHT(M4,2) -> Jan YTD 26 | AL19: Actual | AN19: Forecast | AP19: Plan | AR19: Prior Year | BB19: Forecast | BD19: Plan | BF19: Prior Year
G20: =IF(FlagShowCalendar,OpeningPeriod,"Opening Period: P"&VALUE(TRIM(LEFT(Scenario!$A$4,2)))&" FY"&RIGHT(Scenario!$A$1,2)) -> #NAME? | M20: =_xlfn.XLOOKUP(M$5,'[2]Month Name'!$D:$D, '[2]Month Name'!$C:$C)&" "&RIGHT(M4,2) -> Jan 26 | N20: % of | O20: =_xlfn.XLOOKUP(O$5,'[2]Month Name'!$D:$D, '[2]Month Name'!$C:$C)&" "&RIGHT(O4,2) -> Jan 26 | P20: % of | Q20: =_xlfn.XLOOKUP(Q$5,'[2]Month Name'!$D:$D, '[2]Month Name'!$C:$C)&" "&RIGHT(Q4,2) -> Jan 26 | R20: % of | S20: =_xlfn.XLOOKUP(S$5,'[2]Month Name'!$D:$D, '[2]Month Name'!$C:$C)&" "&RIGHT(S4,2) -> Jan 25 | T20: % of | U20: % Var | V20: $ Var | W20: =Y20 -> % Var | X20: =Z20 -> $ Var | Y20: % Var | Z20: $ Var | AC20: =AF19 -> QTD 26 | AD20: =_xlfn.CONCAT(TEXT((TRIM(MID(M5,4,3))),"mmm")," QTD ",RIGHT(S4,2)) -> QTD 25 | AE20: =AC20 -> QTD 26 | AF20: % Var | AG20: $ Var | AH20: =AF20 -> % Var | AI20: =AG20 -> $ Var | AK20: =_xlfn.XLOOKUP(M$5,'[2]Month Name'!$D:$D, '[2]Month Name'!$C:$C)&" YTD "&RIGHT(M4,2) -> Jan YTD 26 | AL20: % of | AM20: =_xlfn.XLOOKUP(O$5,'[2]Month Name'!$D:$D, '[2]Month Name'!$C:$C)&" YTD "&RIGHT(O4,2) -> Jan YTD 26 | AN20: % of | AO20: =_xlfn.XLOOKUP(Q$5,'[2]Month Name'!$D:$D, '[2]Month Name'!$C:$C)&" YTD "&RIGHT(Q4,2) -> Jan YTD 26 | AP20: % of | AQ20: =_xlfn.XLOOKUP(S$5,'[2]Month Name'!$D:$D, '[2]Month Name'!$C:$C)&" YTD "&RIGHT(S4,2) -> Jan YTD 25 | AR20: % of | AS20: % Var | AT20: $ Var | AU20: =AW20 -> % Var | AV20: =AX20 -> $ Var | AW20: % Var | AX20: $ Var | BA20: ="Full Year "&BA4 -> Full Year 2025 | BB20: % of | BC20: ="Full Year "&BC4 -> Full Year 2025 | BD20: % of | BE20: ="Full Year "&BE4 -> Full Year 2024 | BF20: % of | BG20: =BI20 -> % Var | BH20: =BJ20 -> $ Var | BI20: % Var | BJ20: $ Var
G21: ="in "&$G$5&" currency" -> in currency | M21: =M6 -> Actual | N21: Net Sales | O21: =O6 -> Forecast 3+9 | P21: Net Sales | Q21: =IF(Q6="Plan", "Budget", Q6) -> Budget | R21: Net Sales | S21: ="PY "&S6 -> PY Actual | T21: Net Sales | U21: =O21 -> Forecast 3+9 | V21: =O21 -> Forecast 3+9 | W21: =Q21 -> Budget | X21: =Q21 -> Budget | Y21: PY | Z21: PY | AA21: Commentary | AC21: =AC6 -> Actual | AD21: ="PY "&AD6 -> PY Actual | AE21: Budget | AF21: PY | AG21: PY | AH21: =AE21 -> Budget | AI21: =AH21 -> Budget | AK21: =AK6 -> Actual | AL21: Net Sales | AM21: =AM6 -> Forecast 3+9 | AN21: Net Sales | AO21: =IF(AO6="Plan", "Budget", AO6) -> Budget | AP21: Net Sales | AQ21: ="PY "&AQ6 -> PY Actual | AR21: Net Sales | AS21: =AM21 -> Forecast 3+9 | AT21: =AM21 -> Forecast 3+9 | AU21: =AO21 -> Budget | AV21: =AO21 -> Budget | AW21: PY | AX21: PY | AY21: Commentary | BA21: =IF(BA6="Plan", "Budget", BA6) -> Budget | BB21: Net Sales | BC21: =IF(BC6="Plan", "Budget", BC6) -> Budget | BD21: Net Sales | BE21: =BE6 -> Actual | BF21: Net Sales | BG21: =BC21 -> Budget | BH21: =BC21 -> Budget | BI21: PY | BJ21: PY | BK21: Commentary
B23: #hiderow | H23: Current Year | I23: =YEAR(TODAY()-20) -> 2026
B24: #hiderow | H24: Current Month | I24: =MONTH(TODAY() - 20) -> 2
B25: #hiderow | H25: Current QTD | I25: =_xlfn.CONCAT(I24," QTD") -> 2 QTD
B26: #hiderow | H26: Current YTD | I26: =_xlfn.CONCAT(I24," YTD") -> 2 YTD
B27: #hiderow
B28: #hiderow
B29: #hiderow | G29: Add Description | H29: Add Description | I29: Line-Item Detail | U29: =IFERROR(($O29-M29)/ABS(M29),0) -> 0 | V29: =($O29-M29) -> 0 | W29: =IFERROR(($M29-Q29)/ABS(Q29),0) -> 0 | X29: =($M29-Q29) -> 0 | Y29: =IFERROR(($M29-S29)/ABS(S29),0) -> 0 | Z29: =($M29-S29) -> 0 | AF29: =IFERROR(($AC29-AD29)/ABS(AD29),0) -> 0 | AG29: =($AC29-AD29) -> 0 | AH29: =IFERROR(($AC29-AE29)/ABS(AE29),0) -> 0 | AI29: =($AC29-AE29) -> 0 | AS29: =IFERROR(($O29-AK29)/ABS(AK29),0) -> 0 | AT29: =($O29-AK29) -> 0 | AU29: =IFERROR(($M29-AO29)/ABS(AO29),0) -> 0 | AV29: =($M29-AO29) -> 0 | AW29: =IFERROR(($M29-AQ29)/ABS(AQ29),0) -> 0 | AX29: =($M29-AQ29) -> 0 | BG29: =IFERROR(($BA29-BC29)/ABS(BC29),0) -> 0 | BH29: =($BA29-BC29) -> 0 | BI29: =IFERROR(($BA29-BE29)/ABS(BE29),0) -> 0 | BJ29: =($BA29-BE29) -> 0
B30: =IF(COUNTBLANK(B31:B62)>0,"#showrow","#hiderow") -> #showrow | H30: Revenue
B31: #hiderow | H31: MultiDynamic: Account | N31: =IFERROR(M31/SUMIFS(M:M, $H:$H, "[+] Net Sales"),0) -> 0 | P31: =IFERROR(O31/SUMIFS(O:O, $H:$H, "[+] Net Sales"),0) -> 0 | R31: =IFERROR(Q31/SUMIFS(Q:Q, $H:$H, "[+] Net Sales"),0) -> 0 | T31: =IFERROR(S31/SUMIFS(S:S, $H:$H, "[+] Net Sales"),0) -> 0 | U31: =IFERROR(($M31-O31)/ABS(O31),0) -> 0 | V31: =IFERROR((M31-$O31), $M31-0) -> 0 | W31: =IFERROR((M31-$Q31)/ABS($Q31),0) -> 0 | X31: =IFERROR((M31-$Q31), $M31-0) -> 0 | Y31: =IFERROR((M31-$S31)/ABS($S31),0) -> 0 | Z31: =IFERROR((M31-$S31),$M31-0) -> 0 | AF31: =IFERROR(($AC31-AD31)/ABS(AD31),0) -> 0 | AG31: =($AC31-AD31) -> 0 | AH31: =IFERROR(($AC31-AE31)/ABS(AE31),0) -> 0 | AI31: =($AC31-AE31) -> 0 | AL31: =IFERROR(AK31/SUMIFS(AK:AK, $H:$H, "[+] Net Sales"),0) -> 0 | AN31: =IFERROR(AM31/SUMIFS(AM:AM, $H:$H, "[+] Net Sales"),0) -> 0 | AP31: =IFERROR(AO31/SUMIFS(AO:AO, $H:$H, "[+] Net Sales"),0) -> 0 | AR31: =IFERROR(AQ31/SUMIFS(AQ:AQ, $H:$H, "[+] Net Sales"),0) -> 0 | AS31: =IFERROR((AK31-$AM31)/ABS($AM31),0) -> 0 | AT31: =(AK31-$AM31) -> 0 | AU31: =IFERROR((AK31-$AO31)/ABS($AO31),0) -> 0 | AV31: =(AK31-$AO31) -> 0 | AW31: =IFERROR((AK31-$AQ31)/ABS($AQ31),0) -> 0 | AX31: =(AK31-$AQ31) -> 0 | BB31: =IFERROR(BA31/SUMIFS(BA:BA, $H:$H, "[+] Net Sales"),0) -> 0 | BD31: =IFERROR(BC31/SUMIFS(BC:BC, $H:$H, "[+] Net Sales"),0) -> 0 | BF31: =IFERROR(BE31/SUMIFS(BE:BE, $H:$H, "[+] Net Sales"),0) -> 0 | BG31: =IFERROR((BA31-$BC31)/ABS($BC31),0) -> 0 | BH31: =(BA31-$BC31) -> 0 | BI31: =IFERROR((BA31-$BE31)/ABS($BE31),0) -> 0 | BJ31: =(BA31-$BE31) -> 0
H32: [+] Net Sales | M32: 654439.77 | N32: =IFERROR(M32/SUMIFS(M:M, $H:$H, "[+] Net Sales"),0) -> 1 | O32: 0 | P32: =IFERROR(O32/SUMIFS(O:O, $H:$H, "[+] Net Sales"),0) -> 0 | Q32: 553920.45 | R32: =IFERROR(Q32/SUMIFS(Q:Q, $H:$H, "[+] Net Sales"),0) -> 1 | S32: 509967.01 | T32: =IFERROR(S32/SUMIFS(S:S, $H:$H, "[+] Net Sales"),0) -> 1 | U32: =IFERROR(($M32-O32)/ABS(O32),0) -> 0 | V32: =IFERROR((M32-$O32), $M32-0) -> 654439.77 | W32: =IFERROR((M32-$Q32)/ABS($Q32),0) -> 0.18146888 | X32: =IFERROR((M32-$Q32), $M32-0) -> 100519.32 | Y32: =IFERROR((M32-$S32)/ABS($S32),0) -> 0.28329825 | Z32: =IFERROR((M32-$S32),$M32-0) -> 144472.76 | AC32: 654439.77 | AD32: 509967.01 | AE32: 553920.45 | AF32: =IFERROR(($AC32-AD32)/ABS(AD32),0) -> 0.28329825 | AG32: =($AC32-AD32) -> 144472.76 | AH32: =IFERROR(($AC32-AE32)/ABS(AE32),0) -> 0.18146888 | AI32: =($AC32-AE32) -> 100519.32 | AK32: 654439.77 | AL32: =IFERROR(AK32/SUMIFS(AK:AK, $H:$H, "[+] Net Sales"),0) -> 1 | AM32: 0 | AN32: =IFERROR(AM32/SUMIFS(AM:AM, $H:$H, "[+] Net Sales"),0) -> 0 | AO32: 553920.45 | AP32: =IFERROR(AO32/SUMIFS(AO:AO, $H:$H, "[+] Net Sales"),0) -> 1 | AQ32: 509967.01 | AR32: =IFERROR(AQ32/SUMIFS(AQ:AQ, $H:$H, "[+] Net Sales"),0) -> 1 | AS32: =IFERROR((AK32-$AM32)/ABS($AM32),0) -> 0 | AT32: =(AK32-$AM32) -> 654439.77 | AU32: =IFERROR((AK32-$AO32)/ABS($AO32),0) -> 0.18146888 | AV32: =(AK32-$AO32) -> 100519.32 | AW32: =IFERROR((AK32-$AQ32)/ABS($AQ32),0) -> 0.28329825 | AX32: =(AK32-$AQ32) -> 144472.76 | BA32: 2231199 | BB32: =IFERROR(BA32/SUMIFS(BA:BA, $H:$H, "[+] Net Sales"),0) -> 1 | BC32: 2231199 | BD32: =IFERROR(BC32/SUMIFS(BC:BC, $H:$H, "[+] Net Sales"),0) -> 1 | BE32: 2008626.8 | BF32: =IFERROR(BE32/SUMIFS(BE:BE, $H:$H, "[+] Net Sales"),0) -> 1 | BG32: =IFERROR((BA32-$BC32)/ABS($BC32),0) -> 0 | BH32: =(BA32-$BC32) -> 0 | BI32: =IFERROR((BA32-$BE32)/ABS($BE32),0) -> 0.11080817 | BJ32: =(BA32-$BE32) -> 222572.25
H33: [*] 3010 (Sales - Regular) | M33: 20 | N33: =IFERROR(M33/SUMIFS(M:M, $H:$H, "[+] Net Sales"),0) -> 3.056049e-05 | P33: =IFERROR(O33/SUMIFS(O:O, $H:$H, "[+] Net Sales"),0) -> 0 | R33: =IFERROR(Q33/SUMIFS(Q:Q, $H:$H, "[+] Net Sales"),0) -> 0 | T33: =IFERROR(S33/SUMIFS(S:S, $H:$H, "[+] Net Sales"),0) -> 0 | U33: =IFERROR(($M33-O33)/ABS(O33),0) -> 0 | V33: =IFERROR((M33-$O33), $M33-0) -> 20 | W33: =IFERROR((M33-$Q33)/ABS($Q33),0) -> 0 | X33: =IFERROR((M33-$Q33), $M33-0) -> 20 | Y33: =IFERROR((M33-$S33)/ABS($S33),0) -> 0 | Z33: =IFERROR((M33-$S33),$M33-0) -> 20 | AC33: 20 | AD33: 0 | AE33: 0 | AF33: =IFERROR(($AC33-AD33)/ABS(AD33),0) -> 0 | AG33: =($AC33-AD33) -> 20 | AH33: =IFERROR(($AC33-AE33)/ABS(AE33),0) -> 0 | AI33: =($AC33-AE33) -> 20 | AK33: 20 | AL33: =IFERROR(AK33/SUMIFS(AK:AK, $H:$H, "[+] Net Sales"),0) -> 3.056049e-05 | AM33: 0 | AN33: =IFERROR(AM33/SUMIFS(AM:AM, $H:$H, "[+] Net Sales"),0) -> 0 | AO33: 0 | AP33: =IFERROR(AO33/SUMIFS(AO:AO, $H:$H, "[+] Net Sales"),0) -> 0 | AQ33: 0 | AR33: =IFERROR(AQ33/SUMIFS(AQ:AQ, $H:$H, "[+] Net Sales"),0) -> 0 | AS33: =IFERROR((AK33-$AM33)/ABS($AM33),0) -> 0 | AT33: =(AK33-$AM33) -> 20 | AU33: =IFERROR((AK33-$AO33)/ABS($AO33),0) -> 0 | AV33: =(AK33-$AO33) -> 20 | AW33: =IFERROR((AK33-$AQ33)/ABS($AQ33),0) -> 0 | AX33: =(AK33-$AQ33) -> 20 | BA33: 0 | BB33: =IFERROR(BA33/SUMIFS(BA:BA, $H:$H, "[+] Net Sales"),0) -> 0 | BC33: 0 | BD33: =IFERROR(BC33/SUMIFS(BC:BC, $H:$H, "[+] Net Sales"),0) -> 0 | BE33: 2008647.8 | BF33: =IFERROR(BE33/SUMIFS(BE:BE, $H:$H, "[+] Net Sales"),0) -> 1.0000105 | BG33: =IFERROR((BA33-$BC33)/ABS($BC33),0) -> 0 | BH33: =(BA33-$BC33) -> 0 | BI33: =IFERROR((BA33-$BE33)/ABS($BE33),0) -> -1 | BJ33: =(BA33-$BE33) -> -2008647.8
H34: [*] 3011 (Sales - Paint) | N34: =IFERROR(M34/SUMIFS(M:M, $H:$H, "[+] Net Sales"),0) -> 0 | P34: =IFERROR(O34/SUMIFS(O:O, $H:$H, "[+] Net Sales"),0) -> 0 | R34: =IFERROR(Q34/SUMIFS(Q:Q, $H:$H, "[+] Net Sales"),0) -> 0 | T34: =IFERROR(S34/SUMIFS(S:S, $H:$H, "[+] Net Sales"),0) -> 0 | U34: =IFERROR(($M34-O34)/ABS(O34),0) -> 0 | V34: =IFERROR((M34-$O34), $M34-0) -> 0 | W34: =IFERROR((M34-$Q34)/ABS($Q34),0) -> 0 | X34: =IFERROR((M34-$Q34), $M34-0) -> 0 | Y34: =IFERROR((M34-$S34)/ABS($S34),0) -> 0 | Z34: =IFERROR((M34-$S34),$M34-0) -> 0 | AC34: 0 | AD34: 0 | AE34: 0 | AF34: =IFERROR(($AC34-AD34)/ABS(AD34),0) -> 0 | AG34: =($AC34-AD34) -> 0 | AH34: =IFERROR(($AC34-AE34)/ABS(AE34),0) -> 0 | AI34: =($AC34-AE34) -> 0 | AK34: 0 | AL34: =IFERROR(AK34/SUMIFS(AK:AK, $H:$H, "[+] Net Sales"),0) -> 0 | AM34: 0 | AN34: =IFERROR(AM34/SUMIFS(AM:AM, $H:$H, "[+] Net Sales"),0) -> 0 | AO34: 0 | AP34: =IFERROR(AO34/SUMIFS(AO:AO, $H:$H, "[+] Net Sales"),0) -> 0 | AQ34: 0 | AR34: =IFERROR(AQ34/SUMIFS(AQ:AQ, $H:$H, "[+] Net Sales"),0) -> 0 | AS34: =IFERROR((AK34-$AM34)/ABS($AM34),0) -> 0 | AT34: =(AK34-$AM34) -> 0 | AU34: =IFERROR((AK34-$AO34)/ABS($AO34),0) -> 0 | AV34: =(AK34-$AO34) -> 0 | AW34: =IFERROR((AK34-$AQ34)/ABS($AQ34),0) -> 0 | AX34: =(AK34-$AQ34) -> 0 | BA34: 0 | BB34: =IFERROR(BA34/SUMIFS(BA:BA, $H:$H, "[+] Net Sales"),0) -> 0 | BC34: 0 | BD34: =IFERROR(BC34/SUMIFS(BC:BC, $H:$H, "[+] Net Sales"),0) -> 0 | BE34: 0 | BF34: =IFERROR(BE34/SUMIFS(BE:BE, $H:$H, "[+] Net Sales"),0) -> 0 | BG34: =IFERROR((BA34-$BC34)/ABS($BC34),0) -> 0 | BH34: =(BA34-$BC34) -> 0 | BI34: =IFERROR((BA34-$BE34)/ABS($BE34),0) -> 0 | BJ34: =(BA34-$BE34) -> 0
H35: [*] 3012 (Sales - Paint Samples) | N35: =IFERROR(M35/SUMIFS(M:M, $H:$H, "[+] Net Sales"),0) -> 0 | P35: =IFERROR(O35/SUMIFS(O:O, $H:$H, "[+] Net Sales"),0) -> 0 | R35: =IFERROR(Q35/SUMIFS(Q:Q, $H:$H, "[+] Net Sales"),0) -> 0 | T35: =IFERROR(S35/SUMIFS(S:S, $H:$H, "[+] Net Sales"),0) -> 0 | U35: =IFERROR(($M35-O35)/ABS(O35),0) -> 0 | V35: =IFERROR((M35-$O35), $M35-0) -> 0 | W35: =IFERROR((M35-$Q35)/ABS($Q35),0) -> 0 | X35: =IFERROR((M35-$Q35), $M35-0) -> 0 | Y35: =IFERROR((M35-$S35)/ABS($S35),0) -> 0 | Z35: =IFERROR((M35-$S35),$M35-0) -> 0 | AC35: 0 | AD35: 0 | AE35: 0 | AF35: =IFERROR(($AC35-AD35)/ABS(AD35),0) -> 0 | AG35: =($AC35-AD35) -> 0 | AH35: =IFERROR(($AC35-AE35)/ABS(AE35),0) -> 0 | AI35: =($AC35-AE35) -> 0 | AK35: 0 | AL35: =IFERROR(AK35/SUMIFS(AK:AK, $H:$H, "[+] Net Sales"),0) -> 0 | AM35: 0 | AN35: =IFERROR(AM35/SUMIFS(AM:AM, $H:$H, "[+] Net Sales"),0) -> 0 | AO35: 0 | AP35: =IFERROR(AO35/SUMIFS(AO:AO, $H:$H, "[+] Net Sales"),0) -> 0 | AQ35: 0 | AR35: =IFERROR(AQ35/SUMIFS(AQ:AQ, $H:$H, "[+] Net Sales"),0) -> 0 | AS35: =IFERROR((AK35-$AM35)/ABS($AM35),0) -> 0 | AT35: =(AK35-$AM35) -> 0 | AU35: =IFERROR((AK35-$AO35)/ABS($AO35),0) -> 0 | AV35: =(AK35-$AO35) -> 0 | AW35: =IFERROR((AK35-$AQ35)/ABS($AQ35),0) -> 0 | AX35: =(AK35-$AQ35) -> 0 | BA35: 0 | BB35: =IFERROR(BA35/SUMIFS(BA:BA, $H:$H, "[+] Net Sales"),0) -> 0 | BC35: 0 | BD35: =IFERROR(BC35/SUMIFS(BC:BC, $H:$H, "[+] Net Sales"),0) -> 0 | BE35: 0 | BF35: =IFERROR(BE35/SUMIFS(BE:BE, $H:$H, "[+] Net Sales"),0) -> 0 | BG35: =IFERROR((BA35-$BC35)/ABS($BC35),0) -> 0 | BH35: =(BA35-$BC35) -> 0 | BI35: =IFERROR((BA35-$BE35)/ABS($BE35),0) -> 0 | BJ35: =(BA35-$BE35) -> 0
H36: [*] 3013 (Sales - Paint Supplies) | N36: =IFERROR(M36/SUMIFS(M:M, $H:$H, "[+] Net Sales"),0) -> 0 | P36: =IFERROR(O36/SUMIFS(O:O, $H:$H, "[+] Net Sales"),0) -> 0 | R36: =IFERROR(Q36/SUMIFS(Q:Q, $H:$H, "[+] Net Sales"),0) -> 0 | T36: =IFERROR(S36/SUMIFS(S:S, $H:$H, "[+] Net Sales"),0) -> 0 | U36: =IFERROR(($M36-O36)/ABS(O36),0) -> 0 | V36: =IFERROR((M36-$O36), $M36-0) -> 0 | W36: =IFERROR((M36-$Q36)/ABS($Q36),0) -> 0 | X36: =IFERROR((M36-$Q36), $M36-0) -> 0 | Y36: =IFERROR((M36-$S36)/ABS($S36),0) -> 0 | Z36: =IFERROR((M36-$S36),$M36-0) -> 0 | AC36: 0 | AD36: 0 | AE36: 0 | AF36: =IFERROR(($AC36-AD36)/ABS(AD36),0) -> 0 | AG36: =($AC36-AD36) -> 0 | AH36: =IFERROR(($AC36-AE36)/ABS(AE36),0) -> 0 | AI36: =($AC36-AE36) -> 0 | AK36: 0 | AL36: =IFERROR(AK36/SUMIFS(AK:AK, $H:$H, "[+] Net Sales"),0) -> 0 | AM36: 0 | AN36: =IFERROR(AM36/SUMIFS(AM:AM, $H:$H, "[+] Net Sales"),0) -> 0 | AO36: 0 | AP36: =IFERROR(AO36/SUMIFS(AO:AO, $H:$H, "[+] Net Sales"),0) -> 0 | AQ36: 0 | AR36: =IFERROR(AQ36/SUMIFS(AQ:AQ, $H:$H, "[+] Net Sales"),0) -> 0 | AS36: =IFERROR((AK36-$AM36)/ABS($AM36),0) -> 0 | AT36: =(AK36-$AM36) -> 0 | AU36: =IFERROR((AK36-$AO36)/ABS($AO36),0) -> 0 | AV36: =(AK36-$AO36) -> 0 | AW36: =IFERROR((AK36-$AQ36)/ABS($AQ36),0) -> 0 | AX36: =(AK36-$AQ36) -> 0 | BA36: 0 | BB36: =IFERROR(BA36/SUMIFS(BA:BA, $H:$H, "[+] Net Sales"),0) -> 0 | BC36: 0 | BD36: =IFERROR(BC36/SUMIFS(BC:BC, $H:$H, "[+] Net Sales"),0) -> 0 | BE36: 0 | BF36: =IFERROR(BE36/SUMIFS(BE:BE, $H:$H, "[+] Net Sales"),0) -> 0 | BG36: =IFERROR((BA36-$BC36)/ABS($BC36),0) -> 0 | BH36: =(BA36-$BC36) -> 0 | BI36: =IFERROR((BA36-$BE36)/ABS($BE36),0) -> 0 | BJ36: =(BA36-$BE36) -> 0
H37: [*] 3014 (Sales - Wallcoverings) | N37: =IFERROR(M37/SUMIFS(M:M, $H:$H, "[+] Net Sales"),0) -> 0 | P37: =IFERROR(O37/SUMIFS(O:O, $H:$H, "[+] Net Sales"),0) -> 0 | R37: =IFERROR(Q37/SUMIFS(Q:Q, $H:$H, "[+] Net Sales"),0) -> 0 | T37: =IFERROR(S37/SUMIFS(S:S, $H:$H, "[+] Net Sales"),0) -> 0 | U37: =IFERROR(($M37-O37)/ABS(O37),0) -> 0 | V37: =IFERROR((M37-$O37), $M37-0) -> 0 | W37: =IFERROR((M37-$Q37)/ABS($Q37),0) -> 0 | X37: =IFERROR((M37-$Q37), $M37-0) -> 0 | Y37: =IFERROR((M37-$S37)/ABS($S37),0) -> 0 | Z37: =IFERROR((M37-$S37),$M37-0) -> 0 | AC37: 0 | AD37: 0 | AE37: 0 | AF37: =IFERROR(($AC37-AD37)/ABS(AD37),0) -> 0 | AG37: =($AC37-AD37) -> 0 | AH37: =IFERROR(($AC37-AE37)/ABS(AE37),0) -> 0 | AI37: =($AC37-AE37) -> 0 | AK37: 0 | AL37: =IFERROR(AK37/SUMIFS(AK:AK, $H:$H, "[+] Net Sales"),0) -> 0 | AM37: 0 | AN37: =IFERROR(AM37/SUMIFS(AM:AM, $H:$H, "[+] Net Sales"),0) -> 0 | AO37: 0 | AP37: =IFERROR(AO37/SUMIFS(AO:AO, $H:$H, "[+] Net Sales"),0) -> 0 | AQ37: 0 | AR37: =IFERROR(AQ37/SUMIFS(AQ:AQ, $H:$H, "[+] Net Sales"),0) -> 0 | AS37: =IFERROR((AK37-$AM37)/ABS($AM37),0) -> 0 | AT37: =(AK37-$AM37) -> 0 | AU37: =IFERROR((AK37-$AO37)/ABS($AO37),0) -> 0 | AV37: =(AK37-$AO37) -> 0 | AW37: =IFERROR((AK37-$AQ37)/ABS($AQ37),0) -> 0 | AX37: =(AK37-$AQ37) -> 0 | BA37: 0 | BB37: =IFERROR(BA37/SUMIFS(BA:BA, $H:$H, "[+] Net Sales"),0) -> 0 | BC37: 0 | BD37: =IFERROR(BC37/SUMIFS(BC:BC, $H:$H, "[+] Net Sales"),0) -> 0 | BE37: 0 | BF37: =IFERROR(BE37/SUMIFS(BE:BE, $H:$H, "[+] Net Sales"),0) -> 0 | BG37: =IFERROR((BA37-$BC37)/ABS($BC37),0) -> 0 | BH37: =(BA37-$BC37) -> 0 | BI37: =IFERROR((BA37-$BE37)/ABS($BE37),0) -> 0 | BJ37: =(BA37-$BE37) -> 0
H38: [*] 3015 (Sales Adjustments) | N38: =IFERROR(M38/SUMIFS(M:M, $H:$H, "[+] Net Sales"),0) -> 0 | P38: =IFERROR(O38/SUMIFS(O:O, $H:$H, "[+] Net Sales"),0) -> 0 | R38: =IFERROR(Q38/SUMIFS(Q:Q, $H:$H, "[+] Net Sales"),0) -> 0 | T38: =IFERROR(S38/SUMIFS(S:S, $H:$H, "[+] Net Sales"),0) -> 0 | U38: =IFERROR(($M38-O38)/ABS(O38),0) -> 0 | V38: =IFERROR((M38-$O38), $M38-0) -> 0 | W38: =IFERROR((M38-$Q38)/ABS($Q38),0) -> 0 | X38: =IFERROR((M38-$Q38), $M38-0) -> 0 | Y38: =IFERROR((M38-$S38)/ABS($S38),0) -> 0 | Z38: =IFERROR((M38-$S38),$M38-0) -> 0 | AC38: 0 | AD38: 0 | AE38: 0 | AF38: =IFERROR(($AC38-AD38)/ABS(AD38),0) -> 0 | AG38: =($AC38-AD38) -> 0 | AH38: =IFERROR(($AC38-AE38)/ABS(AE38),0) -> 0 | AI38: =($AC38-AE38) -> 0 | AK38: 0 | AL38: =IFERROR(AK38/SUMIFS(AK:AK, $H:$H, "[+] Net Sales"),0) -> 0 | AM38: 0 | AN38: =IFERROR(AM38/SUMIFS(AM:AM, $H:$H, "[+] Net Sales"),0) -> 0 | AO38: 0 | AP38: =IFERROR(AO38/SUMIFS(AO:AO, $H:$H, "[+] Net Sales"),0) -> 0 | AQ38: 0 | AR38: =IFERROR(AQ38/SUMIFS(AQ:AQ, $H:$H, "[+] Net Sales"),0) -> 0 | AS38: =IFERROR((AK38-$AM38)/ABS($AM38),0) -> 0 | AT38: =(AK38-$AM38) -> 0 | AU38: =IFERROR((AK38-$AO38)/ABS($AO38),0) -> 0 | AV38: =(AK38-$AO38) -> 0 | AW38: =IFERROR((AK38-$AQ38)/ABS($AQ38),0) -> 0 | AX38: =(AK38-$AQ38) -> 0 | BA38: 0 | BB38: =IFERROR(BA38/SUMIFS(BA:BA, $H:$H, "[+] Net Sales"),0) -> 0 | BC38: 0 | BD38: =IFERROR(BC38/SUMIFS(BC:BC, $H:$H, "[+] Net Sales"),0) -> 0 | BE38: 0 | BF38: =IFERROR(BE38/SUMIFS(BE:BE, $H:$H, "[+] Net Sales"),0) -> 0 | BG38: =IFERROR((BA38-$BC38)/ABS($BC38),0) -> 0 | BH38: =(BA38-$BC38) -> 0 | BI38: =IFERROR((BA38-$BE38)/ABS($BE38),0) -> 0 | BJ38: =(BA38-$BE38) -> 0
H39: [*] 3018 (Sales - Popup Showroom) | N39: =IFERROR(M39/SUMIFS(M:M, $H:$H, "[+] Net Sales"),0) -> 0 | P39: =IFERROR(O39/SUMIFS(O:O, $H:$H, "[+] Net Sales"),0) -> 0 | R39: =IFERROR(Q39/SUMIFS(Q:Q, $H:$H, "[+] Net Sales"),0) -> 0 | T39: =IFERROR(S39/SUMIFS(S:S, $H:$H, "[+] Net Sales"),0) -> 0 | U39: =IFERROR(($M39-O39)/ABS(O39),0) -> 0 | V39: =IFERROR((M39-$O39), $M39-0) -> 0 | W39: =IFERROR((M39-$Q39)/ABS($Q39),0) -> 0 | X39: =IFERROR((M39-$Q39), $M39-0) -> 0 | Y39: =IFERROR((M39-$S39)/ABS($S39),0) -> 0 | Z39: =IFERROR((M39-$S39),$M39-0) -> 0 | AC39: 0 | AD39: 0 | AE39: 0 | AF39: =IFERROR(($AC39-AD39)/ABS(AD39),0) -> 0 | AG39: =($AC39-AD39) -> 0 | AH39: =IFERROR(($AC39-AE39)/ABS(AE39),0) -> 0 | AI39: =($AC39-AE39) -> 0 | AK39: 0 | AL39: =IFERROR(AK39/SUMIFS(AK:AK, $H:$H, "[+] Net Sales"),0) -> 0 | AM39: 0 | AN39: =IFERROR(AM39/SUMIFS(AM:AM, $H:$H, "[+] Net Sales"),0) -> 0 | AO39: 0 | AP39: =IFERROR(AO39/SUMIFS(AO:AO, $H:$H, "[+] Net Sales"),0) -> 0 | AQ39: 0 | AR39: =IFERROR(AQ39/SUMIFS(AQ:AQ, $H:$H, "[+] Net Sales"),0) -> 0 | AS39: =IFERROR((AK39-$AM39)/ABS($AM39),0) -> 0 | AT39: =(AK39-$AM39) -> 0 | AU39: =IFERROR((AK39-$AO39)/ABS($AO39),0) -> 0 | AV39: =(AK39-$AO39) -> 0 | AW39: =IFERROR((AK39-$AQ39)/ABS($AQ39),0) -> 0 | AX39: =(AK39-$AQ39) -> 0 | BA39: 0 | BB39: =IFERROR(BA39/SUMIFS(BA:BA, $H:$H, "[+] Net Sales"),0) -> 0 | BC39: 0 | BD39: =IFERROR(BC39/SUMIFS(BC:BC, $H:$H, "[+] Net Sales"),0) -> 0 | BE39: 0 | BF39: =IFERROR(BE39/SUMIFS(BE:BE, $H:$H, "[+] Net Sales"),0) -> 0 | BG39: =IFERROR((BA39-$BC39)/ABS($BC39),0) -> 0 | BH39: =(BA39-$BC39) -> 0 | BI39: =IFERROR((BA39-$BE39)/ABS($BE39),0) -> 0 | BJ39: =(BA39-$BE39) -> 0
H40: [*] 3020 (Sales - 3rd Party) | N40: =IFERROR(M40/SUMIFS(M:M, $H:$H, "[+] Net Sales"),0) -> 0 | P40: =IFERROR(O40/SUMIFS(O:O, $H:$H, "[+] Net Sales"),0) -> 0 | R40: =IFERROR(Q40/SUMIFS(Q:Q, $H:$H, "[+] Net Sales"),0) -> 0 | T40: =IFERROR(S40/SUMIFS(S:S, $H:$H, "[+] Net Sales"),0) -> 0 | U40: =IFERROR(($M40-O40)/ABS(O40),0) -> 0 | V40: =IFERROR((M40-$O40), $M40-0) -> 0 | W40: =IFERROR((M40-$Q40)/ABS($Q40),0) -> 0 | X40: =IFERROR((M40-$Q40), $M40-0) -> 0 | Y40: =IFERROR((M40-$S40)/ABS($S40),0) -> 0 | Z40: =IFERROR((M40-$S40),$M40-0) -> 0 | AC40: 0 | AD40: 0 | AE40: 0 | AF40: =IFERROR(($AC40-AD40)/ABS(AD40),0) -> 0 | AG40: =($AC40-AD40) -> 0 | AH40: =IFERROR(($AC40-AE40)/ABS(AE40),0) -> 0 | AI40: =($AC40-AE40) -> 0 | AK40: 0 | AL40: =IFERROR(AK40/SUMIFS(AK:AK, $H:$H, "[+] Net Sales"),0) -> 0 | AM40: 0 | AN40: =IFERROR(AM40/SUMIFS(AM:AM, $H:$H, "[+] Net Sales"),0) -> 0 | AO40: 0 | AP40: =IFERROR(AO40/SUMIFS(AO:AO, $H:$H, "[+] Net Sales"),0) -> 0 | AQ40: 0 | AR40: =IFERROR(AQ40/SUMIFS(AQ:AQ, $H:$H, "[+] Net Sales"),0) -> 0 | AS40: =IFERROR((AK40-$AM40)/ABS($AM40),0) -> 0 | AT40: =(AK40-$AM40) -> 0 | AU40: =IFERROR((AK40-$AO40)/ABS($AO40),0) -> 0 | AV40: =(AK40-$AO40) -> 0 | AW40: =IFERROR((AK40-$AQ40)/ABS($AQ40),0) -> 0 | AX40: =(AK40-$AQ40) -> 0 | BA40: 0 | BB40: =IFERROR(BA40/SUMIFS(BA:BA, $H:$H, "[+] Net Sales"),0) -> 0 | BC40: 0 | BD40: =IFERROR(BC40/SUMIFS(BC:BC, $H:$H, "[+] Net Sales"),0) -> 0 | BE40: 0 | BF40: =IFERROR(BE40/SUMIFS(BE:BE, $H:$H, "[+] Net Sales"),0) -> 0 | BG40: =IFERROR((BA40-$BC40)/ABS($BC40),0) -> 0 | BH40: =(BA40-$BC40) -> 0 | BI40: =IFERROR((BA40-$BE40)/ABS($BE40),0) -> 0 | BJ40: =(BA40-$BE40) -> 0
H41: [*] 3021 (Sales - Subscriptions) | M41: 269359.77 | N41: =IFERROR(M41/SUMIFS(M:M, $H:$H, "[+] Net Sales"),0) -> 0.41158833 | P41: =IFERROR(O41/SUMIFS(O:O, $H:$H, "[+] Net Sales"),0) -> 0 | Q41: 189510.46 | R41: =IFERROR(Q41/SUMIFS(Q:Q, $H:$H, "[+] Net Sales"),0) -> 0.34212577 | S41: 158374.05 | T41: =IFERROR(S41/SUMIFS(S:S, $H:$H, "[+] Net Sales"),0) -> 0.31055744 | U41: =IFERROR(($M41-O41)/ABS(O41),0) -> 0 | V41: =IFERROR((M41-$O41), $M41-0) -> 269359.77 | W41: =IFERROR((M41-$Q41)/ABS($Q41),0) -> 0.42134512 | X41: =IFERROR((M41-$Q41), $M41-0) -> 79849.308 | Y41: =IFERROR((M41-$S41)/ABS($S41),0) -> 0.70078223 | Z41: =IFERROR((M41-$S41),$M41-0) -> 110985.72 | AC41: 269359.77 | AD41: 158374.05 | AE41: 189510.46 | AF41: =IFERROR(($AC41-AD41)/ABS(AD41),0) -> 0.70078223 | AG41: =($AC41-AD41) -> 110985.72 | AH41: =IFERROR(($AC41-AE41)/ABS(AE41),0) -> 0.42134512 | AI41: =($AC41-AE41) -> 79849.308 | AK41: 269359.77 | AL41: =IFERROR(AK41/SUMIFS(AK:AK, $H:$H, "[+] Net Sales"),0) -> 0.41158833 | AM41: 0 | AN41: =IFERROR(AM41/SUMIFS(AM:AM, $H:$H, "[+] Net Sales"),0) -> 0 | AO41: 189510.46 | AP41: =IFERROR(AO41/SUMIFS(AO:AO, $H:$H, "[+] Net Sales"),0) -> 0.34212577 | AQ41: 158374.05 | AR41: =IFERROR(AQ41/SUMIFS(AQ:AQ, $H:$H, "[+] Net Sales"),0) -> 0.31055744 | AS41: =IFERROR((AK41-$AM41)/ABS($AM41),0) -> 0 | AT41: =(AK41-$AM41) -> 269359.77 | AU41: =IFERROR((AK41-$AO41)/ABS($AO41),0) -> 0.42134512 | AV41: =(AK41-$AO41) -> 79849.308 | AW41: =IFERROR((AK41-$AQ41)/ABS($AQ41),0) -> 0.70078223 | AX41: =(AK41-$AQ41) -> 110985.72 | BA41: 729224 | BB41: =IFERROR(BA41/SUMIFS(BA:BA, $H:$H, "[+] Net Sales"),0) -> 0.32683055 | BC41: 729224 | BD41: =IFERROR(BC41/SUMIFS(BC:BC, $H:$H, "[+] Net Sales"),0) -> 0.32683055 | BE41: 0 | BF41: =IFERROR(BE41/SUMIFS(BE:BE, $H:$H, "[+] Net Sales"),0) -> 0 | BG41: =IFERROR((BA41-$BC41)/ABS($BC41),0) -> 0 | BH41: =(BA41-$BC41) -> 0 | BI41: =IFERROR((BA41-$BE41)/ABS($BE41),0) -> 0 | BJ41: =(BA41-$BE41) -> 729224
H42: [*] 3022 (Sales - Advertising) | M42: 384340 | N42: =IFERROR(M42/SUMIFS(M:M, $H:$H, "[+] Net Sales"),0) -> 0.58728093 | P42: =IFERROR(O42/SUMIFS(O:O, $H:$H, "[+] Net Sales"),0) -> 0 | Q42: 342772.32 | R42: =IFERROR(Q42/SUMIFS(Q:Q, $H:$H, "[+] Net Sales"),0) -> 0.61881146 | S42: 339190 | T42: =IFERROR(S42/SUMIFS(S:S, $H:$H, "[+] Net Sales"),0) -> 0.66512146 | U42: =IFERROR(($M42-O42)/ABS(O42),0) -> 0 | V42: =IFERROR((M42-$O42), $M42-0) -> 384340 | W42: =IFERROR((M42-$Q42)/ABS($Q42),0) -> 0.12126907 | X42: =IFERROR((M42-$Q42), $M42-0) -> 41567.68 | Y42: =IFERROR((M42-$S42)/ABS($S42),0) -> 0.13311124 | Z42: =IFERROR((M42-$S42),$M42-0) -> 45150 | AC42: 384340 | AD42: 339190 | AE42: 342772.32 | AF42: =IFERROR(($AC42-AD42)/ABS(AD42),0) -> 0.13311124 | AG42: =($AC42-AD42) -> 45150 | AH42: =IFERROR(($AC42-AE42)/ABS(AE42),0) -> 0.12126907 | AI42: =($AC42-AE42) -> 41567.68 | AK42: 384340 | AL42: =IFERROR(AK42/SUMIFS(AK:AK, $H:$H, "[+] Net Sales"),0) -> 0.58728093 | AM42: 0 | AN42: =IFERROR(AM42/SUMIFS(AM:AM, $H:$H, "[+] Net Sales"),0) -> 0 | AO42: 342772.32 | AP42: =IFERROR(AO42/SUMIFS(AO:AO, $H:$H, "[+] Net Sales"),0) -> 0.61881146 | AQ42: 339190 | AR42: =IFERROR(AQ42/SUMIFS(AQ:AQ, $H:$H, "[+] Net Sales"),0) -> 0.66512146 | AS42: =IFERROR((AK42-$AM42)/ABS($AM42),0) -> 0 | AT42: =(AK42-$AM42) -> 384340 | AU42: =IFERROR((AK42-$AO42)/ABS($AO42),0) -> 0.12126907 | AV42: =(AK42-$AO42) -> 41567.68 | AW42: =IFERROR((AK42-$AQ42)/ABS($AQ42),0) -> 0.13311124 | AX42: =(AK42-$AQ42) -> 45150 | BA42: 1415475 | BB42: =IFERROR(BA42/SUMIFS(BA:BA, $H:$H, "[+] Net Sales"),0) -> 0.63440106 | BC42: 1415475 | BD42: =IFERROR(BC42/SUMIFS(BC:BC, $H:$H, "[+] Net Sales"),0) -> 0.63440106 | BE42: 0 | BF42: =IFERROR(BE42/SUMIFS(BE:BE, $H:$H, "[+] Net Sales"),0) -> 0 | BG42: =IFERROR((BA42-$BC42)/ABS($BC42),0) -> 0 | BH42: =(BA42-$BC42) -> 0 | BI42: =IFERROR((BA42-$BE42)/ABS($BE42),0) -> 0 | BJ42: =(BA42-$BE42) -> 1415475
H43: [*] 3023 (Sales - Media) | M43: 720 | N43: =IFERROR(M43/SUMIFS(M:M, $H:$H, "[+] Net Sales"),0) -> 0.0011001776 | P43: =IFERROR(O43/SUMIFS(O:O, $H:$H, "[+] Net Sales"),0) -> 0 | Q43: 21637.667 | R43: =IFERROR(Q43/SUMIFS(Q:Q, $H:$H, "[+] Net Sales"),0) -> 0.039062769 | S43: 12402.96 | T43: =IFERROR(S43/SUMIFS(S:S, $H:$H, "[+] Net Sales"),0) -> 0.024321103 | U43: =IFERROR(($M43-O43)/ABS(O43),0) -> 0 | V43: =IFERROR((M43-$O43), $M43-0) -> 720 | W43: =IFERROR((M43-$Q43)/ABS($Q43),0) -> -0.96672469 | X43: =IFERROR((M43-$Q43), $M43-0) -> -20917.667 | Y43: =IFERROR((M43-$S43)/ABS($S43),0) -> -0.94194934 | Z43: =IFERROR((M43-$S43),$M43-0) -> -11682.96 | AC43: 720 | AD43: 12402.96 | AE43: 21637.667 | AF43: =IFERROR(($AC43-AD43)/ABS(AD43),0) -> -0.94194934 | AG43: =($AC43-AD43) -> -11682.96 | AH43: =IFERROR(($AC43-AE43)/ABS(AE43),0) -> -0.96672469 | AI43: =($AC43-AE43) -> -20917.667 | AK43: 720 | AL43: =IFERROR(AK43/SUMIFS(AK:AK, $H:$H, "[+] Net Sales"),0) -> 0.0011001776 | AM43: 0 | AN43: =IFERROR(AM43/SUMIFS(AM:AM, $H:$H, "[+] Net Sales"),0) -> 0 | AO43: 21637.667 | AP43: =IFERROR(AO43/SUMIFS(AO:AO, $H:$H, "[+] Net Sales"),0) -> 0.039062769 | AQ43: 12402.96 | AR43: =IFERROR(AQ43/SUMIFS(AQ:AQ, $H:$H, "[+] Net Sales"),0) -> 0.024321103 | AS43: =IFERROR((AK43-$AM43)/ABS($AM43),0) -> 0 | AT43: =(AK43-$AM43) -> 720 | AU43: =IFERROR((AK43-$AO43)/ABS($AO43),0) -> -0.96672469 | AV43: =(AK43-$AO43) -> -20917.667 | AW43: =IFERROR((AK43-$AQ43)/ABS($AQ43),0) -> -0.94194934 | AX43: =(AK43-$AQ43) -> -11682.96 | BA43: 86500 | BB43: =IFERROR(BA43/SUMIFS(BA:BA, $H:$H, "[+] Net Sales"),0) -> 0.038768393 | BC43: 86500 | BD43: =IFERROR(BC43/SUMIFS(BC:BC, $H:$H, "[+] Net Sales"),0) -> 0.038768393 | BE43: 0 | BF43: =IFERROR(BE43/SUMIFS(BE:BE, $H:$H, "[+] Net Sales"),0) -> 0 | BG43: =IFERROR((BA43-$BC43)/ABS($BC43),0) -> 0 | BH43: =(BA43-$BC43) -> 0 | BI43: =IFERROR((BA43-$BE43)/ABS($BE43),0) -> 0 | BJ43: =(BA43-$BE43) -> 86500
H44: [*] 3025 (Sales - Intercompany) | N44: =IFERROR(M44/SUMIFS(M:M, $H:$H, "[+] Net Sales"),0) -> 0 | P44: =IFERROR(O44/SUMIFS(O:O, $H:$H, "[+] Net Sales"),0) -> 0 | R44: =IFERROR(Q44/SUMIFS(Q:Q, $H:$H, "[+] Net Sales"),0) -> 0 | T44: =IFERROR(S44/SUMIFS(S:S, $H:$H, "[+] Net Sales"),0) -> 0 | U44: =IFERROR(($M44-O44)/ABS(O44),0) -> 0 | V44: =IFERROR((M44-$O44), $M44-0) -> 0 | W44: =IFERROR((M44-$Q44)/ABS($Q44),0) -> 0 | X44: =IFERROR((M44-$Q44), $M44-0) -> 0 | Y44: =IFERROR((M44-$S44)/ABS($S44),0) -> 0 | Z44: =IFERROR((M44-$S44),$M44-0) -> 0 | AC44: 0 | AD44: 0 | AE44: 0 | AF44: =IFERROR(($AC44-AD44)/ABS(AD44),0) -> 0 | AG44: =($AC44-AD44) -> 0 | AH44: =IFERROR(($AC44-AE44)/ABS(AE44),0) -> 0 | AI44: =($AC44-AE44) -> 0 | AK44: 0 | AL44: =IFERROR(AK44/SUMIFS(AK:AK, $H:$H, "[+] Net Sales"),0) -> 0 | AM44: 0 | AN44: =IFERROR(AM44/SUMIFS(AM:AM, $H:$H, "[+] Net Sales"),0) -> 0 | AO44: 0 | AP44: =IFERROR(AO44/SUMIFS(AO:AO, $H:$H, "[+] Net Sales"),0) -> 0 | AQ44: 0 | AR44: =IFERROR(AQ44/SUMIFS(AQ:AQ, $H:$H, "[+] Net Sales"),0) -> 0 | AS44: =IFERROR((AK44-$AM44)/ABS($AM44),0) -> 0 | AT44: =(AK44-$AM44) -> 0 | AU44: =IFERROR((AK44-$AO44)/ABS($AO44),0) -> 0 | AV44: =(AK44-$AO44) -> 0 | AW44: =IFERROR((AK44-$AQ44)/ABS($AQ44),0) -> 0 | AX44: =(AK44-$AQ44) -> 0 | BA44: 0 | BB44: =IFERROR(BA44/SUMIFS(BA:BA, $H:$H, "[+] Net Sales"),0) -> 0 | BC44: 0 | BD44: =IFERROR(BC44/SUMIFS(BC:BC, $H:$H, "[+] Net Sales"),0) -> 0 | BE44: 0 | BF44: =IFERROR(BE44/SUMIFS(BE:BE, $H:$H, "[+] Net Sales"),0) -> 0 | BG44: =IFERROR((BA44-$BC44)/ABS($BC44),0) -> 0 | BH44: =(BA44-$BC44) -> 0 | BI44: =IFERROR((BA44-$BE44)/ABS($BE44),0) -> 0 | BJ44: =(BA44-$BE44) -> 0
H45: [*] 3050 (Returns - Regular) | N45: =IFERROR(M45/SUMIFS(M:M, $H:$H, "[+] Net Sales"),0) -> 0 | P45: =IFERROR(O45/SUMIFS(O:O, $H:$H, "[+] Net Sales"),0) -> 0 | R45: =IFERROR(Q45/SUMIFS(Q:Q, $H:$H, "[+] Net Sales"),0) -> 0 | T45: =IFERROR(S45/SUMIFS(S:S, $H:$H, "[+] Net Sales"),0) -> 0 | U45: =IFERROR(($M45-O45)/ABS(O45),0) -> 0 | V45: =IFERROR((M45-$O45), $M45-0) -> 0 | W45: =IFERROR((M45-$Q45)/ABS($Q45),0) -> 0 | X45: =IFERROR((M45-$Q45), $M45-0) -> 0 | Y45: =IFERROR((M45-$S45)/ABS($S45),0) -> 0 | Z45: =IFERROR((M45-$S45),$M45-0) -> 0 | AC45: 0 | AD45: 0 | AE45: 0 | AF45: =IFERROR(($AC45-AD45)/ABS(AD45),0) -> 0 | AG45: =($AC45-AD45) -> 0 | AH45: =IFERROR(($AC45-AE45)/ABS(AE45),0) -> 0 | AI45: =($AC45-AE45) -> 0 | AK45: 0 | AL45: =IFERROR(AK45/SUMIFS(AK:AK, $H:$H, "[+] Net Sales"),0) -> 0 | AM45: 0 | AN45: =IFERROR(AM45/SUMIFS(AM:AM, $H:$H, "[+] Net Sales"),0) -> 0 | AO45: 0 | AP45: =IFERROR(AO45/SUMIFS(AO:AO, $H:$H, "[+] Net Sales"),0) -> 0 | AQ45: 0 | AR45: =IFERROR(AQ45/SUMIFS(AQ:AQ, $H:$H, "[+] Net Sales"),0) -> 0 | AS45: =IFERROR((AK45-$AM45)/ABS($AM45),0) -> 0 | AT45: =(AK45-$AM45) -> 0 | AU45: =IFERROR((AK45-$AO45)/ABS($AO45),0) -> 0 | AV45: =(AK45-$AO45) -> 0 | AW45: =IFERROR((AK45-$AQ45)/ABS($AQ45),0) -> 0 | AX45: =(AK45-$AQ45) -> 0 | BA45: 0 | BB45: =IFERROR(BA45/SUMIFS(BA:BA, $H:$H, "[+] Net Sales"),0) -> 0 | BC45: 0 | BD45: =IFERROR(BC45/SUMIFS(BC:BC, $H:$H, "[+] Net Sales"),0) -> 0 | BE45: -21 | BF45: =IFERROR(BE45/SUMIFS(BE:BE, $H:$H, "[+] Net Sales"),0) -> -1.0454904e-05 | BG45: =IFERROR((BA45-$BC45)/ABS($BC45),0) -> 0 | BH45: =(BA45-$BC45) -> 0 | BI45: =IFERROR((BA45-$BE45)/ABS($BE45),0) -> 1 | BJ45: =(BA45-$BE45) -> 21
H46: [*] 3051 (Returns - Trim) | N46: =IFERROR(M46/SUMIFS(M:M, $H:$H, "[+] Net Sales"),0) -> 0 | P46: =IFERROR(O46/SUMIFS(O:O, $H:$H, "[+] Net Sales"),0) -> 0 | R46: =IFERROR(Q46/SUMIFS(Q:Q, $H:$H, "[+] Net Sales"),0) -> 0 | T46: =IFERROR(S46/SUMIFS(S:S, $H:$H, "[+] Net Sales"),0) -> 0 | U46: =IFERROR(($M46-O46)/ABS(O46),0) -> 0 | V46: =IFERROR((M46-$O46), $M46-0) -> 0 | W46: =IFERROR((M46-$Q46)/ABS($Q46),0) -> 0 | X46: =IFERROR((M46-$Q46), $M46-0) -> 0 | Y46: =IFERROR((M46-$S46)/ABS($S46),0) -> 0 | Z46: =IFERROR((M46-$S46),$M46-0) -> 0 | AC46: 0 | AD46: 0 | AE46: 0 | AF46: =IFERROR(($AC46-AD46)/ABS(AD46),0) -> 0 | AG46: =($AC46-AD46) -> 0 | AH46: =IFERROR(($AC46-AE46)/ABS(AE46),0) -> 0 | AI46: =($AC46-AE46) -> 0 | AK46: 0 | AL46: =IFERROR(AK46/SUMIFS(AK:AK, $H:$H, "[+] Net Sales"),0) -> 0 | AM46: 0 | AN46: =IFERROR(AM46/SUMIFS(AM:AM, $H:$H, "[+] Net Sales"),0) -> 0 | AO46: 0 | AP46: =IFERROR(AO46/SUMIFS(AO:AO, $H:$H, "[+] Net Sales"),0) -> 0 | AQ46: 0 | AR46: =IFERROR(AQ46/SUMIFS(AQ:AQ, $H:$H, "[+] Net Sales"),0) -> 0 | AS46: =IFERROR((AK46-$AM46)/ABS($AM46),0) -> 0 | AT46: =(AK46-$AM46) -> 0 | AU46: =IFERROR((AK46-$AO46)/ABS($AO46),0) -> 0 | AV46: =(AK46-$AO46) -> 0 | AW46: =IFERROR((AK46-$AQ46)/ABS($AQ46),0) -> 0 | AX46: =(AK46-$AQ46) -> 0 | BA46: 0 | BB46: =IFERROR(BA46/SUMIFS(BA:BA, $H:$H, "[+] Net Sales"),0) -> 0 | BC46: 0 | BD46: =IFERROR(BC46/SUMIFS(BC:BC, $H:$H, "[+] Net Sales"),0) -> 0 | BE46: 0 | BF46: =IFERROR(BE46/SUMIFS(BE:BE, $H:$H, "[+] Net Sales"),0) -> 0 | BG46: =IFERROR((BA46-$BC46)/ABS($BC46),0) -> 0 | BH46: =(BA46-$BC46) -> 0 | BI46: =IFERROR((BA46-$BE46)/ABS($BE46),0) -> 0 | BJ46: =(BA46-$BE46) -> 0
H47: [*] 3052 (Allowances) | N47: =IFERROR(M47/SUMIFS(M:M, $H:$H, "[+] Net Sales"),0) -> 0 | P47: =IFERROR(O47/SUMIFS(O:O, $H:$H, "[+] Net Sales"),0) -> 0 | R47: =IFERROR(Q47/SUMIFS(Q:Q, $H:$H, "[+] Net Sales"),0) -> 0 | T47: =IFERROR(S47/SUMIFS(S:S, $H:$H, "[+] Net Sales"),0) -> 0 | U47: =IFERROR(($M47-O47)/ABS(O47),0) -> 0 | V47: =IFERROR((M47-$O47), $M47-0) -> 0 | W47: =IFERROR((M47-$Q47)/ABS($Q47),0) -> 0 | X47: =IFERROR((M47-$Q47), $M47-0) -> 0 | Y47: =IFERROR((M47-$S47)/ABS($S47),0) -> 0 | Z47: =IFERROR((M47-$S47),$M47-0) -> 0 | AC47: 0 | AD47: 0 | AE47: 0 | AF47: =IFERROR(($AC47-AD47)/ABS(AD47),0) -> 0 | AG47: =($AC47-AD47) -> 0 | AH47: =IFERROR(($AC47-AE47)/ABS(AE47),0) -> 0 | AI47: =($AC47-AE47) -> 0 | AK47: 0 | AL47: =IFERROR(AK47/SUMIFS(AK:AK, $H:$H, "[+] Net Sales"),0) -> 0 | AM47: 0 | AN47: =IFERROR(AM47/SUMIFS(AM:AM, $H:$H, "[+] Net Sales"),0) -> 0 | AO47: 0 | AP47: =IFERROR(AO47/SUMIFS(AO:AO, $H:$H, "[+] Net Sales"),0) -> 0 | AQ47: 0 | AR47: =IFERROR(AQ47/SUMIFS(AQ:AQ, $H:$H, "[+] Net Sales"),0) -> 0 | AS47: =IFERROR((AK47-$AM47)/ABS($AM47),0) -> 0 | AT47: =(AK47-$AM47) -> 0 | AU47: =IFERROR((AK47-$AO47)/ABS($AO47),0) -> 0 | AV47: =(AK47-$AO47) -> 0 | AW47: =IFERROR((AK47-$AQ47)/ABS($AQ47),0) -> 0 | AX47: =(AK47-$AQ47) -> 0 | BA47: 0 | BB47: =IFERROR(BA47/SUMIFS(BA:BA, $H:$H, "[+] Net Sales"),0) -> 0 | BC47: 0 | BD47: =IFERROR(BC47/SUMIFS(BC:BC, $H:$H, "[+] Net Sales"),0) -> 0 | BE47: 0 | BF47: =IFERROR(BE47/SUMIFS(BE:BE, $H:$H, "[+] Net Sales"),0) -> 0 | BG47: =IFERROR((BA47-$BC47)/ABS($BC47),0) -> 0 | BH47: =(BA47-$BC47) -> 0 | BI47: =IFERROR((BA47-$BE47)/ABS($BE47),0) -> 0 | BJ47: =(BA47-$BE47) -> 0
H48: [*] 3053 (Allowances - Trim) | N48: =IFERROR(M48/SUMIFS(M:M, $H:$H, "[+] Net Sales"),0) -> 0 | P48: =IFERROR(O48/SUMIFS(O:O, $H:$H, "[+] Net Sales"),0) -> 0 | R48: =IFERROR(Q48/SUMIFS(Q:Q, $H:$H, "[+] Net Sales"),0) -> 0 | T48: =IFERROR(S48/SUMIFS(S:S, $H:$H, "[+] Net Sales"),0) -> 0 | U48: =IFERROR(($M48-O48)/ABS(O48),0) -> 0 | V48: =IFERROR((M48-$O48), $M48-0) -> 0 | W48: =IFERROR((M48-$Q48)/ABS($Q48),0) -> 0 | X48: =IFERROR((M48-$Q48), $M48-0) -> 0 | Y48: =IFERROR((M48-$S48)/ABS($S48),0) -> 0 | Z48: =IFERROR((M48-$S48),$M48-0) -> 0 | AC48: 0 | AD48: 0 | AE48: 0 | AF48: =IFERROR(($AC48-AD48)/ABS(AD48),0) -> 0 | AG48: =($AC48-AD48) -> 0 | AH48: =IFERROR(($AC48-AE48)/ABS(AE48),0) -> 0 | AI48: =($AC48-AE48) -> 0 | AK48: 0 | AL48: =IFERROR(AK48/SUMIFS(AK:AK, $H:$H, "[+] Net Sales"),0) -> 0 | AM48: 0 | AN48: =IFERROR(AM48/SUMIFS(AM:AM, $H:$H, "[+] Net Sales"),0) -> 0 | AO48: 0 | AP48: =IFERROR(AO48/SUMIFS(AO:AO, $H:$H, "[+] Net Sales"),0) -> 0 | AQ48: 0 | AR48: =IFERROR(AQ48/SUMIFS(AQ:AQ, $H:$H, "[+] Net Sales"),0) -> 0 | AS48: =IFERROR((AK48-$AM48)/ABS($AM48),0) -> 0 | AT48: =(AK48-$AM48) -> 0 | AU48: =IFERROR((AK48-$AO48)/ABS($AO48),0) -> 0 | AV48: =(AK48-$AO48) -> 0 | AW48: =IFERROR((AK48-$AQ48)/ABS($AQ48),0) -> 0 | AX48: =(AK48-$AQ48) -> 0 | BA48: 0 | BB48: =IFERROR(BA48/SUMIFS(BA:BA, $H:$H, "[+] Net Sales"),0) -> 0 | BC48: 0 | BD48: =IFERROR(BC48/SUMIFS(BC:BC, $H:$H, "[+] Net Sales"),0) -> 0 | BE48: 0 | BF48: =IFERROR(BE48/SUMIFS(BE:BE, $H:$H, "[+] Net Sales"),0) -> 0 | BG48: =IFERROR((BA48-$BC48)/ABS($BC48),0) -> 0 | BH48: =(BA48-$BC48) -> 0 | BI48: =IFERROR((BA48-$BE48)/ABS($BE48),0) -> 0 | BJ48: =(BA48-$BE48) -> 0
H49: [*] 3200 (Sales - Samples) | N49: =IFERROR(M49/SUMIFS(M:M, $H:$H, "[+] Net Sales"),0) -> 0 | P49: =IFERROR(O49/SUMIFS(O:O, $H:$H, "[+] Net Sales"),0) -> 0 | R49: =IFERROR(Q49/SUMIFS(Q:Q, $H:$H, "[+] Net Sales"),0) -> 0 | T49: =IFERROR(S49/SUMIFS(S:S, $H:$H, "[+] Net Sales"),0) -> 0 | U49: =IFERROR(($M49-O49)/ABS(O49),0) -> 0 | V49: =IFERROR((M49-$O49), $M49-0) -> 0 | W49: =IFERROR((M49-$Q49)/ABS($Q49),0) -> 0 | X49: =IFERROR((M49-$Q49), $M49-0) -> 0 | Y49: =IFERROR((M49-$S49)/ABS($S49),0) -> 0 | Z49: =IFERROR((M49-$S49),$M49-0) -> 0 | AC49: 0 | AD49: 0 | AE49: 0 | AF49: =IFERROR(($AC49-AD49)/ABS(AD49),0) -> 0 | AG49: =($AC49-AD49) -> 0 | AH49: =IFERROR(($AC49-AE49)/ABS(AE49),0) -> 0 | AI49: =($AC49-AE49) -> 0 | AK49: 0 | AL49: =IFERROR(AK49/SUMIFS(AK:AK, $H:$H, "[+] Net Sales"),0) -> 0 | AM49: 0 | AN49: =IFERROR(AM49/SUMIFS(AM:AM, $H:$H, "[+] Net Sales"),0) -> 0 | AO49: 0 | AP49: =IFERROR(AO49/SUMIFS(AO:AO, $H:$H, "[+] Net Sales"),0) -> 0 | AQ49: 0 | AR49: =IFERROR(AQ49/SUMIFS(AQ:AQ, $H:$H, "[+] Net Sales"),0) -> 0 | AS49: =IFERROR((AK49-$AM49)/ABS($AM49),0) -> 0 | AT49: =(AK49-$AM49) -> 0 | AU49: =IFERROR((AK49-$AO49)/ABS($AO49),0) -> 0 | AV49: =(AK49-$AO49) -> 0 | AW49: =IFERROR((AK49-$AQ49)/ABS($AQ49),0) -> 0 | AX49: =(AK49-$AQ49) -> 0 | BA49: 0 | BB49: =IFERROR(BA49/SUMIFS(BA:BA, $H:$H, "[+] Net Sales"),0) -> 0 | BC49: 0 | BD49: =IFERROR(BC49/SUMIFS(BC:BC, $H:$H, "[+] Net Sales"),0) -> 0 | BE49: 0 | BF49: =IFERROR(BE49/SUMIFS(BE:BE, $H:$H, "[+] Net Sales"),0) -> 0 | BG49: =IFERROR((BA49-$BC49)/ABS($BC49),0) -> 0 | BH49: =(BA49-$BC49) -> 0 | BI49: =IFERROR((BA49-$BE49)/ABS($BE49),0) -> 0 | BJ49: =(BA49-$BE49) -> 0
H50: [*] 3250 (Returns & Allowances - Samples) | N50: =IFERROR(M50/SUMIFS(M:M, $H:$H, "[+] Net Sales"),0) -> 0 | P50: =IFERROR(O50/SUMIFS(O:O, $H:$H, "[+] Net Sales"),0) -> 0 | R50: =IFERROR(Q50/SUMIFS(Q:Q, $H:$H, "[+] Net Sales"),0) -> 0 | T50: =IFERROR(S50/SUMIFS(S:S, $H:$H, "[+] Net Sales"),0) -> 0 | U50: =IFERROR(($M50-O50)/ABS(O50),0) -> 0 | V50: =IFERROR((M50-$O50), $M50-0) -> 0 | W50: =IFERROR((M50-$Q50)/ABS($Q50),0) -> 0 | X50: =IFERROR((M50-$Q50), $M50-0) -> 0 | Y50: =IFERROR((M50-$S50)/ABS($S50),0) -> 0 | Z50: =IFERROR((M50-$S50),$M50-0) -> 0 | AC50: 0 | AD50: 0 | AE50: 0 | AF50: =IFERROR(($AC50-AD50)/ABS(AD50),0) -> 0 | AG50: =($AC50-AD50) -> 0 | AH50: =IFERROR(($AC50-AE50)/ABS(AE50),0) -> 0 | AI50: =($AC50-AE50) -> 0 | AK50: 0 | AL50: =IFERROR(AK50/SUMIFS(AK:AK, $H:$H, "[+] Net Sales"),0) -> 0 | AM50: 0 | AN50: =IFERROR(AM50/SUMIFS(AM:AM, $H:$H, "[+] Net Sales"),0) -> 0 | AO50: 0 | AP50: =IFERROR(AO50/SUMIFS(AO:AO, $H:$H, "[+] Net Sales"),0) -> 0 | AQ50: 0 | AR50: =IFERROR(AQ50/SUMIFS(AQ:AQ, $H:$H, "[+] Net Sales"),0) -> 0 | AS50: =IFERROR((AK50-$AM50)/ABS($AM50),0) -> 0 | AT50: =(AK50-$AM50) -> 0 | AU50: =IFERROR((AK50-$AO50)/ABS($AO50),0) -> 0 | AV50: =(AK50-$AO50) -> 0 | AW50: =IFERROR((AK50-$AQ50)/ABS($AQ50),0) -> 0 | AX50: =(AK50-$AQ50) -> 0 | BA50: 0 | BB50: =IFERROR(BA50/SUMIFS(BA:BA, $H:$H, "[+] Net Sales"),0) -> 0 | BC50: 0 | BD50: =IFERROR(BC50/SUMIFS(BC:BC, $H:$H, "[+] Net Sales"),0) -> 0 | BE50: 0 | BF50: =IFERROR(BE50/SUMIFS(BE:BE, $H:$H, "[+] Net Sales"),0) -> 0 | BG50: =IFERROR((BA50-$BC50)/ABS($BC50),0) -> 0 | BH50: =(BA50-$BC50) -> 0 | BI50: =IFERROR((BA50-$BE50)/ABS($BE50),0) -> 0 | BJ50: =(BA50-$BE50) -> 0
H51: [*] 3550 (Returns & Allowances Reserve) | N51: =IFERROR(M51/SUMIFS(M:M, $H:$H, "[+] Net Sales"),0) -> 0 | P51: =IFERROR(O51/SUMIFS(O:O, $H:$H, "[+] Net Sales"),0) -> 0 | R51: =IFERROR(Q51/SUMIFS(Q:Q, $H:$H, "[+] Net Sales"),0) -> 0 | T51: =IFERROR(S51/SUMIFS(S:S, $H:$H, "[+] Net Sales"),0) -> 0 | U51: =IFERROR(($M51-O51)/ABS(O51),0) -> 0 | V51: =IFERROR((M51-$O51), $M51-0) -> 0 | W51: =IFERROR((M51-$Q51)/ABS($Q51),0) -> 0 | X51: =IFERROR((M51-$Q51), $M51-0) -> 0 | Y51: =IFERROR((M51-$S51)/ABS($S51),0) -> 0 | Z51: =IFERROR((M51-$S51),$M51-0) -> 0 | AC51: 0 | AD51: 0 | AE51: 0 | AF51: =IFERROR(($AC51-AD51)/ABS(AD51),0) -> 0 | AG51: =($AC51-AD51) -> 0 | AH51: =IFERROR(($AC51-AE51)/ABS(AE51),0) -> 0 | AI51: =($AC51-AE51) -> 0 | AK51: 0 | AL51: =IFERROR(AK51/SUMIFS(AK:AK, $H:$H, "[+] Net Sales"),0) -> 0 | AM51: 0 | AN51: =IFERROR(AM51/SUMIFS(AM:AM, $H:$H, "[+] Net Sales"),0) -> 0 | AO51: 0 | AP51: =IFERROR(AO51/SUMIFS(AO:AO, $H:$H, "[+] Net Sales"),0) -> 0 | AQ51: 0 | AR51: =IFERROR(AQ51/SUMIFS(AQ:AQ, $H:$H, "[+] Net Sales"),0) -> 0 | AS51: =IFERROR((AK51-$AM51)/ABS($AM51),0) -> 0 | AT51: =(AK51-$AM51) -> 0 | AU51: =IFERROR((AK51-$AO51)/ABS($AO51),0) -> 0 | AV51: =(AK51-$AO51) -> 0 | AW51: =IFERROR((AK51-$AQ51)/ABS($AQ51),0) -> 0 | AX51: =(AK51-$AQ51) -> 0 | BA51: 0 | BB51: =IFERROR(BA51/SUMIFS(BA:BA, $H:$H, "[+] Net Sales"),0) -> 0 | BC51: 0 | BD51: =IFERROR(BC51/SUMIFS(BC:BC, $H:$H, "[+] Net Sales"),0) -> 0 | BE51: 0 | BF51: =IFERROR(BE51/SUMIFS(BE:BE, $H:$H, "[+] Net Sales"),0) -> 0 | BG51: =IFERROR((BA51-$BC51)/ABS($BC51),0) -> 0 | BH51: =(BA51-$BC51) -> 0 | BI51: =IFERROR((BA51-$BE51)/ABS($BE51),0) -> 0 | BJ51: =(BA51-$BE51) -> 0
H52: [*] 3610 (Discounts) | N52: =IFERROR(M52/SUMIFS(M:M, $H:$H, "[+] Net Sales"),0) -> 0 | P52: =IFERROR(O52/SUMIFS(O:O, $H:$H, "[+] Net Sales"),0) -> 0 | R52: =IFERROR(Q52/SUMIFS(Q:Q, $H:$H, "[+] Net Sales"),0) -> 0 | T52: =IFERROR(S52/SUMIFS(S:S, $H:$H, "[+] Net Sales"),0) -> 0 | U52: =IFERROR(($M52-O52)/ABS(O52),0) -> 0 | V52: =IFERROR((M52-$O52), $M52-0) -> 0 | W52: =IFERROR((M52-$Q52)/ABS($Q52),0) -> 0 | X52: =IFERROR((M52-$Q52), $M52-0) -> 0 | Y52: =IFERROR((M52-$S52)/ABS($S52),0) -> 0 | Z52: =IFERROR((M52-$S52),$M52-0) -> 0 | AC52: 0 | AD52: 0 | AE52: 0 | AF52: =IFERROR(($AC52-AD52)/ABS(AD52),0) -> 0 | AG52: =($AC52-AD52) -> 0 | AH52: =IFERROR(($AC52-AE52)/ABS(AE52),0) -> 0 | AI52: =($AC52-AE52) -> 0 | AK52: 0 | AL52: =IFERROR(AK52/SUMIFS(AK:AK, $H:$H, "[+] Net Sales"),0) -> 0 | AM52: 0 | AN52: =IFERROR(AM52/SUMIFS(AM:AM, $H:$H, "[+] Net Sales"),0) -> 0 | AO52: 0 | AP52: =IFERROR(AO52/SUMIFS(AO:AO, $H:$H, "[+] Net Sales"),0) -> 0 | AQ52: 0 | AR52: =IFERROR(AQ52/SUMIFS(AQ:AQ, $H:$H, "[+] Net Sales"),0) -> 0 | AS52: =IFERROR((AK52-$AM52)/ABS($AM52),0) -> 0 | AT52: =(AK52-$AM52) -> 0 | AU52: =IFERROR((AK52-$AO52)/ABS($AO52),0) -> 0 | AV52: =(AK52-$AO52) -> 0 | AW52: =IFERROR((AK52-$AQ52)/ABS($AQ52),0) -> 0 | AX52: =(AK52-$AQ52) -> 0 | BA52: 0 | BB52: =IFERROR(BA52/SUMIFS(BA:BA, $H:$H, "[+] Net Sales"),0) -> 0 | BC52: 0 | BD52: =IFERROR(BC52/SUMIFS(BC:BC, $H:$H, "[+] Net Sales"),0) -> 0 | BE52: 0 | BF52: =IFERROR(BE52/SUMIFS(BE:BE, $H:$H, "[+] Net Sales"),0) -> 0 | BG52: =IFERROR((BA52-$BC52)/ABS($BC52),0) -> 0 | BH52: =(BA52-$BC52) -> 0 | BI52: =IFERROR((BA52-$BE52)/ABS($BE52),0) -> 0 | BJ52: =(BA52-$BE52) -> 0
H53: [*] 3611 (Discounts - Trim) | N53: =IFERROR(M53/SUMIFS(M:M, $H:$H, "[+] Net Sales"),0) -> 0 | P53: =IFERROR(O53/SUMIFS(O:O, $H:$H, "[+] Net Sales"),0) -> 0 | R53: =IFERROR(Q53/SUMIFS(Q:Q, $H:$H, "[+] Net Sales"),0) -> 0 | T53: =IFERROR(S53/SUMIFS(S:S, $H:$H, "[+] Net Sales"),0) -> 0 | U53: =IFERROR(($M53-O53)/ABS(O53),0) -> 0 | V53: =IFERROR((M53-$O53), $M53-0) -> 0 | W53: =IFERROR((M53-$Q53)/ABS($Q53),0) -> 0 | X53: =IFERROR((M53-$Q53), $M53-0) -> 0 | Y53: =IFERROR((M53-$S53)/ABS($S53),0) -> 0 | Z53: =IFERROR((M53-$S53),$M53-0) -> 0 | AC53: 0 | AD53: 0 | AE53: 0 | AF53: =IFERROR(($AC53-AD53)/ABS(AD53),0) -> 0 | AG53: =($AC53-AD53) -> 0 | AH53: =IFERROR(($AC53-AE53)/ABS(AE53),0) -> 0 | AI53: =($AC53-AE53) -> 0 | AK53: 0 | AL53: =IFERROR(AK53/SUMIFS(AK:AK, $H:$H, "[+] Net Sales"),0) -> 0 | AM53: 0 | AN53: =IFERROR(AM53/SUMIFS(AM:AM, $H:$H, "[+] Net Sales"),0) -> 0 | AO53: 0 | AP53: =IFERROR(AO53/SUMIFS(AO:AO, $H:$H, "[+] Net Sales"),0) -> 0 | AQ53: 0 | AR53: =IFERROR(AQ53/SUMIFS(AQ:AQ, $H:$H, "[+] Net Sales"),0) -> 0 | AS53: =IFERROR((AK53-$AM53)/ABS($AM53),0) -> 0 | AT53: =(AK53-$AM53) -> 0 | AU53: =IFERROR((AK53-$AO53)/ABS($AO53),0) -> 0 | AV53: =(AK53-$AO53) -> 0 | AW53: =IFERROR((AK53-$AQ53)/ABS($AQ53),0) -> 0 | AX53: =(AK53-$AQ53) -> 0 | BA53: 0 | BB53: =IFERROR(BA53/SUMIFS(BA:BA, $H:$H, "[+] Net Sales"),0) -> 0 | BC53: 0 | BD53: =IFERROR(BC53/SUMIFS(BC:BC, $H:$H, "[+] Net Sales"),0) -> 0 | BE53: 0 | BF53: =IFERROR(BE53/SUMIFS(BE:BE, $H:$H, "[+] Net Sales"),0) -> 0 | BG53: =IFERROR((BA53-$BC53)/ABS($BC53),0) -> 0 | BH53: =(BA53-$BC53) -> 0 | BI53: =IFERROR((BA53-$BE53)/ABS($BE53),0) -> 0 | BJ53: =(BA53-$BE53) -> 0
H54: [*] 3640 (Special Charges) | N54: =IFERROR(M54/SUMIFS(M:M, $H:$H, "[+] Net Sales"),0) -> 0 | P54: =IFERROR(O54/SUMIFS(O:O, $H:$H, "[+] Net Sales"),0) -> 0 | R54: =IFERROR(Q54/SUMIFS(Q:Q, $H:$H, "[+] Net Sales"),0) -> 0 | T54: =IFERROR(S54/SUMIFS(S:S, $H:$H, "[+] Net Sales"),0) -> 0 | U54: =IFERROR(($M54-O54)/ABS(O54),0) -> 0 | V54: =IFERROR((M54-$O54), $M54-0) -> 0 | W54: =IFERROR((M54-$Q54)/ABS($Q54),0) -> 0 | X54: =IFERROR((M54-$Q54), $M54-0) -> 0 | Y54: =IFERROR((M54-$S54)/ABS($S54),0) -> 0 | Z54: =IFERROR((M54-$S54),$M54-0) -> 0 | AC54: 0 | AD54: 0 | AE54: 0 | AF54: =IFERROR(($AC54-AD54)/ABS(AD54),0) -> 0 | AG54: =($AC54-AD54) -> 0 | AH54: =IFERROR(($AC54-AE54)/ABS(AE54),0) -> 0 | AI54: =($AC54-AE54) -> 0 | AK54: 0 | AL54: =IFERROR(AK54/SUMIFS(AK:AK, $H:$H, "[+] Net Sales"),0) -> 0 | AM54: 0 | AN54: =IFERROR(AM54/SUMIFS(AM:AM, $H:$H, "[+] Net Sales"),0) -> 0 | AO54: 0 | AP54: =IFERROR(AO54/SUMIFS(AO:AO, $H:$H, "[+] Net Sales"),0) -> 0 | AQ54: 0 | AR54: =IFERROR(AQ54/SUMIFS(AQ:AQ, $H:$H, "[+] Net Sales"),0) -> 0 | AS54: =IFERROR((AK54-$AM54)/ABS($AM54),0) -> 0 | AT54: =(AK54-$AM54) -> 0 | AU54: =IFERROR((AK54-$AO54)/ABS($AO54),0) -> 0 | AV54: =(AK54-$AO54) -> 0 | AW54: =IFERROR((AK54-$AQ54)/ABS($AQ54),0) -> 0 | AX54: =(AK54-$AQ54) -> 0 | BA54: 0 | BB54: =IFERROR(BA54/SUMIFS(BA:BA, $H:$H, "[+] Net Sales"),0) -> 0 | BC54: 0 | BD54: =IFERROR(BC54/SUMIFS(BC:BC, $H:$H, "[+] Net Sales"),0) -> 0 | BE54: 0 | BF54: =IFERROR(BE54/SUMIFS(BE:BE, $H:$H, "[+] Net Sales"),0) -> 0 | BG54: =IFERROR((BA54-$BC54)/ABS($BC54),0) -> 0 | BH54: =(BA54-$BC54) -> 0 | BI54: =IFERROR((BA54-$BE54)/ABS($BE54),0) -> 0 | BJ54: =(BA54-$BE54) -> 0
H55: [*] 3660 (Sales Restocking Charge) | N55: =IFERROR(M55/SUMIFS(M:M, $H:$H, "[+] Net Sales"),0) -> 0 | P55: =IFERROR(O55/SUMIFS(O:O, $H:$H, "[+] Net Sales"),0) -> 0 | R55: =IFERROR(Q55/SUMIFS(Q:Q, $H:$H, "[+] Net Sales"),0) -> 0 | T55: =IFERROR(S55/SUMIFS(S:S, $H:$H, "[+] Net Sales"),0) -> 0 | U55: =IFERROR(($M55-O55)/ABS(O55),0) -> 0 | V55: =IFERROR((M55-$O55), $M55-0) -> 0 | W55: =IFERROR((M55-$Q55)/ABS($Q55),0) -> 0 | X55: =IFERROR((M55-$Q55), $M55-0) -> 0 | Y55: =IFERROR((M55-$S55)/ABS($S55),0) -> 0 | Z55: =IFERROR((M55-$S55),$M55-0) -> 0 | AC55: 0 | AD55: 0 | AE55: 0 | AF55: =IFERROR(($AC55-AD55)/ABS(AD55),0) -> 0 | AG55: =($AC55-AD55) -> 0 | AH55: =IFERROR(($AC55-AE55)/ABS(AE55),0) -> 0 | AI55: =($AC55-AE55) -> 0 | AK55: 0 | AL55: =IFERROR(AK55/SUMIFS(AK:AK, $H:$H, "[+] Net Sales"),0) -> 0 | AM55: 0 | AN55: =IFERROR(AM55/SUMIFS(AM:AM, $H:$H, "[+] Net Sales"),0) -> 0 | AO55: 0 | AP55: =IFERROR(AO55/SUMIFS(AO:AO, $H:$H, "[+] Net Sales"),0) -> 0 | AQ55: 0 | AR55: =IFERROR(AQ55/SUMIFS(AQ:AQ, $H:$H, "[+] Net Sales"),0) -> 0 | AS55: =IFERROR((AK55-$AM55)/ABS($AM55),0) -> 0 | AT55: =(AK55-$AM55) -> 0 | AU55: =IFERROR((AK55-$AO55)/ABS($AO55),0) -> 0 | AV55: =(AK55-$AO55) -> 0 | AW55: =IFERROR((AK55-$AQ55)/ABS($AQ55),0) -> 0 | AX55: =(AK55-$AQ55) -> 0 | BA55: 0 | BB55: =IFERROR(BA55/SUMIFS(BA:BA, $H:$H, "[+] Net Sales"),0) -> 0 | BC55: 0 | BD55: =IFERROR(BC55/SUMIFS(BC:BC, $H:$H, "[+] Net Sales"),0) -> 0 | BE55: 0 | BF55: =IFERROR(BE55/SUMIFS(BE:BE, $H:$H, "[+] Net Sales"),0) -> 0 | BG55: =IFERROR((BA55-$BC55)/ABS($BC55),0) -> 0 | BH55: =(BA55-$BC55) -> 0 | BI55: =IFERROR((BA55-$BE55)/ABS($BE55),0) -> 0 | BJ55: =(BA55-$BE55) -> 0
H56: [+] Freight Revenue | M56: 0 | N56: =IFERROR(M56/SUMIFS(M:M, $H:$H, "[+] Net Sales"),0) -> 0 | O56: 0 | P56: =IFERROR(O56/SUMIFS(O:O, $H:$H, "[+] Net Sales"),0) -> 0 | Q56: 0 | R56: =IFERROR(Q56/SUMIFS(Q:Q, $H:$H, "[+] Net Sales"),0) -> 0 | S56: 0 | T56: =IFERROR(S56/SUMIFS(S:S, $H:$H, "[+] Net Sales"),0) -> 0 | U56: =IFERROR(($M56-O56)/ABS(O56),0) -> 0 | V56: =IFERROR((M56-$O56), $M56-0) -> 0 | W56: =IFERROR((M56-$Q56)/ABS($Q56),0) -> 0 | X56: =IFERROR((M56-$Q56), $M56-0) -> 0 | Y56: =IFERROR((M56-$S56)/ABS($S56),0) -> 0 | Z56: =IFERROR((M56-$S56),$M56-0) -> 0 | AC56: 0 | AD56: 0 | AE56: 0 | AF56: =IFERROR(($AC56-AD56)/ABS(AD56),0) -> 0 | AG56: =($AC56-AD56) -> 0 | AH56: =IFERROR(($AC56-AE56)/ABS(AE56),0) -> 0 | AI56: =($AC56-AE56) -> 0 | AK56: 0 | AL56: =IFERROR(AK56/SUMIFS(AK:AK, $H:$H, "[+] Net Sales"),0) -> 0 | AM56: 0 | AN56: =IFERROR(AM56/SUMIFS(AM:AM, $H:$H, "[+] Net Sales"),0) -> 0 | AO56: 0 | AP56: =IFERROR(AO56/SUMIFS(AO:AO, $H:$H, "[+] Net Sales"),0) -> 0 | AQ56: 0 | AR56: =IFERROR(AQ56/SUMIFS(AQ:AQ, $H:$H, "[+] Net Sales"),0) -> 0 | AS56: =IFERROR((AK56-$AM56)/ABS($AM56),0) -> 0 | AT56: =(AK56-$AM56) -> 0 | AU56: =IFERROR((AK56-$AO56)/ABS($AO56),0) -> 0 | AV56: =(AK56-$AO56) -> 0 | AW56: =IFERROR((AK56-$AQ56)/ABS($AQ56),0) -> 0 | AX56: =(AK56-$AQ56) -> 0 | BA56: 0 | BB56: =IFERROR(BA56/SUMIFS(BA:BA, $H:$H, "[+] Net Sales"),0) -> 0 | BC56: 0 | BD56: =IFERROR(BC56/SUMIFS(BC:BC, $H:$H, "[+] Net Sales"),0) -> 0 | BE56: 0 | BF56: =IFERROR(BE56/SUMIFS(BE:BE, $H:$H, "[+] Net Sales"),0) -> 0 | BG56: =IFERROR((BA56-$BC56)/ABS($BC56),0) -> 0 | BH56: =(BA56-$BC56) -> 0 | BI56: =IFERROR((BA56-$BE56)/ABS($BE56),0) -> 0 | BJ56: =(BA56-$BE56) -> 0
H57: [*] 4326 (Freight Out Merchandise - Billed- Revenue) | N57: =IFERROR(M57/SUMIFS(M:M, $H:$H, "[+] Net Sales"),0) -> 0 | P57: =IFERROR(O57/SUMIFS(O:O, $H:$H, "[+] Net Sales"),0) -> 0 | R57: =IFERROR(Q57/SUMIFS(Q:Q, $H:$H, "[+] Net Sales"),0) -> 0 | T57: =IFERROR(S57/SUMIFS(S:S, $H:$H, "[+] Net Sales"),0) -> 0 | U57: =IFERROR(($M57-O57)/ABS(O57),0) -> 0 | V57: =IFERROR((M57-$O57), $M57-0) -> 0 | W57: =IFERROR((M57-$Q57)/ABS($Q57),0) -> 0 | X57: =IFERROR((M57-$Q57), $M57-0) -> 0 | Y57: =IFERROR((M57-$S57)/ABS($S57),0) -> 0 | Z57: =IFERROR((M57-$S57),$M57-0) -> 0 | AC57: 0 | AD57: 0 | AE57: 0 | AF57: =IFERROR(($AC57-AD57)/ABS(AD57),0) -> 0 | AG57: =($AC57-AD57) -> 0 | AH57: =IFERROR(($AC57-AE57)/ABS(AE57),0) -> 0 | AI57: =($AC57-AE57) -> 0 | AK57: 0 | AL57: =IFERROR(AK57/SUMIFS(AK:AK, $H:$H, "[+] Net Sales"),0) -> 0 | AM57: 0 | AN57: =IFERROR(AM57/SUMIFS(AM:AM, $H:$H, "[+] Net Sales"),0) -> 0 | AO57: 0 | AP57: =IFERROR(AO57/SUMIFS(AO:AO, $H:$H, "[+] Net Sales"),0) -> 0 | AQ57: 0 | AR57: =IFERROR(AQ57/SUMIFS(AQ:AQ, $H:$H, "[+] Net Sales"),0) -> 0 | AS57: =IFERROR((AK57-$AM57)/ABS($AM57),0) -> 0 | AT57: =(AK57-$AM57) -> 0 | AU57: =IFERROR((AK57-$AO57)/ABS($AO57),0) -> 0 | AV57: =(AK57-$AO57) -> 0 | AW57: =IFERROR((AK57-$AQ57)/ABS($AQ57),0) -> 0 | AX57: =(AK57-$AQ57) -> 0 | BA57: 0 | BB57: =IFERROR(BA57/SUMIFS(BA:BA, $H:$H, "[+] Net Sales"),0) -> 0 | BC57: 0 | BD57: =IFERROR(BC57/SUMIFS(BC:BC, $H:$H, "[+] Net Sales"),0) -> 0 | BE57: 0 | BF57: =IFERROR(BE57/SUMIFS(BE:BE, $H:$H, "[+] Net Sales"),0) -> 0 | BG57: =IFERROR((BA57-$BC57)/ABS($BC57),0) -> 0 | BH57: =(BA57-$BC57) -> 0 | BI57: =IFERROR((BA57-$BE57)/ABS($BE57),0) -> 0 | BJ57: =(BA57-$BE57) -> 0
H58: [+] Other Revenue | M58: 0 | N58: =IFERROR(M58/SUMIFS(M:M, $H:$H, "[+] Net Sales"),0) -> 0 | O58: 0 | P58: =IFERROR(O58/SUMIFS(O:O, $H:$H, "[+] Net Sales"),0) -> 0 | Q58: 0 | R58: =IFERROR(Q58/SUMIFS(Q:Q, $H:$H, "[+] Net Sales"),0) -> 0 | S58: 0 | T58: =IFERROR(S58/SUMIFS(S:S, $H:$H, "[+] Net Sales"),0) -> 0 | U58: =IFERROR(($M58-O58)/ABS(O58),0) -> 0 | V58: =IFERROR((M58-$O58), $M58-0) -> 0 | W58: =IFERROR((M58-$Q58)/ABS($Q58),0) -> 0 | X58: =IFERROR((M58-$Q58), $M58-0) -> 0 | Y58: =IFERROR((M58-$S58)/ABS($S58),0) -> 0 | Z58: =IFERROR((M58-$S58),$M58-0) -> 0 | AC58: 0 | AD58: 0 | AE58: 0 | AF58: =IFERROR(($AC58-AD58)/ABS(AD58),0) -> 0 | AG58: =($AC58-AD58) -> 0 | AH58: =IFERROR(($AC58-AE58)/ABS(AE58),0) -> 0 | AI58: =($AC58-AE58) -> 0 | AK58: 0 | AL58: =IFERROR(AK58/SUMIFS(AK:AK, $H:$H, "[+] Net Sales"),0) -> 0 | AM58: 0 | AN58: =IFERROR(AM58/SUMIFS(AM:AM, $H:$H, "[+] Net Sales"),0) -> 0 | AO58: 0 | AP58: =IFERROR(AO58/SUMIFS(AO:AO, $H:$H, "[+] Net Sales"),0) -> 0 | AQ58: 0 | AR58: =IFERROR(AQ58/SUMIFS(AQ:AQ, $H:$H, "[+] Net Sales"),0) -> 0 | AS58: =IFERROR((AK58-$AM58)/ABS($AM58),0) -> 0 | AT58: =(AK58-$AM58) -> 0 | AU58: =IFERROR((AK58-$AO58)/ABS($AO58),0) -> 0 | AV58: =(AK58-$AO58) -> 0 | AW58: =IFERROR((AK58-$AQ58)/ABS($AQ58),0) -> 0 | AX58: =(AK58-$AQ58) -> 0 | BA58: 0 | BB58: =IFERROR(BA58/SUMIFS(BA:BA, $H:$H, "[+] Net Sales"),0) -> 0 | BC58: 0 | BD58: =IFERROR(BC58/SUMIFS(BC:BC, $H:$H, "[+] Net Sales"),0) -> 0 | BE58: 0 | BF58: =IFERROR(BE58/SUMIFS(BE:BE, $H:$H, "[+] Net Sales"),0) -> 0 | BG58: =IFERROR((BA58-$BC58)/ABS($BC58),0) -> 0 | BH58: =(BA58-$BC58) -> 0 | BI58: =IFERROR((BA58-$BE58)/ABS($BE58),0) -> 0 | BJ58: =(BA58-$BE58) -> 0
H59: [*] 3690 (Other Income - Royalty) | N59: =IFERROR(M59/SUMIFS(M:M, $H:$H, "[+] Net Sales"),0) -> 0 | P59: =IFERROR(O59/SUMIFS(O:O, $H:$H, "[+] Net Sales"),0) -> 0 | R59: =IFERROR(Q59/SUMIFS(Q:Q, $H:$H, "[+] Net Sales"),0) -> 0 | T59: =IFERROR(S59/SUMIFS(S:S, $H:$H, "[+] Net Sales"),0) -> 0 | U59: =IFERROR(($M59-O59)/ABS(O59),0) -> 0 | V59: =IFERROR((M59-$O59), $M59-0) -> 0 | W59: =IFERROR((M59-$Q59)/ABS($Q59),0) -> 0 | X59: =IFERROR((M59-$Q59), $M59-0) -> 0 | Y59: =IFERROR((M59-$S59)/ABS($S59),0) -> 0 | Z59: =IFERROR((M59-$S59),$M59-0) -> 0 | AC59: 0 | AD59: 0 | AE59: 0 | AF59: =IFERROR(($AC59-AD59)/ABS(AD59),0) -> 0 | AG59: =($AC59-AD59) -> 0 | AH59: =IFERROR(($AC59-AE59)/ABS(AE59),0) -> 0 | AI59: =($AC59-AE59) -> 0 | AK59: 0 | AL59: =IFERROR(AK59/SUMIFS(AK:AK, $H:$H, "[+] Net Sales"),0) -> 0 | AM59: 0 | AN59: =IFERROR(AM59/SUMIFS(AM:AM, $H:$H, "[+] Net Sales"),0) -> 0 | AO59: 0 | AP59: =IFERROR(AO59/SUMIFS(AO:AO, $H:$H, "[+] Net Sales"),0) -> 0 | AQ59: 0 | AR59: =IFERROR(AQ59/SUMIFS(AQ:AQ, $H:$H, "[+] Net Sales"),0) -> 0 | AS59: =IFERROR((AK59-$AM59)/ABS($AM59),0) -> 0 | AT59: =(AK59-$AM59) -> 0 | AU59: =IFERROR((AK59-$AO59)/ABS($AO59),0) -> 0 | AV59: =(AK59-$AO59) -> 0 | AW59: =IFERROR((AK59-$AQ59)/ABS($AQ59),0) -> 0 | AX59: =(AK59-$AQ59) -> 0 | BA59: 0 | BB59: =IFERROR(BA59/SUMIFS(BA:BA, $H:$H, "[+] Net Sales"),0) -> 0 | BC59: 0 | BD59: =IFERROR(BC59/SUMIFS(BC:BC, $H:$H, "[+] Net Sales"),0) -> 0 | BE59: 0 | BF59: =IFERROR(BE59/SUMIFS(BE:BE, $H:$H, "[+] Net Sales"),0) -> 0 | BG59: =IFERROR((BA59-$BC59)/ABS($BC59),0) -> 0 | BH59: =(BA59-$BC59) -> 0 | BI59: =IFERROR((BA59-$BE59)/ABS($BE59),0) -> 0 | BJ59: =(BA59-$BE59) -> 0
H60: [*] 3695 (Other Income - Commission) | N60: =IFERROR(M60/SUMIFS(M:M, $H:$H, "[+] Net Sales"),0) -> 0 | P60: =IFERROR(O60/SUMIFS(O:O, $H:$H, "[+] Net Sales"),0) -> 0 | R60: =IFERROR(Q60/SUMIFS(Q:Q, $H:$H, "[+] Net Sales"),0) -> 0 | T60: =IFERROR(S60/SUMIFS(S:S, $H:$H, "[+] Net Sales"),0) -> 0 | U60: =IFERROR(($M60-O60)/ABS(O60),0) -> 0 | V60: =IFERROR((M60-$O60), $M60-0) -> 0 | W60: =IFERROR((M60-$Q60)/ABS($Q60),0) -> 0 | X60: =IFERROR((M60-$Q60), $M60-0) -> 0 | Y60: =IFERROR((M60-$S60)/ABS($S60),0) -> 0 | Z60: =IFERROR((M60-$S60),$M60-0) -> 0 | AC60: 0 | AD60: 0 | AE60: 0 | AF60: =IFERROR(($AC60-AD60)/ABS(AD60),0) -> 0 | AG60: =($AC60-AD60) -> 0 | AH60: =IFERROR(($AC60-AE60)/ABS(AE60),0) -> 0 | AI60: =($AC60-AE60) -> 0 | AK60: 0 | AL60: =IFERROR(AK60/SUMIFS(AK:AK, $H:$H, "[+] Net Sales"),0) -> 0 | AM60: 0 | AN60: =IFERROR(AM60/SUMIFS(AM:AM, $H:$H, "[+] Net Sales"),0) -> 0 | AO60: 0 | AP60: =IFERROR(AO60/SUMIFS(AO:AO, $H:$H, "[+] Net Sales"),0) -> 0 | AQ60: 0 | AR60: =IFERROR(AQ60/SUMIFS(AQ:AQ, $H:$H, "[+] Net Sales"),0) -> 0 | AS60: =IFERROR((AK60-$AM60)/ABS($AM60),0) -> 0 | AT60: =(AK60-$AM60) -> 0 | AU60: =IFERROR((AK60-$AO60)/ABS($AO60),0) -> 0 | AV60: =(AK60-$AO60) -> 0 | AW60: =IFERROR((AK60-$AQ60)/ABS($AQ60),0) -> 0 | AX60: =(AK60-$AQ60) -> 0 | BA60: 0 | BB60: =IFERROR(BA60/SUMIFS(BA:BA, $H:$H, "[+] Net Sales"),0) -> 0 | BC60: 0 | BD60: =IFERROR(BC60/SUMIFS(BC:BC, $H:$H, "[+] Net Sales"),0) -> 0 | BE60: 0 | BF60: =IFERROR(BE60/SUMIFS(BE:BE, $H:$H, "[+] Net Sales"),0) -> 0 | BG60: =IFERROR((BA60-$BC60)/ABS($BC60),0) -> 0 | BH60: =(BA60-$BC60) -> 0 | BI60: =IFERROR((BA60-$BE60)/ABS($BE60),0) -> 0 | BJ60: =(BA60-$BE60) -> 0
H61: [*] 3650 (Other Revenue) | N61: =IFERROR(M61/SUMIFS(M:M, $H:$H, "[+] Net Sales"),0) -> 0 | P61: =IFERROR(O61/SUMIFS(O:O, $H:$H, "[+] Net Sales"),0) -> 0 | R61: =IFERROR(Q61/SUMIFS(Q:Q, $H:$H, "[+] Net Sales"),0) -> 0 | T61: =IFERROR(S61/SUMIFS(S:S, $H:$H, "[+] Net Sales"),0) -> 0 | U61: =IFERROR(($M61-O61)/ABS(O61),0) -> 0 | V61: =IFERROR((M61-$O61), $M61-0) -> 0 | W61: =IFERROR((M61-$Q61)/ABS($Q61),0) -> 0 | X61: =IFERROR((M61-$Q61), $M61-0) -> 0 | Y61: =IFERROR((M61-$S61)/ABS($S61),0) -> 0 | Z61: =IFERROR((M61-$S61),$M61-0) -> 0 | AC61: 0 | AD61: 0 | AE61: 0 | AF61: =IFERROR(($AC61-AD61)/ABS(AD61),0) -> 0 | AG61: =($AC61-AD61) -> 0 | AH61: =IFERROR(($AC61-AE61)/ABS(AE61),0) -> 0 | AI61: =($AC61-AE61) -> 0 | AK61: 0 | AL61: =IFERROR(AK61/SUMIFS(AK:AK, $H:$H, "[+] Net Sales"),0) -> 0 | AM61: 0 | AN61: =IFERROR(AM61/SUMIFS(AM:AM, $H:$H, "[+] Net Sales"),0) -> 0 | AO61: 0 | AP61: =IFERROR(AO61/SUMIFS(AO:AO, $H:$H, "[+] Net Sales"),0) -> 0 | AQ61: 0 | AR61: =IFERROR(AQ61/SUMIFS(AQ:AQ, $H:$H, "[+] Net Sales"),0) -> 0 | AS61: =IFERROR((AK61-$AM61)/ABS($AM61),0) -> 0 | AT61: =(AK61-$AM61) -> 0 | AU61: =IFERROR((AK61-$AO61)/ABS($AO61),0) -> 0 | AV61: =(AK61-$AO61) -> 0 | AW61: =IFERROR((AK61-$AQ61)/ABS($AQ61),0) -> 0 | AX61: =(AK61-$AQ61) -> 0 | BA61: 0 | BB61: =IFERROR(BA61/SUMIFS(BA:BA, $H:$H, "[+] Net Sales"),0) -> 0 | BC61: 0 | BD61: =IFERROR(BC61/SUMIFS(BC:BC, $H:$H, "[+] Net Sales"),0) -> 0 | BE61: 0 | BF61: =IFERROR(BE61/SUMIFS(BE:BE, $H:$H, "[+] Net Sales"),0) -> 0 | BG61: =IFERROR((BA61-$BC61)/ABS($BC61),0) -> 0 | BH61: =(BA61-$BC61) -> 0 | BI61: =IFERROR((BA61-$BE61)/ABS($BE61),0) -> 0 | BJ61: =(BA61-$BE61) -> 0
B62: #hiderow | N62: =IFERROR(M62/SUMIFS(M:M, $H:$H, "[+] Net Sales"),0) -> 0 | P62: =IFERROR(O62/SUMIFS(O:O, $H:$H, "[+] Net Sales"),0) -> 0 | R62: =IFERROR(Q62/SUMIFS(Q:Q, $H:$H, "[+] Net Sales"),0) -> 0 | T62: =IFERROR(S62/SUMIFS(S:S, $H:$H, "[+] Net Sales"),0) -> 0 | AL62: =IFERROR(AK62/SUMIFS(AK:AK, $H:$H, "[+] Net Sales"),0) -> 0 | AN62: =IFERROR(AM62/SUMIFS(AM:AM, $H:$H, "[+] Net Sales"),0) -> 0 | AP62: =IFERROR(AO62/SUMIFS(AO:AO, $H:$H, "[+] Net Sales"),0) -> 0 | AR62: =IFERROR(AQ62/SUMIFS(AQ:AQ, $H:$H, "[+] Net Sales"),0) -> 0 | BB62: =IFERROR(BA62/SUMIFS(BA:BA, $H:$H, "[+] Net Sales"),0) -> 0 | BD62: =IFERROR(BC62/SUMIFS(BC:BC, $H:$H, "[+] Net Sales"),0) -> 0 | BF62: =IFERROR(BE62/SUMIFS(BE:BE, $H:$H, "[+] Net Sales"),0) -> 0
B63: =B30 -> #showrow | H63: Total Revenue | L63: 1 | M63: =SUMIFS(M31:M62,$I31:$I62,"<>"&$I$29,$E31:$E62,"<>*[-]*",$F31:$F62,"<>*[-]*",$G31:$G62,"<>*[-]*",$H31:$H62,"*[+]*") -> 654439.77 | N63: =IFERROR(M63/SUMIFS(M:M, $H:$H, "[+] Net Sales"),0) -> 1 | O63: =SUMIFS(O31:O62,$I31:$I62,"<>"&$I$29,$E31:$E62,"<>*[-]*",$F31:$F62,"<>*[-]*",$G31:$G62,"<>*[-]*",$H31:$H62,"*[+]*") -> 0 | P63: =IFERROR(O63/SUMIFS(O:O, $H:$H, "[+] Net Sales"),0) -> 0 | Q63: =SUMIFS(Q31:Q62,$I31:$I62,"<>"&$I$29,$E31:$E62,"<>*[-]*",$F31:$F62,"<>*[-]*",$G31:$G62,"<>*[-]*",$H31:$H62,"*[+]*") -> 553920.45 | R63: =IFERROR(Q63/SUMIFS(Q:Q, $H:$H, "[+] Net Sales"),0) -> 1 | S63: =SUMIFS(S31:S62,$I31:$I62,"<>"&$I$29,$E31:$E62,"<>*[-]*",$F31:$F62,"<>*[-]*",$G31:$G62,"<>*[-]*",$H31:$H62,"*[+]*") -> 509967.01 | T63: =IFERROR(S63/SUMIFS(S:S, $H:$H, "[+] Net Sales"),0) -> 1 | U63: =IFERROR(($M63-O63)/ABS(O63),0) -> 0 | V63: =IFERROR((M63-$O63), $M63-0) -> 654439.77 | W63: =IFERROR((M63-$Q63)/ABS($Q63),0) -> 0.18146888 | X63: =IFERROR((M63-$Q63), $M63-0) -> 100519.32 | Y63: =IFERROR((M63-$S63)/ABS($S63),0) -> 0.28329825 | Z63: =IFERROR((M63-$S63),$M63-0) -> 144472.76 | AC63: =SUMIFS(AC31:AC62,$I31:$I62,"<>"&$I$29,$E31:$E62,"<>*[-]*",$F31:$F62,"<>*[-]*",$G31:$G62,"<>*[-]*",$H31:$H62,"*[+]*") -> 654439.77 | AD63: =SUMIFS(AD31:AD62,$I31:$I62,"<>"&$I$29,$E31:$E62,"<>*[-]*",$F31:$F62,"<>*[-]*",$G31:$G62,"<>*[-]*",$H31:$H62,"*[+]*") -> 509967.01 | AE63: =SUMIFS(AE31:AE62,$I31:$I62,"<>"&$I$29,$E31:$E62,"<>*[-]*",$F31:$F62,"<>*[-]*",$G31:$G62,"<>*[-]*",$H31:$H62,"*[+]*") -> 553920.45 | AF63: =IFERROR((AC63-$AD63)/ABS($AD63),0) -> 0.28329825 | AG63: =(AC63-$AD63) -> 144472.76 | AH63: =IFERROR((AC63-$AE63)/ABS($AE63),0) -> 0.18146888 | AI63: =(AC63-$AE63) -> 100519.32 | AK63: =SUMIFS(AK31:AK62,$I31:$I62,"<>"&$I$29,$E31:$E62,"<>*[-]*",$F31:$F62,"<>*[-]*",$G31:$G62,"<>*[-]*",$H31:$H62,"*[+]*") -> 654439.77 | AL63: =IFERROR(AK63/SUMIFS(AK:AK, $H:$H, "[+] Net Sales"),0) -> 1 | AM63: =SUMIFS(AM31:AM62,$I31:$I62,"<>"&$I$29,$E31:$E62,"<>*[-]*",$F31:$F62,"<>*[-]*",$G31:$G62,"<>*[-]*",$H31:$H62,"*[+]*") -> 0 | AN63: =IFERROR(AM63/SUMIFS(AM:AM, $H:$H, "[+] Net Sales"),0) -> 0 | AO63: =SUMIFS(AO31:AO62,$I31:$I62,"<>"&$I$29,$E31:$E62,"<>*[-]*",$F31:$F62,"<>*[-]*",$G31:$G62,"<>*[-]*",$H31:$H62,"*[+]*") -> 553920.45 | AP63: =IFERROR(AO63/SUMIFS(AO:AO, $H:$H, "[+] Net Sales"),0) -> 1 | AQ63: =SUMIFS(AQ31:AQ62,$I31:$I62,"<>"&$I$29,$E31:$E62,"<>*[-]*",$F31:$F62,"<>*[-]*",$G31:$G62,"<>*[-]*",$H31:$H62,"*[+]*") -> 509967.01 | AR63: =IFERROR(AQ63/SUMIFS(AQ:AQ, $H:$H, "[+] Net Sales"),0) -> 1 | AS63: =IFERROR((AK63-$AM63)/ABS($AM63),0) -> 0 | AT63: =(AK63-$AM63) -> 654439.77 | AU63: =IFERROR((AK63-$AO63)/ABS($AO63),0) -> 0.18146888 | AV63: =(AK63-$AO63) -> 100519.32 | AW63: =IFERROR((AK63-$AQ63)/ABS($AQ63),0) -> 0.28329825 | AX63: =(AK63-$AQ63) -> 144472.76 | BA63: =SUMIFS(BA31:BA62,$I31:$I62,"<>"&$I$29,$E31:$E62,"<>*[-]*",$F31:$F62,"<>*[-]*",$G31:$G62,"<>*[-]*",$H31:$H62,"*[+]*") -> 2231199 | BB63: =IFERROR(BA63/SUMIFS(BA:BA, $H:$H, "[+] Net Sales"),0) -> 1 | BC63: =SUMIFS(BC31:BC62,$I31:$I62,"<>"&$I$29,$E31:$E62,"<>*[-]*",$F31:$F62,"<>*[-]*",$G31:$G62,"<>*[-]*",$H31:$H62,"*[+]*") -> 2231199 | BD63: =IFERROR(BC63/SUMIFS(BC:BC, $H:$H, "[+] Net Sales"),0) -> 1 | BE63: =SUMIFS(BE31:BE62,$I31:$I62,"<>"&$I$29,$E31:$E62,"<>*[-]*",$F31:$F62,"<>*[-]*",$G31:$G62,"<>*[-]*",$H31:$H62,"*[+]*") -> 2008626.8 | BF63: =IFERROR(BE63/SUMIFS(BE:BE, $H:$H, "[+] Net Sales"),0) -> 1 | BG63: =IFERROR((BA63-$BC63)/ABS($BC63),0) -> 0 | BH63: =(BA63-$BC63) -> 0 | BI63: =IFERROR((BA63-$BE63)/ABS($BE63),0) -> 0.11080817 | BJ63: =(BA63-$BE63) -> 222572.25
B64: =B63 -> #showrow
B65: =IF(COUNTBLANK(B66:B139)>0,"#showrow","#hiderow") -> #showrow | H65: Cost of Goods Sold
B66: #hiderow | H66: MultiDynamic: Account | N66: =IFERROR(M66/SUMIFS(M:M, $H:$H, "[+] Net Sales"),0) -> 0 | P66: =IFERROR(O66/SUMIFS(O:O, $H:$H, "[+] Net Sales"),0) -> 0 | R66: =IFERROR(Q66/SUMIFS(Q:Q, $H:$H, "[+] Net Sales"),0) -> 0 | T66: =IFERROR(S66/SUMIFS(S:S, $H:$H, "[+] Net Sales"),0) -> 0 | U66: =IFERROR(($O66-M66)/ABS(M66),0) -> 0 | V66: =IFERROR((O66-$M66), 0-$M66) -> 0 | W66: =IFERROR((Q66-$M66)/ABS($M66),0) -> 0 | X66: =IFERROR((Q66-$M66), 0 -$M66) -> 0 | Y66: =IFERROR((S66-$M66)/ABS($M66),0) -> 0 | Z66: =IFERROR((S66-$M66),0-$M66) -> 0 | AF66: =IFERROR((AD66-$AC66)/ABS($AC66),0) -> 0 | AG66: =(AD66-$AC66) -> 0 | AH66: =IFERROR((AE66-$AC66)/ABS($AC66),0) -> 0 | AI66: =(AE66-$AC66) -> 0 | AL66: =IFERROR(AK66/SUMIFS(AK:AK, $H:$H, "[+] Net Sales"),0) -> 0 | AN66: =IFERROR(AM66/SUMIFS(AM:AM, $H:$H, "[+] Net Sales"),0) -> 0 | AP66: =IFERROR(AO66/SUMIFS(AO:AO, $H:$H, "[+] Net Sales"),0) -> 0 | AR66: =IFERROR(AQ66/SUMIFS(AQ:AQ, $H:$H, "[+] Net Sales"),0) -> 0 | AS66: =IFERROR((AM66-$AK66)/ABS($AK66),0) -> 0 | AT66: =(AM66-$AK66) -> 0 | AU66: =IFERROR((AO66-$AK66)/ABS($AO66),0) -> 0 | AV66: =(AO66-$AK66) -> 0 | AW66: =IFERROR((AQ66-$AK66)/ABS($AK66),0) -> 0 | AX66: =(AQ66-$AK66) -> 0 | BB66: =IFERROR(BA66/SUMIFS(BA:BA, $H:$H, "[+] Net Sales"),0) -> 0 | BD66: =IFERROR(BC66/SUMIFS(BC:BC, $H:$H, "[+] Net Sales"),0) -> 0 | BF66: =IFERROR(BE66/SUMIFS(BE:BE, $H:$H, "[+] Net Sales"),0) -> 0 | BG66: =IFERROR((BC66-$BA66)/ABS($BA66),0) -> 0 | BH66: =(BC66-$BA66) -> 0 | BI66: =IFERROR((BE66-$BA66)/ABS($BA66),0) -> 0 | BJ66: =(BE66-$BA66) -> 0
H67: [+] Material | M67: 6.4 | N67: =IFERROR(M67/SUMIFS(M:M, $H:$H, "[+] Net Sales"),0) -> 9.7793568e-06 | O67: 0 | P67: =IFERROR(O67/SUMIFS(O:O, $H:$H, "[+] Net Sales"),0) -> 0 | Q67: 0 | R67: =IFERROR(Q67/SUMIFS(Q:Q, $H:$H, "[+] Net Sales"),0) -> 0 | S67: 0 | T67: =IFERROR(S67/SUMIFS(S:S, $H:$H, "[+] Net Sales"),0) -> 0 | U67: =IFERROR(($O67-M67)/ABS(M67),0) -> -1 | V67: =IFERROR((O67-$M67), 0-$M67) -> -6.4 | W67: =IFERROR((Q67-$M67)/ABS($M67),0) -> -1 | X67: =IFERROR((Q67-$M67), 0 -$M67) -> -6.4 | Y67: =IFERROR((S67-$M67)/ABS($M67),0) -> -1 | Z67: =IFERROR((S67-$M67),0-$M67) -> -6.4 | AC67: 6.4 | AD67: 0 | AE67: 0 | AF67: =IFERROR((AD67-$AC67)/ABS($AC67),0) -> -1 | AG67: =(AD67-$AC67) -> -6.4 | AH67: =IFERROR((AE67-$AC67)/ABS($AC67),0) -> -1 | AI67: =(AE67-$AC67) -> -6.4 | AK67: 6.4 | AL67: =IFERROR(AK67/SUMIFS(AK:AK, $H:$H, "[+] Net Sales"),0) -> 9.7793568e-06 | AM67: 0 | AN67: =IFERROR(AM67/SUMIFS(AM:AM, $H:$H, "[+] Net Sales"),0) -> 0 | AO67: 0 | AP67: =IFERROR(AO67/SUMIFS(AO:AO, $H:$H, "[+] Net Sales"),0) -> 0 | AQ67: 0 | AR67: =IFERROR(AQ67/SUMIFS(AQ:AQ, $H:$H, "[+] Net Sales"),0) -> 0 | AS67: =IFERROR((AM67-$AK67)/ABS($AK67),0) -> -1 | AT67: =(AM67-$AK67) -> -6.4 | AU67: =IFERROR((AO67-$AK67)/ABS($AO67),0) -> 0 | AV67: =(AO67-$AK67) -> -6.4 | AW67: =IFERROR((AQ67-$AK67)/ABS($AK67),0) -> -1 | AX67: =(AQ67-$AK67) -> -6.4 | BA67: 0 | BB67: =IFERROR(BA67/SUMIFS(BA:BA, $H:$H, "[+] Net Sales"),0) -> 0 | BC67: 0 | BD67: =IFERROR(BC67/SUMIFS(BC:BC, $H:$H, "[+] Net Sales"),0) -> 0 | BE67: 602031.13 | BF67: =IFERROR(BE67/SUMIFS(BE:BE, $H:$H, "[+] Net Sales"),0) -> 0.29972275 | BG67: =IFERROR((BC67-$BA67)/ABS($BA67),0) -> 0 | BH67: =(BC67-$BA67) -> 0 | BI67: =IFERROR((BE67-$BA67)/ABS($BA67),0) -> 0 | BJ67: =(BE67-$BA67) -> 602031.13
H68: [*] 4100 (COGS) | M68: 6.4 | N68: =IFERROR(M68/SUMIFS(M:M, $H:$H, "[+] Net Sales"),0) -> 9.7793568e-06 | P68: =IFERROR(O68/SUMIFS(O:O, $H:$H, "[+] Net Sales"),0) -> 0 | R68: =IFERROR(Q68/SUMIFS(Q:Q, $H:$H, "[+] Net Sales"),0) -> 0 | T68: =IFERROR(S68/SUMIFS(S:S, $H:$H, "[+] Net Sales"),0) -> 0 | U68: =IFERROR(($O68-M68)/ABS(M68),0) -> -1 | V68: =IFERROR((O68-$M68), 0-$M68) -> -6.4 | W68: =IFERROR((Q68-$M68)/ABS($M68),0) -> -1 | X68: =IFERROR((Q68-$M68), 0 -$M68) -> -6.4 | Y68: =IFERROR((S68-$M68)/ABS($M68),0) -> -1 | Z68: =IFERROR((S68-$M68),0-$M68) -> -6.4 | AC68: 6.4 | AD68: 0 | AE68: 0 | AF68: =IFERROR((AD68-$AC68)/ABS($AC68),0) -> -1 | AG68: =(AD68-$AC68) -> -6.4 | AH68: =IFERROR((AE68-$AC68)/ABS($AC68),0) -> -1 | AI68: =(AE68-$AC68) -> -6.4 | AK68: 6.4 | AL68: =IFERROR(AK68/SUMIFS(AK:AK, $H:$H, "[+] Net Sales"),0) -> 9.7793568e-06 | AM68: 0 | AN68: =IFERROR(AM68/SUMIFS(AM:AM, $H:$H, "[+] Net Sales"),0) -> 0 | AO68: 0 | AP68: =IFERROR(AO68/SUMIFS(AO:AO, $H:$H, "[+] Net Sales"),0) -> 0 | AQ68: 0 | AR68: =IFERROR(AQ68/SUMIFS(AQ:AQ, $H:$H, "[+] Net Sales"),0) -> 0 | AS68: =IFERROR((AM68-$AK68)/ABS($AK68),0) -> -1 | AT68: =(AM68-$AK68) -> -6.4 | AU68: =IFERROR((AO68-$AK68)/ABS($AO68),0) -> 0 | AV68: =(AO68-$AK68) -> -6.4 | AW68: =IFERROR((AQ68-$AK68)/ABS($AK68),0) -> -1 | AX68: =(AQ68-$AK68) -> -6.4 | BA68: 0 | BB68: =IFERROR(BA68/SUMIFS(BA:BA, $H:$H, "[+] Net Sales"),0) -> 0 | BC68: 0 | BD68: =IFERROR(BC68/SUMIFS(BC:BC, $H:$H, "[+] Net Sales"),0) -> 0 | BE68: -6352.56 | BF68: =IFERROR(BE68/SUMIFS(BE:BE, $H:$H, "[+] Net Sales"),0) -> -0.0031626384 | BG68: =IFERROR((BC68-$BA68)/ABS($BA68),0) -> 0 | BH68: =(BC68-$BA68) -> 0 | BI68: =IFERROR((BE68-$BA68)/ABS($BA68),0) -> 0 | BJ68: =(BE68-$BA68) -> -6352.56
H69: [*] 4101 (COGS - Paint Product) | N69: =IFERROR(M69/SUMIFS(M:M, $H:$H, "[+] Net Sales"),0) -> 0 | P69: =IFERROR(O69/SUMIFS(O:O, $H:$H, "[+] Net Sales"),0) -> 0 | R69: =IFERROR(Q69/SUMIFS(Q:Q, $H:$H, "[+] Net Sales"),0) -> 0 | T69: =IFERROR(S69/SUMIFS(S:S, $H:$H, "[+] Net Sales"),0) -> 0 | U69: =IFERROR(($O69-M69)/ABS(M69),0) -> 0 | V69: =IFERROR((O69-$M69), 0-$M69) -> 0 | W69: =IFERROR((Q69-$M69)/ABS($M69),0) -> 0 | X69: =IFERROR((Q69-$M69), 0 -$M69) -> 0 | Y69: =IFERROR((S69-$M69)/ABS($M69),0) -> 0 | Z69: =IFERROR((S69-$M69),0-$M69) -> 0 | AC69: 0 | AD69: 0 | AE69: 0 | AF69: =IFERROR((AD69-$AC69)/ABS($AC69),0) -> 0 | AG69: =(AD69-$AC69) -> 0 | AH69: =IFERROR((AE69-$AC69)/ABS($AC69),0) -> 0 | AI69: =(AE69-$AC69) -> 0 | AK69: 0 | AL69: =IFERROR(AK69/SUMIFS(AK:AK, $H:$H, "[+] Net Sales"),0) -> 0 | AM69: 0 | AN69: =IFERROR(AM69/SUMIFS(AM:AM, $H:$H, "[+] Net Sales"),0) -> 0 | AO69: 0 | AP69: =IFERROR(AO69/SUMIFS(AO:AO, $H:$H, "[+] Net Sales"),0) -> 0 | AQ69: 0 | AR69: =IFERROR(AQ69/SUMIFS(AQ:AQ, $H:$H, "[+] Net Sales"),0) -> 0 | AS69: =IFERROR((AM69-$AK69)/ABS($AK69),0) -> 0 | AT69: =(AM69-$AK69) -> 0 | AU69: =IFERROR((AO69-$AK69)/ABS($AO69),0) -> 0 | AV69: =(AO69-$AK69) -> 0 | AW69: =IFERROR((AQ69-$AK69)/ABS($AK69),0) -> 0 | AX69: =(AQ69-$AK69) -> 0 | BA69: 0 | BB69: =IFERROR(BA69/SUMIFS(BA:BA, $H:$H, "[+] Net Sales"),0) -> 0 | BC69: 0 | BD69: =IFERROR(BC69/SUMIFS(BC:BC, $H:$H, "[+] Net Sales"),0) -> 0 | BE69: 0 | BF69: =IFERROR(BE69/SUMIFS(BE:BE, $H:$H, "[+] Net Sales"),0) -> 0 | BG69: =IFERROR((BC69-$BA69)/ABS($BA69),0) -> 0 | BH69: =(BC69-$BA69) -> 0 | BI69: =IFERROR((BE69-$BA69)/ABS($BA69),0) -> 0 | BJ69: =(BE69-$BA69) -> 0
H70: [*] 4102 (COGS - Sample Stickers) | N70: =IFERROR(M70/SUMIFS(M:M, $H:$H, "[+] Net Sales"),0) -> 0 | P70: =IFERROR(O70/SUMIFS(O:O, $H:$H, "[+] Net Sales"),0) -> 0 | R70: =IFERROR(Q70/SUMIFS(Q:Q, $H:$H, "[+] Net Sales"),0) -> 0 | T70: =IFERROR(S70/SUMIFS(S:S, $H:$H, "[+] Net Sales"),0) -> 0 | U70: =IFERROR(($O70-M70)/ABS(M70),0) -> 0 | V70: =IFERROR((O70-$M70), 0-$M70) -> 0 | W70: =IFERROR((Q70-$M70)/ABS($M70),0) -> 0 | X70: =IFERROR((Q70-$M70), 0 -$M70) -> 0 | Y70: =IFERROR((S70-$M70)/ABS($M70),0) -> 0 | Z70: =IFERROR((S70-$M70),0-$M70) -> 0 | AC70: 0 | AD70: 0 | AE70: 0 | AF70: =IFERROR((AD70-$AC70)/ABS($AC70),0) -> 0 | AG70: =(AD70-$AC70) -> 0 | AH70: =IFERROR((AE70-$AC70)/ABS($AC70),0) -> 0 | AI70: =(AE70-$AC70) -> 0 | AK70: 0 | AL70: =IFERROR(AK70/SUMIFS(AK:AK, $H:$H, "[+] Net Sales"),0) -> 0 | AM70: 0 | AN70: =IFERROR(AM70/SUMIFS(AM:AM, $H:$H, "[+] Net Sales"),0) -> 0 | AO70: 0 | AP70: =IFERROR(AO70/SUMIFS(AO:AO, $H:$H, "[+] Net Sales"),0) -> 0 | AQ70: 0 | AR70: =IFERROR(AQ70/SUMIFS(AQ:AQ, $H:$H, "[+] Net Sales"),0) -> 0 | AS70: =IFERROR((AM70-$AK70)/ABS($AK70),0) -> 0 | AT70: =(AM70-$AK70) -> 0 | AU70: =IFERROR((AO70-$AK70)/ABS($AO70),0) -> 0 | AV70: =(AO70-$AK70) -> 0 | AW70: =IFERROR((AQ70-$AK70)/ABS($AK70),0) -> 0 | AX70: =(AQ70-$AK70) -> 0 | BA70: 0 | BB70: =IFERROR(BA70/SUMIFS(BA:BA, $H:$H, "[+] Net Sales"),0) -> 0 | BC70: 0 | BD70: =IFERROR(BC70/SUMIFS(BC:BC, $H:$H, "[+] Net Sales"),0) -> 0 | BE70: 0 | BF70: =IFERROR(BE70/SUMIFS(BE:BE, $H:$H, "[+] Net Sales"),0) -> 0 | BG70: =IFERROR((BC70-$BA70)/ABS($BA70),0) -> 0 | BH70: =(BC70-$BA70) -> 0 | BI70: =IFERROR((BE70-$BA70)/ABS($BA70),0) -> 0 | BJ70: =(BE70-$BA70) -> 0
H71: [*] 4103 (COGS - Paint Supply Product) | N71: =IFERROR(M71/SUMIFS(M:M, $H:$H, "[+] Net Sales"),0) -> 0 | P71: =IFERROR(O71/SUMIFS(O:O, $H:$H, "[+] Net Sales"),0) -> 0 | R71: =IFERROR(Q71/SUMIFS(Q:Q, $H:$H, "[+] Net Sales"),0) -> 0 | T71: =IFERROR(S71/SUMIFS(S:S, $H:$H, "[+] Net Sales"),0) -> 0 | U71: =IFERROR(($O71-M71)/ABS(M71),0) -> 0 | V71: =IFERROR((O71-$M71), 0-$M71) -> 0 | W71: =IFERROR((Q71-$M71)/ABS($M71),0) -> 0 | X71: =IFERROR((Q71-$M71), 0 -$M71) -> 0 | Y71: =IFERROR((S71-$M71)/ABS($M71),0) -> 0 | Z71: =IFERROR((S71-$M71),0-$M71) -> 0 | AC71: 0 | AD71: 0 | AE71: 0 | AF71: =IFERROR((AD71-$AC71)/ABS($AC71),0) -> 0 | AG71: =(AD71-$AC71) -> 0 | AH71: =IFERROR((AE71-$AC71)/ABS($AC71),0) -> 0 | AI71: =(AE71-$AC71) -> 0 | AK71: 0 | AL71: =IFERROR(AK71/SUMIFS(AK:AK, $H:$H, "[+] Net Sales"),0) -> 0 | AM71: 0 | AN71: =IFERROR(AM71/SUMIFS(AM:AM, $H:$H, "[+] Net Sales"),0) -> 0 | AO71: 0 | AP71: =IFERROR(AO71/SUMIFS(AO:AO, $H:$H, "[+] Net Sales"),0) -> 0 | AQ71: 0 | AR71: =IFERROR(AQ71/SUMIFS(AQ:AQ, $H:$H, "[+] Net Sales"),0) -> 0 | AS71: =IFERROR((AM71-$AK71)/ABS($AK71),0) -> 0 | AT71: =(AM71-$AK71) -> 0 | AU71: =IFERROR((AO71-$AK71)/ABS($AO71),0) -> 0 | AV71: =(AO71-$AK71) -> 0 | AW71: =IFERROR((AQ71-$AK71)/ABS($AK71),0) -> 0 | AX71: =(AQ71-$AK71) -> 0 | BA71: 0 | BB71: =IFERROR(BA71/SUMIFS(BA:BA, $H:$H, "[+] Net Sales"),0) -> 0 | BC71: 0 | BD71: =IFERROR(BC71/SUMIFS(BC:BC, $H:$H, "[+] Net Sales"),0) -> 0 | BE71: 0 | BF71: =IFERROR(BE71/SUMIFS(BE:BE, $H:$H, "[+] Net Sales"),0) -> 0 | BG71: =IFERROR((BC71-$BA71)/ABS($BA71),0) -> 0 | BH71: =(BC71-$BA71) -> 0 | BI71: =IFERROR((BE71-$BA71)/ABS($BA71),0) -> 0 | BJ71: =(BE71-$BA71) -> 0
H72: [*] 4104 (COGS - Material Cost - 3rd Party) | N72: =IFERROR(M72/SUMIFS(M:M, $H:$H, "[+] Net Sales"),0) -> 0 | P72: =IFERROR(O72/SUMIFS(O:O, $H:$H, "[+] Net Sales"),0) -> 0 | R72: =IFERROR(Q72/SUMIFS(Q:Q, $H:$H, "[+] Net Sales"),0) -> 0 | T72: =IFERROR(S72/SUMIFS(S:S, $H:$H, "[+] Net Sales"),0) -> 0 | U72: =IFERROR(($O72-M72)/ABS(M72),0) -> 0 | V72: =IFERROR((O72-$M72), 0-$M72) -> 0 | W72: =IFERROR((Q72-$M72)/ABS($M72),0) -> 0 | X72: =IFERROR((Q72-$M72), 0 -$M72) -> 0 | Y72: =IFERROR((S72-$M72)/ABS($M72),0) -> 0 | Z72: =IFERROR((S72-$M72),0-$M72) -> 0 | AC72: 0 | AD72: 0 | AE72: 0 | AF72: =IFERROR((AD72-$AC72)/ABS($AC72),0) -> 0 | AG72: =(AD72-$AC72) -> 0 | AH72: =IFERROR((AE72-$AC72)/ABS($AC72),0) -> 0 | AI72: =(AE72-$AC72) -> 0 | AK72: 0 | AL72: =IFERROR(AK72/SUMIFS(AK:AK, $H:$H, "[+] Net Sales"),0) -> 0 | AM72: 0 | AN72: =IFERROR(AM72/SUMIFS(AM:AM, $H:$H, "[+] Net Sales"),0) -> 0 | AO72: 0 | AP72: =IFERROR(AO72/SUMIFS(AO:AO, $H:$H, "[+] Net Sales"),0) -> 0 | AQ72: 0 | AR72: =IFERROR(AQ72/SUMIFS(AQ:AQ, $H:$H, "[+] Net Sales"),0) -> 0 | AS72: =IFERROR((AM72-$AK72)/ABS($AK72),0) -> 0 | AT72: =(AM72-$AK72) -> 0 | AU72: =IFERROR((AO72-$AK72)/ABS($AO72),0) -> 0 | AV72: =(AO72-$AK72) -> 0 | AW72: =IFERROR((AQ72-$AK72)/ABS($AK72),0) -> 0 | AX72: =(AQ72-$AK72) -> 0 | BA72: 0 | BB72: =IFERROR(BA72/SUMIFS(BA:BA, $H:$H, "[+] Net Sales"),0) -> 0 | BC72: 0 | BD72: =IFERROR(BC72/SUMIFS(BC:BC, $H:$H, "[+] Net Sales"),0) -> 0 | BE72: 0 | BF72: =IFERROR(BE72/SUMIFS(BE:BE, $H:$H, "[+] Net Sales"),0) -> 0 | BG72: =IFERROR((BC72-$BA72)/ABS($BA72),0) -> 0 | BH72: =(BC72-$BA72) -> 0 | BI72: =IFERROR((BE72-$BA72)/ABS($BA72),0) -> 0 | BJ72: =(BE72-$BA72) -> 0
H73: [*] 4105 (COGS - Material Cost - Intercompany) | N73: =IFERROR(M73/SUMIFS(M:M, $H:$H, "[+] Net Sales"),0) -> 0 | P73: =IFERROR(O73/SUMIFS(O:O, $H:$H, "[+] Net Sales"),0) -> 0 | R73: =IFERROR(Q73/SUMIFS(Q:Q, $H:$H, "[+] Net Sales"),0) -> 0 | T73: =IFERROR(S73/SUMIFS(S:S, $H:$H, "[+] Net Sales"),0) -> 0 | U73: =IFERROR(($O73-M73)/ABS(M73),0) -> 0 | V73: =IFERROR((O73-$M73), 0-$M73) -> 0 | W73: =IFERROR((Q73-$M73)/ABS($M73),0) -> 0 | X73: =IFERROR((Q73-$M73), 0 -$M73) -> 0 | Y73: =IFERROR((S73-$M73)/ABS($M73),0) -> 0 | Z73: =IFERROR((S73-$M73),0-$M73) -> 0 | AC73: 0 | AD73: 0 | AE73: 0 | AF73: =IFERROR((AD73-$AC73)/ABS($AC73),0) -> 0 | AG73: =(AD73-$AC73) -> 0 | AH73: =IFERROR((AE73-$AC73)/ABS($AC73),0) -> 0 | AI73: =(AE73-$AC73) -> 0 | AK73: 0 | AL73: =IFERROR(AK73/SUMIFS(AK:AK, $H:$H, "[+] Net Sales"),0) -> 0 | AM73: 0 | AN73: =IFERROR(AM73/SUMIFS(AM:AM, $H:$H, "[+] Net Sales"),0) -> 0 | AO73: 0 | AP73: =IFERROR(AO73/SUMIFS(AO:AO, $H:$H, "[+] Net Sales"),0) -> 0 | AQ73: 0 | AR73: =IFERROR(AQ73/SUMIFS(AQ:AQ, $H:$H, "[+] Net Sales"),0) -> 0 | AS73: =IFERROR((AM73-$AK73)/ABS($AK73),0) -> 0 | AT73: =(AM73-$AK73) -> 0 | AU73: =IFERROR((AO73-$AK73)/ABS($AO73),0) -> 0 | AV73: =(AO73-$AK73) -> 0 | AW73: =IFERROR((AQ73-$AK73)/ABS($AK73),0) -> 0 | AX73: =(AQ73-$AK73) -> 0 | BA73: 0 | BB73: =IFERROR(BA73/SUMIFS(BA:BA, $H:$H, "[+] Net Sales"),0) -> 0 | BC73: 0 | BD73: =IFERROR(BC73/SUMIFS(BC:BC, $H:$H, "[+] Net Sales"),0) -> 0 | BE73: 0 | BF73: =IFERROR(BE73/SUMIFS(BE:BE, $H:$H, "[+] Net Sales"),0) -> 0 | BG73: =IFERROR((BC73-$BA73)/ABS($BA73),0) -> 0 | BH73: =(BC73-$BA73) -> 0 | BI73: =IFERROR((BE73-$BA73)/ABS($BA73),0) -> 0 | BJ73: =(BE73-$BA73) -> 0
H74: [*] 4106 (4106) | N74: =IFERROR(M74/SUMIFS(M:M, $H:$H, "[+] Net Sales"),0) -> 0 | P74: =IFERROR(O74/SUMIFS(O:O, $H:$H, "[+] Net Sales"),0) -> 0 | R74: =IFERROR(Q74/SUMIFS(Q:Q, $H:$H, "[+] Net Sales"),0) -> 0 | T74: =IFERROR(S74/SUMIFS(S:S, $H:$H, "[+] Net Sales"),0) -> 0 | U74: =IFERROR(($O74-M74)/ABS(M74),0) -> 0 | V74: =IFERROR((O74-$M74), 0-$M74) -> 0 | W74: =IFERROR((Q74-$M74)/ABS($M74),0) -> 0 | X74: =IFERROR((Q74-$M74), 0 -$M74) -> 0 | Y74: =IFERROR((S74-$M74)/ABS($M74),0) -> 0 | Z74: =IFERROR((S74-$M74),0-$M74) -> 0 | AC74: 0 | AD74: 0 | AE74: 0 | AF74: =IFERROR((AD74-$AC74)/ABS($AC74),0) -> 0 | AG74: =(AD74-$AC74) -> 0 | AH74: =IFERROR((AE74-$AC74)/ABS($AC74),0) -> 0 | AI74: =(AE74-$AC74) -> 0 | AK74: 0 | AL74: =IFERROR(AK74/SUMIFS(AK:AK, $H:$H, "[+] Net Sales"),0) -> 0 | AM74: 0 | AN74: =IFERROR(AM74/SUMIFS(AM:AM, $H:$H, "[+] Net Sales"),0) -> 0 | AO74: 0 | AP74: =IFERROR(AO74/SUMIFS(AO:AO, $H:$H, "[+] Net Sales"),0) -> 0 | AQ74: 0 | AR74: =IFERROR(AQ74/SUMIFS(AQ:AQ, $H:$H, "[+] Net Sales"),0) -> 0 | AS74: =IFERROR((AM74-$AK74)/ABS($AK74),0) -> 0 | AT74: =(AM74-$AK74) -> 0 | AU74: =IFERROR((AO74-$AK74)/ABS($AO74),0) -> 0 | AV74: =(AO74-$AK74) -> 0 | AW74: =IFERROR((AQ74-$AK74)/ABS($AK74),0) -> 0 | AX74: =(AQ74-$AK74) -> 0 | BA74: 0 | BB74: =IFERROR(BA74/SUMIFS(BA:BA, $H:$H, "[+] Net Sales"),0) -> 0 | BC74: 0 | BD74: =IFERROR(BC74/SUMIFS(BC:BC, $H:$H, "[+] Net Sales"),0) -> 0 | BE74: 0 | BF74: =IFERROR(BE74/SUMIFS(BE:BE, $H:$H, "[+] Net Sales"),0) -> 0 | BG74: =IFERROR((BC74-$BA74)/ABS($BA74),0) -> 0 | BH74: =(BC74-$BA74) -> 0 | BI74: =IFERROR((BE74-$BA74)/ABS($BA74),0) -> 0 | BJ74: =(BE74-$BA74) -> 0
H75: [*] 4107 (COGS - Wallcovering Textiles) | N75: =IFERROR(M75/SUMIFS(M:M, $H:$H, "[+] Net Sales"),0) -> 0 | P75: =IFERROR(O75/SUMIFS(O:O, $H:$H, "[+] Net Sales"),0) -> 0 | R75: =IFERROR(Q75/SUMIFS(Q:Q, $H:$H, "[+] Net Sales"),0) -> 0 | T75: =IFERROR(S75/SUMIFS(S:S, $H:$H, "[+] Net Sales"),0) -> 0 | U75: =IFERROR(($O75-M75)/ABS(M75),0) -> 0 | V75: =IFERROR((O75-$M75), 0-$M75) -> 0 | W75: =IFERROR((Q75-$M75)/ABS($M75),0) -> 0 | X75: =IFERROR((Q75-$M75), 0 -$M75) -> 0 | Y75: =IFERROR((S75-$M75)/ABS($M75),0) -> 0 | Z75: =IFERROR((S75-$M75),0-$M75) -> 0 | AC75: 0 | AD75: 0 | AE75: 0 | AF75: =IFERROR((AD75-$AC75)/ABS($AC75),0) -> 0 | AG75: =(AD75-$AC75) -> 0 | AH75: =IFERROR((AE75-$AC75)/ABS($AC75),0) -> 0 | AI75: =(AE75-$AC75) -> 0 | AK75: 0 | AL75: =IFERROR(AK75/SUMIFS(AK:AK, $H:$H, "[+] Net Sales"),0) -> 0 | AM75: 0 | AN75: =IFERROR(AM75/SUMIFS(AM:AM, $H:$H, "[+] Net Sales"),0) -> 0 | AO75: 0 | AP75: =IFERROR(AO75/SUMIFS(AO:AO, $H:$H, "[+] Net Sales"),0) -> 0 | AQ75: 0 | AR75: =IFERROR(AQ75/SUMIFS(AQ:AQ, $H:$H, "[+] Net Sales"),0) -> 0 | AS75: =IFERROR((AM75-$AK75)/ABS($AK75),0) -> 0 | AT75: =(AM75-$AK75) -> 0 | AU75: =IFERROR((AO75-$AK75)/ABS($AO75),0) -> 0 | AV75: =(AO75-$AK75) -> 0 | AW75: =IFERROR((AQ75-$AK75)/ABS($AK75),0) -> 0 | AX75: =(AQ75-$AK75) -> 0 | BA75: 0 | BB75: =IFERROR(BA75/SUMIFS(BA:BA, $H:$H, "[+] Net Sales"),0) -> 0 | BC75: 0 | BD75: =IFERROR(BC75/SUMIFS(BC:BC, $H:$H, "[+] Net Sales"),0) -> 0 | BE75: 0 | BF75: =IFERROR(BE75/SUMIFS(BE:BE, $H:$H, "[+] Net Sales"),0) -> 0 | BG75: =IFERROR((BC75-$BA75)/ABS($BA75),0) -> 0 | BH75: =(BC75-$BA75) -> 0 | BI75: =IFERROR((BE75-$BA75)/ABS($BA75),0) -> 0 | BJ75: =(BE75-$BA75) -> 0
H76: [*] 4108 (COGS - Labor - 3rd Party) | N76: =IFERROR(M76/SUMIFS(M:M, $H:$H, "[+] Net Sales"),0) -> 0 | P76: =IFERROR(O76/SUMIFS(O:O, $H:$H, "[+] Net Sales"),0) -> 0 | R76: =IFERROR(Q76/SUMIFS(Q:Q, $H:$H, "[+] Net Sales"),0) -> 0 | T76: =IFERROR(S76/SUMIFS(S:S, $H:$H, "[+] Net Sales"),0) -> 0 | U76: =IFERROR(($O76-M76)/ABS(M76),0) -> 0 | V76: =IFERROR((O76-$M76), 0-$M76) -> 0 | W76: =IFERROR((Q76-$M76)/ABS($M76),0) -> 0 | X76: =IFERROR((Q76-$M76), 0 -$M76) -> 0 | Y76: =IFERROR((S76-$M76)/ABS($M76),0) -> 0 | Z76: =IFERROR((S76-$M76),0-$M76) -> 0 | AC76: 0 | AD76: 0 | AE76: 0 | AF76: =IFERROR((AD76-$AC76)/ABS($AC76),0) -> 0 | AG76: =(AD76-$AC76) -> 0 | AH76: =IFERROR((AE76-$AC76)/ABS($AC76),0) -> 0 | AI76: =(AE76-$AC76) -> 0 | AK76: 0 | AL76: =IFERROR(AK76/SUMIFS(AK:AK, $H:$H, "[+] Net Sales"),0) -> 0 | AM76: 0 | AN76: =IFERROR(AM76/SUMIFS(AM:AM, $H:$H, "[+] Net Sales"),0) -> 0 | AO76: 0 | AP76: =IFERROR(AO76/SUMIFS(AO:AO, $H:$H, "[+] Net Sales"),0) -> 0 | AQ76: 0 | AR76: =IFERROR(AQ76/SUMIFS(AQ:AQ, $H:$H, "[+] Net Sales"),0) -> 0 | AS76: =IFERROR((AM76-$AK76)/ABS($AK76),0) -> 0 | AT76: =(AM76-$AK76) -> 0 | AU76: =IFERROR((AO76-$AK76)/ABS($AO76),0) -> 0 | AV76: =(AO76-$AK76) -> 0 | AW76: =IFERROR((AQ76-$AK76)/ABS($AK76),0) -> 0 | AX76: =(AQ76-$AK76) -> 0 | BA76: 0 | BB76: =IFERROR(BA76/SUMIFS(BA:BA, $H:$H, "[+] Net Sales"),0) -> 0 | BC76: 0 | BD76: =IFERROR(BC76/SUMIFS(BC:BC, $H:$H, "[+] Net Sales"),0) -> 0 | BE76: 0 | BF76: =IFERROR(BE76/SUMIFS(BE:BE, $H:$H, "[+] Net Sales"),0) -> 0 | BG76: =IFERROR((BC76-$BA76)/ABS($BA76),0) -> 0 | BH76: =(BC76-$BA76) -> 0 | BI76: =IFERROR((BE76-$BA76)/ABS($BA76),0) -> 0 | BJ76: =(BE76-$BA76) -> 0
H77: [*] 4109 (COGS - Labor - Intercompany) | N77: =IFERROR(M77/SUMIFS(M:M, $H:$H, "[+] Net Sales"),0) -> 0 | P77: =IFERROR(O77/SUMIFS(O:O, $H:$H, "[+] Net Sales"),0) -> 0 | R77: =IFERROR(Q77/SUMIFS(Q:Q, $H:$H, "[+] Net Sales"),0) -> 0 | T77: =IFERROR(S77/SUMIFS(S:S, $H:$H, "[+] Net Sales"),0) -> 0 | U77: =IFERROR(($O77-M77)/ABS(M77),0) -> 0 | V77: =IFERROR((O77-$M77), 0-$M77) -> 0 | W77: =IFERROR((Q77-$M77)/ABS($M77),0) -> 0 | X77: =IFERROR((Q77-$M77), 0 -$M77) -> 0 | Y77: =IFERROR((S77-$M77)/ABS($M77),0) -> 0 | Z77: =IFERROR((S77-$M77),0-$M77) -> 0 | AC77: 0 | AD77: 0 | AE77: 0 | AF77: =IFERROR((AD77-$AC77)/ABS($AC77),0) -> 0 | AG77: =(AD77-$AC77) -> 0 | AH77: =IFERROR((AE77-$AC77)/ABS($AC77),0) -> 0 | AI77: =(AE77-$AC77) -> 0 | AK77: 0 | AL77: =IFERROR(AK77/SUMIFS(AK:AK, $H:$H, "[+] Net Sales"),0) -> 0 | AM77: 0 | AN77: =IFERROR(AM77/SUMIFS(AM:AM, $H:$H, "[+] Net Sales"),0) -> 0 | AO77: 0 | AP77: =IFERROR(AO77/SUMIFS(AO:AO, $H:$H, "[+] Net Sales"),0) -> 0 | AQ77: 0 | AR77: =IFERROR(AQ77/SUMIFS(AQ:AQ, $H:$H, "[+] Net Sales"),0) -> 0 | AS77: =IFERROR((AM77-$AK77)/ABS($AK77),0) -> 0 | AT77: =(AM77-$AK77) -> 0 | AU77: =IFERROR((AO77-$AK77)/ABS($AO77),0) -> 0 | AV77: =(AO77-$AK77) -> 0 | AW77: =IFERROR((AQ77-$AK77)/ABS($AK77),0) -> 0 | AX77: =(AQ77-$AK77) -> 0 | BA77: 0 | BB77: =IFERROR(BA77/SUMIFS(BA:BA, $H:$H, "[+] Net Sales"),0) -> 0 | BC77: 0 | BD77: =IFERROR(BC77/SUMIFS(BC:BC, $H:$H, "[+] Net Sales"),0) -> 0 | BE77: 0 | BF77: =IFERROR(BE77/SUMIFS(BE:BE, $H:$H, "[+] Net Sales"),0) -> 0 | BG77: =IFERROR((BC77-$BA77)/ABS($BA77),0) -> 0 | BH77: =(BC77-$BA77) -> 0 | BI77: =IFERROR((BE77-$BA77)/ABS($BA77),0) -> 0 | BJ77: =(BE77-$BA77) -> 0
H78: [*] 4110 (Packaging & Other) | N78: =IFERROR(M78/SUMIFS(M:M, $H:$H, "[+] Net Sales"),0) -> 0 | P78: =IFERROR(O78/SUMIFS(O:O, $H:$H, "[+] Net Sales"),0) -> 0 | R78: =IFERROR(Q78/SUMIFS(Q:Q, $H:$H, "[+] Net Sales"),0) -> 0 | T78: =IFERROR(S78/SUMIFS(S:S, $H:$H, "[+] Net Sales"),0) -> 0 | U78: =IFERROR(($O78-M78)/ABS(M78),0) -> 0 | V78: =IFERROR((O78-$M78), 0-$M78) -> 0 | W78: =IFERROR((Q78-$M78)/ABS($M78),0) -> 0 | X78: =IFERROR((Q78-$M78), 0 -$M78) -> 0 | Y78: =IFERROR((S78-$M78)/ABS($M78),0) -> 0 | Z78: =IFERROR((S78-$M78),0-$M78) -> 0 | AC78: 0 | AD78: 0 | AE78: 0 | AF78: =IFERROR((AD78-$AC78)/ABS($AC78),0) -> 0 | AG78: =(AD78-$AC78) -> 0 | AH78: =IFERROR((AE78-$AC78)/ABS($AC78),0) -> 0 | AI78: =(AE78-$AC78) -> 0 | AK78: 0 | AL78: =IFERROR(AK78/SUMIFS(AK:AK, $H:$H, "[+] Net Sales"),0) -> 0 | AM78: 0 | AN78: =IFERROR(AM78/SUMIFS(AM:AM, $H:$H, "[+] Net Sales"),0) -> 0 | AO78: 0 | AP78: =IFERROR(AO78/SUMIFS(AO:AO, $H:$H, "[+] Net Sales"),0) -> 0 | AQ78: 0 | AR78: =IFERROR(AQ78/SUMIFS(AQ:AQ, $H:$H, "[+] Net Sales"),0) -> 0 | AS78: =IFERROR((AM78-$AK78)/ABS($AK78),0) -> 0 | AT78: =(AM78-$AK78) -> 0 | AU78: =IFERROR((AO78-$AK78)/ABS($AO78),0) -> 0 | AV78: =(AO78-$AK78) -> 0 | AW78: =IFERROR((AQ78-$AK78)/ABS($AK78),0) -> 0 | AX78: =(AQ78-$AK78) -> 0 | BA78: 0 | BB78: =IFERROR(BA78/SUMIFS(BA:BA, $H:$H, "[+] Net Sales"),0) -> 0 | BC78: 0 | BD78: =IFERROR(BC78/SUMIFS(BC:BC, $H:$H, "[+] Net Sales"),0) -> 0 | BE78: 0 | BF78: =IFERROR(BE78/SUMIFS(BE:BE, $H:$H, "[+] Net Sales"),0) -> 0 | BG78: =IFERROR((BC78-$BA78)/ABS($BA78),0) -> 0 | BH78: =(BC78-$BA78) -> 0 | BI78: =IFERROR((BE78-$BA78)/ABS($BA78),0) -> 0 | BJ78: =(BE78-$BA78) -> 0
H79: [*] 4111 (COGS - WIP - Intercompany) | N79: =IFERROR(M79/SUMIFS(M:M, $H:$H, "[+] Net Sales"),0) -> 0 | P79: =IFERROR(O79/SUMIFS(O:O, $H:$H, "[+] Net Sales"),0) -> 0 | R79: =IFERROR(Q79/SUMIFS(Q:Q, $H:$H, "[+] Net Sales"),0) -> 0 | T79: =IFERROR(S79/SUMIFS(S:S, $H:$H, "[+] Net Sales"),0) -> 0 | U79: =IFERROR(($O79-M79)/ABS(M79),0) -> 0 | V79: =IFERROR((O79-$M79), 0-$M79) -> 0 | W79: =IFERROR((Q79-$M79)/ABS($M79),0) -> 0 | X79: =IFERROR((Q79-$M79), 0 -$M79) -> 0 | Y79: =IFERROR((S79-$M79)/ABS($M79),0) -> 0 | Z79: =IFERROR((S79-$M79),0-$M79) -> 0 | AC79: 0 | AD79: 0 | AE79: 0 | AF79: =IFERROR((AD79-$AC79)/ABS($AC79),0) -> 0 | AG79: =(AD79-$AC79) -> 0 | AH79: =IFERROR((AE79-$AC79)/ABS($AC79),0) -> 0 | AI79: =(AE79-$AC79) -> 0 | AK79: 0 | AL79: =IFERROR(AK79/SUMIFS(AK:AK, $H:$H, "[+] Net Sales"),0) -> 0 | AM79: 0 | AN79: =IFERROR(AM79/SUMIFS(AM:AM, $H:$H, "[+] Net Sales"),0) -> 0 | AO79: 0 | AP79: =IFERROR(AO79/SUMIFS(AO:AO, $H:$H, "[+] Net Sales"),0) -> 0 | AQ79: 0 | AR79: =IFERROR(AQ79/SUMIFS(AQ:AQ, $H:$H, "[+] Net Sales"),0) -> 0 | AS79: =IFERROR((AM79-$AK79)/ABS($AK79),0) -> 0 | AT79: =(AM79-$AK79) -> 0 | AU79: =IFERROR((AO79-$AK79)/ABS($AO79),0) -> 0 | AV79: =(AO79-$AK79) -> 0 | AW79: =IFERROR((AQ79-$AK79)/ABS($AK79),0) -> 0 | AX79: =(AQ79-$AK79) -> 0 | BA79: 0 | BB79: =IFERROR(BA79/SUMIFS(BA:BA, $H:$H, "[+] Net Sales"),0) -> 0 | BC79: 0 | BD79: =IFERROR(BC79/SUMIFS(BC:BC, $H:$H, "[+] Net Sales"),0) -> 0 | BE79: 0 | BF79: =IFERROR(BE79/SUMIFS(BE:BE, $H:$H, "[+] Net Sales"),0) -> 0 | BG79: =IFERROR((BC79-$BA79)/ABS($BA79),0) -> 0 | BH79: =(BC79-$BA79) -> 0 | BI79: =IFERROR((BE79-$BA79)/ABS($BA79),0) -> 0 | BJ79: =(BE79-$BA79) -> 0
H80: [*] 4112 (COGS - WIP - 3rd Party) | N80: =IFERROR(M80/SUMIFS(M:M, $H:$H, "[+] Net Sales"),0) -> 0 | P80: =IFERROR(O80/SUMIFS(O:O, $H:$H, "[+] Net Sales"),0) -> 0 | R80: =IFERROR(Q80/SUMIFS(Q:Q, $H:$H, "[+] Net Sales"),0) -> 0 | T80: =IFERROR(S80/SUMIFS(S:S, $H:$H, "[+] Net Sales"),0) -> 0 | U80: =IFERROR(($O80-M80)/ABS(M80),0) -> 0 | V80: =IFERROR((O80-$M80), 0-$M80) -> 0 | W80: =IFERROR((Q80-$M80)/ABS($M80),0) -> 0 | X80: =IFERROR((Q80-$M80), 0 -$M80) -> 0 | Y80: =IFERROR((S80-$M80)/ABS($M80),0) -> 0 | Z80: =IFERROR((S80-$M80),0-$M80) -> 0 | AC80: 0 | AD80: 0 | AE80: 0 | AF80: =IFERROR((AD80-$AC80)/ABS($AC80),0) -> 0 | AG80: =(AD80-$AC80) -> 0 | AH80: =IFERROR((AE80-$AC80)/ABS($AC80),0) -> 0 | AI80: =(AE80-$AC80) -> 0 | AK80: 0 | AL80: =IFERROR(AK80/SUMIFS(AK:AK, $H:$H, "[+] Net Sales"),0) -> 0 | AM80: 0 | AN80: =IFERROR(AM80/SUMIFS(AM:AM, $H:$H, "[+] Net Sales"),0) -> 0 | AO80: 0 | AP80: =IFERROR(AO80/SUMIFS(AO:AO, $H:$H, "[+] Net Sales"),0) -> 0 | AQ80: 0 | AR80: =IFERROR(AQ80/SUMIFS(AQ:AQ, $H:$H, "[+] Net Sales"),0) -> 0 | AS80: =IFERROR((AM80-$AK80)/ABS($AK80),0) -> 0 | AT80: =(AM80-$AK80) -> 0 | AU80: =IFERROR((AO80-$AK80)/ABS($AO80),0) -> 0 | AV80: =(AO80-$AK80) -> 0 | AW80: =IFERROR((AQ80-$AK80)/ABS($AK80),0) -> 0 | AX80: =(AQ80-$AK80) -> 0 | BA80: 0 | BB80: =IFERROR(BA80/SUMIFS(BA:BA, $H:$H, "[+] Net Sales"),0) -> 0 | BC80: 0 | BD80: =IFERROR(BC80/SUMIFS(BC:BC, $H:$H, "[+] Net Sales"),0) -> 0 | BE80: 0 | BF80: =IFERROR(BE80/SUMIFS(BE:BE, $H:$H, "[+] Net Sales"),0) -> 0 | BG80: =IFERROR((BC80-$BA80)/ABS($BA80),0) -> 0 | BH80: =(BC80-$BA80) -> 0 | BI80: =IFERROR((BE80-$BA80)/ABS($BA80),0) -> 0 | BJ80: =(BE80-$BA80) -> 0
... H98: [*] 4940 (Graphics Printing-Graphics Printing--) | N98: =IFERROR(M98/SUMIFS(M:M, $H:$H, "[+] Net Sales"),0) -> 0 | P98: =IFERROR(O98/SUMIFS(O:O, $H:$H, "[+] Net Sales"),0) -> 0 | R98: =IFERROR(Q98/SUMIFS(Q:Q, $H:$H, "[+] Net Sales"),0) -> 0 | T98: =IFERROR(S98/SUMIFS(S:S, $H:$H, "[+] Net Sales"),0) -> 0 | U98: =IFERROR(($O98-M98)/ABS(M98),0) -> 0 | V98: =IFERROR((O98-$M98), 0-$M98) -> 0 | W98: =IFERROR((Q98-$M98)/ABS($M98),0) -> 0 | X98: =IFERROR((Q98-$M98), 0 -$M98) -> 0 | Y98: =IFERROR((S98-$M98)/ABS($M98),0) -> 0 | Z98: =IFERROR((S98-$M98),0-$M98) -> 0 | AC98: 0 | AD98: 0 | AE98: 0 | AF98: =IFERROR((AD98-$AC98)/ABS($AC98),0) -> 0 | AG98: =(AD98-$AC98) -> 0 | AH98: =IFERROR((AE98-$AC98)/ABS($AC98),0) -> 0 | AI98: =(AE98-$AC98) -> 0 | AK98: 0 | AL98: =IFERROR(AK98/SUMIFS(AK:AK, $H:$H, "[+] Net Sales"),0) -> 0 | AM98: 0 | AN98: =IFERROR(AM98/SUMIFS(AM:AM, $H:$H, "[+] Net Sales"),0) -> 0 | AO98: 0 | AP98: =IFERROR(AO98/SUMIFS(AO:AO, $H:$H, "[+] Net Sales"),0) -> 0 | AQ98: 0 | AR98: =IFERROR(AQ98/SUMIFS(AQ:AQ, $H:$H, "[+] Net Sales"),0) -> 0 | AS98: =IFERROR((AM98-$AK98)/ABS($AK98),0) -> 0 | AT98: =(AM98-$AK98) -> 0 | AU98: =IFERROR((AO98-$AK98)/ABS($AO98),0) -> 0 | AV98: =(AO98-$AK98) -> 0 | AW98: =IFERROR((AQ98-$AK98)/ABS($AK98),0) -> 0 | AX98: =(AQ98-$AK98) -> 0 | BA98: 0 | BB98: =IFERROR(BA98/SUMIFS(BA:BA, $H:$H, "[+] Net Sales"),0) -> 0 | BC98: 0 | BD98: =IFERROR(BC98/SUMIFS(BC:BC, $H:$H, "[+] Net Sales"),0) -> 0 | BE98: 0 | BF98: =IFERROR(BE98/SUMIFS(BE:BE, $H:$H, "[+] Net Sales"),0) -> 0 | BG98: =IFERROR((BC98-$BA98)/ABS($BA98),0) -> 0 | BH98: =(BC98-$BA98) -> 0 | BI98: =IFERROR((BE98-$BA98)/ABS($BA98),0) -> 0 | BJ98: =(BE98-$BA98) -> 0
H99: [+] Freight | M99: 0 | N99: =IFERROR(M99/SUMIFS(M:M, $H:$H, "[+] Net Sales"),0) -> 0 | O99: 0 | P99: =IFERROR(O99/SUMIFS(O:O, $H:$H, "[+] Net Sales"),0) -> 0 | Q99: 0 | R99: =IFERROR(Q99/SUMIFS(Q:Q, $H:$H, "[+] Net Sales"),0) -> 0 | S99: 0 | T99: =IFERROR(S99/SUMIFS(S:S, $H:$H, "[+] Net Sales"),0) -> 0 | U99: =IFERROR(($O99-M99)/ABS(M99),0) -> 0 | V99: =IFERROR((O99-$M99), 0-$M99) -> 0 | W99: =IFERROR((Q99-$M99)/ABS($M99),0) -> 0 | X99: =IFERROR((Q99-$M99), 0 -$M99) -> 0 | Y99: =IFERROR((S99-$M99)/ABS($M99),0) -> 0 | Z99: =IFERROR((S99-$M99),0-$M99) -> 0 | AC99: 0 | AD99: 0 | AE99: 0 | AF99: =IFERROR((AD99-$AC99)/ABS($AC99),0) -> 0 | AG99: =(AD99-$AC99) -> 0 | AH99: =IFERROR((AE99-$AC99)/ABS($AC99),0) -> 0 | AI99: =(AE99-$AC99) -> 0 | AK99: 0 | AL99: =IFERROR(AK99/SUMIFS(AK:AK, $H:$H, "[+] Net Sales"),0) -> 0 | AM99: 0 | AN99: =IFERROR(AM99/SUMIFS(AM:AM, $H:$H, "[+] Net Sales"),0) -> 0 | AO99: 0 | AP99: =IFERROR(AO99/SUMIFS(AO:AO, $H:$H, "[+] Net Sales"),0) -> 0 | AQ99: 0 | AR99: =IFERROR(AQ99/SUMIFS(AQ:AQ, $H:$H, "[+] Net Sales"),0) -> 0 | AS99: =IFERROR((AM99-$AK99)/ABS($AK99),0) -> 0 | AT99: =(AM99-$AK99) -> 0 | AU99: =IFERROR((AO99-$AK99)/ABS($AO99),0) -> 0 | AV99: =(AO99-$AK99) -> 0 | AW99: =IFERROR((AQ99-$AK99)/ABS($AK99),0) -> 0 | AX99: =(AQ99-$AK99) -> 0 | BA99: 0 | BB99: =IFERROR(BA99/SUMIFS(BA:BA, $H:$H, "[+] Net Sales"),0) -> 0 | BC99: 0 | BD99: =IFERROR(BC99/SUMIFS(BC:BC, $H:$H, "[+] Net Sales"),0) -> 0 | BE99: 0 | BF99: =IFERROR(BE99/SUMIFS(BE:BE, $H:$H, "[+] Net Sales"),0) -> 0 | BG99: =IFERROR((BC99-$BA99)/ABS($BA99),0) -> 0 | BH99: =(BC99-$BA99) -> 0 | BI99: =IFERROR((BE99-$BA99)/ABS($BA99),0) -> 0 | BJ99: =(BE99-$BA99) -> 0
H100: [+] Freight In | M100: 0 | N100: =IFERROR(M100/SUMIFS(M:M, $H:$H, "[+] Net Sales"),0) -> 0 | O100: 0 | P100: =IFERROR(O100/SUMIFS(O:O, $H:$H, "[+] Net Sales"),0) -> 0 | Q100: 0 | R100: =IFERROR(Q100/SUMIFS(Q:Q, $H:$H, "[+] Net Sales"),0) -> 0 | S100: 0 | T100: =IFERROR(S100/SUMIFS(S:S, $H:$H, "[+] Net Sales"),0) -> 0 | U100: =IFERROR(($O100-M100)/ABS(M100),0) -> 0 | V100: =IFERROR((O100-$M100), 0-$M100) -> 0 | W100: =IFERROR((Q100-$M100)/ABS($M100),0) -> 0 | X100: =IFERROR((Q100-$M100), 0 -$M100) -> 0 | Y100: =IFERROR((S100-$M100)/ABS($M100),0) -> 0 | Z100: =IFERROR((S100-$M100),0-$M100) -> 0 | AC100: 0 | AD100: 0 | AE100: 0 | AF100: =IFERROR((AD100-$AC100)/ABS($AC100),0) -> 0 | AG100: =(AD100-$AC100) -> 0 | AH100: =IFERROR((AE100-$AC100)/ABS($AC100),0) -> 0 | AI100: =(AE100-$AC100) -> 0 | AK100: 0 | AL100: =IFERROR(AK100/SUMIFS(AK:AK, $H:$H, "[+] Net Sales"),0) -> 0 | AM100: 0 | AN100: =IFERROR(AM100/SUMIFS(AM:AM, $H:$H, "[+] Net Sales"),0) -> 0 | AO100: 0 | AP100: =IFERROR(AO100/SUMIFS(AO:AO, $H:$H, "[+] Net Sales"),0) -> 0 | AQ100: 0 | AR100: =IFERROR(AQ100/SUMIFS(AQ:AQ, $H:$H, "[+] Net Sales"),0) -> 0 | AS100: =IFERROR((AM100-$AK100)/ABS($AK100),0) -> 0 | AT100: =(AM100-$AK100) -> 0 | AU100: =IFERROR((AO100-$AK100)/ABS($AO100),0) -> 0 | AV100: =(AO100-$AK100) -> 0 | AW100: =IFERROR((AQ100-$AK100)/ABS($AK100),0) -> 0 | AX100: =(AQ100-$AK100) -> 0 | BA100: 0 | BB100: =IFERROR(BA100/SUMIFS(BA:BA, $H:$H, "[+] Net Sales"),0) -> 0 | BC100: 0 | BD100: =IFERROR(BC100/SUMIFS(BC:BC, $H:$H, "[+] Net Sales"),0) -> 0 | BE100: 0 | BF100: =IFERROR(BE100/SUMIFS(BE:BE, $H:$H, "[+] Net Sales"),0) -> 0 | BG100: =IFERROR((BC100-$BA100)/ABS($BA100),0) -> 0 | BH100: =(BC100-$BA100) -> 0 | BI100: =IFERROR((BE100-$BA100)/ABS($BA100),0) -> 0 | BJ100: =(BE100-$BA100) -> 0
H101: [*] 4305 (Freight In Merchandise- Domestic) | N101: =IFERROR(M101/SUMIFS(M:M, $H:$H, "[+] Net Sales"),0) -> 0 | P101: =IFERROR(O101/SUMIFS(O:O, $H:$H, "[+] Net Sales"),0) -> 0 | R101: =IFERROR(Q101/SUMIFS(Q:Q, $H:$H, "[+] Net Sales"),0) -> 0 | T101: =IFERROR(S101/SUMIFS(S:S, $H:$H, "[+] Net Sales"),0) -> 0 | U101: =IFERROR(($O101-M101)/ABS(M101),0) -> 0 | V101: =IFERROR((O101-$M101), 0-$M101) -> 0 | W101: =IFERROR((Q101-$M101)/ABS($M101),0) -> 0 | X101: =IFERROR((Q101-$M101), 0 -$M101) -> 0 | Y101: =IFERROR((S101-$M101)/ABS($M101),0) -> 0 | Z101: =IFERROR((S101-$M101),0-$M101) -> 0 | AC101: 0 | AD101: 0 | AE101: 0 | AF101: =IFERROR((AD101-$AC101)/ABS($AC101),0) -> 0 | AG101: =(AD101-$AC101) -> 0 | AH101: =IFERROR((AE101-$AC101)/ABS($AC101),0) -> 0 | AI101: =(AE101-$AC101) -> 0 | AK101: 0 | AL101: =IFERROR(AK101/SUMIFS(AK:AK, $H:$H, "[+] Net Sales"),0) -> 0 | AM101: 0 | AN101: =IFERROR(AM101/SUMIFS(AM:AM, $H:$H, "[+] Net Sales"),0) -> 0 | AO101: 0 | AP101: =IFERROR(AO101/SUMIFS(AO:AO, $H:$H, "[+] Net Sales"),0) -> 0 | AQ101: 0 | AR101: =IFERROR(AQ101/SUMIFS(AQ:AQ, $H:$H, "[+] Net Sales"),0) -> 0 | AS101: =IFERROR((AM101-$AK101)/ABS($AK101),0) -> 0 | AT101: =(AM101-$AK101) -> 0 | AU101: =IFERROR((AO101-$AK101)/ABS($AO101),0) -> 0 | AV101: =(AO101-$AK101) -> 0 | AW101: =IFERROR((AQ101-$AK101)/ABS($AK101),0) -> 0 | AX101: =(AQ101-$AK101) -> 0 | BA101: 0 | BB101: =IFERROR(BA101/SUMIFS(BA:BA, $H:$H, "[+] Net Sales"),0) -> 0 | BC101: 0 | BD101: =IFERROR(BC101/SUMIFS(BC:BC, $H:$H, "[+] Net Sales"),0) -> 0 | BE101: 0 | BF101: =IFERROR(BE101/SUMIFS(BE:BE, $H:$H, "[+] Net Sales"),0) -> 0 | BG101: =IFERROR((BC101-$BA101)/ABS($BA101),0) -> 0 | BH101: =(BC101-$BA101) -> 0 | BI101: =IFERROR((BE101-$BA101)/ABS($BA101),0) -> 0 | BJ101: =(BE101-$BA101) -> 0
H102: [*] 4310 (Foreign Import Costs- Sea) | N102: =IFERROR(M102/SUMIFS(M:M, $H:$H, "[+] Net Sales"),0) -> 0 | P102: =IFERROR(O102/SUMIFS(O:O, $H:$H, "[+] Net Sales"),0) -> 0 | R102: =IFERROR(Q102/SUMIFS(Q:Q, $H:$H, "[+] Net Sales"),0) -> 0 | T102: =IFERROR(S102/SUMIFS(S:S, $H:$H, "[+] Net Sales"),0) -> 0 | U102: =IFERROR(($O102-M102)/ABS(M102),0) -> 0 | V102: =IFERROR((O102-$M102), 0-$M102) -> 0 | W102: =IFERROR((Q102-$M102)/ABS($M102),0) -> 0 | X102: =IFERROR((Q102-$M102), 0 -$M102) -> 0 | Y102: =IFERROR((S102-$M102)/ABS($M102),0) -> 0 | Z102: =IFERROR((S102-$M102),0-$M102) -> 0 | AC102: 0 | AD102: 0 | AE102: 0 | AF102: =IFERROR((AD102-$AC102)/ABS($AC102),0) -> 0 | AG102: =(AD102-$AC102) -> 0 | AH102: =IFERROR((AE102-$AC102)/ABS($AC102),0) -> 0 | AI102: =(AE102-$AC102) -> 0 | AK102: 0 | AL102: =IFERROR(AK102/SUMIFS(AK:AK, $H:$H, "[+] Net Sales"),0) -> 0 | AM102: 0 | AN102: =IFERROR(AM102/SUMIFS(AM:AM, $H:$H, "[+] Net Sales"),0) -> 0 | AO102: 0 | AP102: =IFERROR(AO102/SUMIFS(AO:AO, $H:$H, "[+] Net Sales"),0) -> 0 | AQ102: 0 | AR102: =IFERROR(AQ102/SUMIFS(AQ:AQ, $H:$H, "[+] Net Sales"),0) -> 0 | AS102: =IFERROR((AM102-$AK102)/ABS($AK102),0) -> 0 | AT102: =(AM102-$AK102) -> 0 | AU102: =IFERROR((AO102-$AK102)/ABS($AO102),0) -> 0 | AV102: =(AO102-$AK102) -> 0 | AW102: =IFERROR((AQ102-$AK102)/ABS($AK102),0) -> 0 | AX102: =(AQ102-$AK102) -> 0 | BA102: 0 | BB102: =IFERROR(BA102/SUMIFS(BA:BA, $H:$H, "[+] Net Sales"),0) -> 0 | BC102: 0 | BD102: =IFERROR(BC102/SUMIFS(BC:BC, $H:$H, "[+] Net Sales"),0) -> 0 | BE102: 0 | BF102: =IFERROR(BE102/SUMIFS(BE:BE, $H:$H, "[+] Net Sales"),0) -> 0 | BG102: =IFERROR((BC102-$BA102)/ABS($BA102),0) -> 0 | BH102: =(BC102-$BA102) -> 0 | BI102: =IFERROR((BE102-$BA102)/ABS($BA102),0) -> 0 | BJ102: =(BE102-$BA102) -> 0
H103: [*] 4311 (Foreign Import Costs - Air) | N103: =IFERROR(M103/SUMIFS(M:M, $H:$H, "[+] Net Sales"),0) -> 0 | P103: =IFERROR(O103/SUMIFS(O:O, $H:$H, "[+] Net Sales"),0) -> 0 | R103: =IFERROR(Q103/SUMIFS(Q:Q, $H:$H, "[+] Net Sales"),0) -> 0 | T103: =IFERROR(S103/SUMIFS(S:S, $H:$H, "[+] Net Sales"),0) -> 0 | U103: =IFERROR(($O103-M103)/ABS(M103),0) -> 0 | V103: =IFERROR((O103-$M103), 0-$M103) -> 0 | W103: =IFERROR((Q103-$M103)/ABS($M103),0) -> 0 | X103: =IFERROR((Q103-$M103), 0 -$M103) -> 0 | Y103: =IFERROR((S103-$M103)/ABS($M103),0) -> 0 | Z103: =IFERROR((S103-$M103),0-$M103) -> 0 | AC103: 0 | AD103: 0 | AE103: 0 | AF103: =IFERROR((AD103-$AC103)/ABS($AC103),0) -> 0 | AG103: =(AD103-$AC103) -> 0 | AH103: =IFERROR((AE103-$AC103)/ABS($AC103),0) -> 0 | AI103: =(AE103-$AC103) -> 0 | AK103: 0 | AL103: =IFERROR(AK103/SUMIFS(AK:AK, $H:$H, "[+] Net Sales"),0) -> 0 | AM103: 0 | AN103: =IFERROR(AM103/SUMIFS(AM:AM, $H:$H, "[+] Net Sales"),0) -> 0 | AO103: 0 | AP103: =IFERROR(AO103/SUMIFS(AO:AO, $H:$H, "[+] Net Sales"),0) -> 0 | AQ103: 0 | AR103: =IFERROR(AQ103/SUMIFS(AQ:AQ, $H:$H, "[+] Net Sales"),0) -> 0 | AS103: =IFERROR((AM103-$AK103)/ABS($AK103),0) -> 0 | AT103: =(AM103-$AK103) -> 0 | AU103: =IFERROR((AO103-$AK103)/ABS($AO103),0) -> 0 | AV103: =(AO103-$AK103) -> 0 | AW103: =IFERROR((AQ103-$AK103)/ABS($AK103),0) -> 0 | AX103: =(AQ103-$AK103) -> 0 | BA103: 0 | BB103: =IFERROR(BA103/SUMIFS(BA:BA, $H:$H, "[+] Net Sales"),0) -> 0 | BC103: 0 | BD103: =IFERROR(BC103/SUMIFS(BC:BC, $H:$H, "[+] Net Sales"),0) -> 0 | BE103: 0 | BF103: =IFERROR(BE103/SUMIFS(BE:BE, $H:$H, "[+] Net Sales"),0) -> 0 | BG103: =IFERROR((BC103-$BA103)/ABS($BA103),0) -> 0 | BH103: =(BC103-$BA103) -> 0 | BI103: =IFERROR((BE103-$BA103)/ABS($BA103),0) -> 0 | BJ103: =(BE103-$BA103) -> 0
H104: [*] 4312 (Foreign Import Costs - Ocean) | N104: =IFERROR(M104/SUMIFS(M:M, $H:$H, "[+] Net Sales"),0) -> 0 | P104: =IFERROR(O104/SUMIFS(O:O, $H:$H, "[+] Net Sales"),0) -> 0 | R104: =IFERROR(Q104/SUMIFS(Q:Q, $H:$H, "[+] Net Sales"),0) -> 0 | T104: =IFERROR(S104/SUMIFS(S:S, $H:$H, "[+] Net Sales"),0) -> 0 | U104: =IFERROR(($O104-M104)/ABS(M104),0) -> 0 | V104: =IFERROR((O104-$M104), 0-$M104) -> 0 | W104: =IFERROR((Q104-$M104)/ABS($M104),0) -> 0 | X104: =IFERROR((Q104-$M104), 0 -$M104) -> 0 | Y104: =IFERROR((S104-$M104)/ABS($M104),0) -> 0 | Z104: =IFERROR((S104-$M104),0-$M104) -> 0 | AC104: 0 | AD104: 0 | AE104: 0 | AF104: =IFERROR((AD104-$AC104)/ABS($AC104),0) -> 0 | AG104: =(AD104-$AC104) -> 0 | AH104: =IFERROR((AE104-$AC104)/ABS($AC104),0) -> 0 | AI104: =(AE104-$AC104) -> 0 | AK104: 0 | AL104: =IFERROR(AK104/SUMIFS(AK:AK, $H:$H, "[+] Net Sales"),0) -> 0 | AM104: 0 | AN104: =IFERROR(AM104/SUMIFS(AM:AM, $H:$H, "[+] Net Sales"),0) -> 0 | AO104: 0 | AP104: =IFERROR(AO104/SUMIFS(AO:AO, $H:$H, "[+] Net Sales"),0) -> 0 | AQ104: 0 | AR104: =IFERROR(AQ104/SUMIFS(AQ:AQ, $H:$H, "[+] Net Sales"),0) -> 0 | AS104: =IFERROR((AM104-$AK104)/ABS($AK104),0) -> 0 | AT104: =(AM104-$AK104) -> 0 | AU104: =IFERROR((AO104-$AK104)/ABS($AO104),0) -> 0 | AV104: =(AO104-$AK104) -> 0 | AW104: =IFERROR((AQ104-$AK104)/ABS($AK104),0) -> 0 | AX104: =(AQ104-$AK104) -> 0 | BA104: 0 | BB104: =IFERROR(BA104/SUMIFS(BA:BA, $H:$H, "[+] Net Sales"),0) -> 0 | BC104: 0 | BD104: =IFERROR(BC104/SUMIFS(BC:BC, $H:$H, "[+] Net Sales"),0) -> 0 | BE104: 0 | BF104: =IFERROR(BE104/SUMIFS(BE:BE, $H:$H, "[+] Net Sales"),0) -> 0 | BG104: =IFERROR((BC104-$BA104)/ABS($BA104),0) -> 0 | BH104: =(BC104-$BA104) -> 0 | BI104: =IFERROR((BE104-$BA104)/ABS($BA104),0) -> 0 | BJ104: =(BE104-$BA104) -> 0
H105: [*] 4313 (Foreign Import Costs - Customs Duty) | N105: =IFERROR(M105/SUMIFS(M:M, $H:$H, "[+] Net Sales"),0) -> 0 | P105: =IFERROR(O105/SUMIFS(O:O, $H:$H, "[+] Net Sales"),0) -> 0 | R105: =IFERROR(Q105/SUMIFS(Q:Q, $H:$H, "[+] Net Sales"),0) -> 0 | T105: =IFERROR(S105/SUMIFS(S:S, $H:$H, "[+] Net Sales"),0) -> 0 | U105: =IFERROR(($O105-M105)/ABS(M105),0) -> 0 | V105: =IFERROR((O105-$M105), 0-$M105) -> 0 | W105: =IFERROR((Q105-$M105)/ABS($M105),0) -> 0 | X105: =IFERROR((Q105-$M105), 0 -$M105) -> 0 | Y105: =IFERROR((S105-$M105)/ABS($M105),0) -> 0 | Z105: =IFERROR((S105-$M105),0-$M105) -> 0 | AC105: 0 | AD105: 0 | AE105: 0 | AF105: =IFERROR((AD105-$AC105)/ABS($AC105),0) -> 0 | AG105: =(AD105-$AC105) -> 0 | AH105: =IFERROR((AE105-$AC105)/ABS($AC105),0) -> 0 | AI105: =(AE105-$AC105) -> 0 | AK105: 0 | AL105: =IFERROR(AK105/SUMIFS(AK:AK, $H:$H, "[+] Net Sales"),0) -> 0 | AM105: 0 | AN105: =IFERROR(AM105/SUMIFS(AM:AM, $H:$H, "[+] Net Sales"),0) -> 0 | AO105: 0 | AP105: =IFERROR(AO105/SUMIFS(AO:AO, $H:$H, "[+] Net Sales"),0) -> 0 | AQ105: 0 | AR105: =IFERROR(AQ105/SUMIFS(AQ:AQ, $H:$H, "[+] Net Sales"),0) -> 0 | AS105: =IFERROR((AM105-$AK105)/ABS($AK105),0) -> 0 | AT105: =(AM105-$AK105) -> 0 | AU105: =IFERROR((AO105-$AK105)/ABS($AO105),0) -> 0 | AV105: =(AO105-$AK105) -> 0 | AW105: =IFERROR((AQ105-$AK105)/ABS($AK105),0) -> 0 | AX105: =(AQ105-$AK105) -> 0 | BA105: 0 | BB105: =IFERROR(BA105/SUMIFS(BA:BA, $H:$H, "[+] Net Sales"),0) -> 0 | BC105: 0 | BD105: =IFERROR(BC105/SUMIFS(BC:BC, $H:$H, "[+] Net Sales"),0) -> 0 | BE105: 0 | BF105: =IFERROR(BE105/SUMIFS(BE:BE, $H:$H, "[+] Net Sales"),0) -> 0 | BG105: =IFERROR((BC105-$BA105)/ABS($BA105),0) -> 0 | BH105: =(BC105-$BA105) -> 0 | BI105: =IFERROR((BE105-$BA105)/ABS($BA105),0) -> 0 | BJ105: =(BE105-$BA105) -> 0
H106: [*] 4319 (Foreign Import Costs - Misc Costs) | N106: =IFERROR(M106/SUMIFS(M:M, $H:$H, "[+] Net Sales"),0) -> 0 | P106: =IFERROR(O106/SUMIFS(O:O, $H:$H, "[+] Net Sales"),0) -> 0 | R106: =IFERROR(Q106/SUMIFS(Q:Q, $H:$H, "[+] Net Sales"),0) -> 0 | T106: =IFERROR(S106/SUMIFS(S:S, $H:$H, "[+] Net Sales"),0) -> 0 | U106: =IFERROR(($O106-M106)/ABS(M106),0) -> 0 | V106: =IFERROR((O106-$M106), 0-$M106) -> 0 | W106: =IFERROR((Q106-$M106)/ABS($M106),0) -> 0 | X106: =IFERROR((Q106-$M106), 0 -$M106) -> 0 | Y106: =IFERROR((S106-$M106)/ABS($M106),0) -> 0 | Z106: =IFERROR((S106-$M106),0-$M106) -> 0 | AC106: 0 | AD106: 0 | AE106: 0 | AF106: =IFERROR((AD106-$AC106)/ABS($AC106),0) -> 0 | AG106: =(AD106-$AC106) -> 0 | AH106: =IFERROR((AE106-$AC106)/ABS($AC106),0) -> 0 | AI106: =(AE106-$AC106) -> 0 | AK106: 0 | AL106: =IFERROR(AK106/SUMIFS(AK:AK, $H:$H, "[+] Net Sales"),0) -> 0 | AM106: 0 | AN106: =IFERROR(AM106/SUMIFS(AM:AM, $H:$H, "[+] Net Sales"),0) -> 0 | AO106: 0 | AP106: =IFERROR(AO106/SUMIFS(AO:AO, $H:$H, "[+] Net Sales"),0) -> 0 | AQ106: 0 | AR106: =IFERROR(AQ106/SUMIFS(AQ:AQ, $H:$H, "[+] Net Sales"),0) -> 0 | AS106: =IFERROR((AM106-$AK106)/ABS($AK106),0) -> 0 | AT106: =(AM106-$AK106) -> 0 | AU106: =IFERROR((AO106-$AK106)/ABS($AO106),0) -> 0 | AV106: =(AO106-$AK106) -> 0 | AW106: =IFERROR((AQ106-$AK106)/ABS($AK106),0) -> 0 | AX106: =(AQ106-$AK106) -> 0 | BA106: 0 | BB106: =IFERROR(BA106/SUMIFS(BA:BA, $H:$H, "[+] Net Sales"),0) -> 0 | BC106: 0 | BD106: =IFERROR(BC106/SUMIFS(BC:BC, $H:$H, "[+] Net Sales"),0) -> 0 | BE106: 0 | BF106: =IFERROR(BE106/SUMIFS(BE:BE, $H:$H, "[+] Net Sales"),0) -> 0 | BG106: =IFERROR((BC106-$BA106)/ABS($BA106),0) -> 0 | BH106: =(BC106-$BA106) -> 0 | BI106: =IFERROR((BE106-$BA106)/ABS($BA106),0) -> 0 | BJ106: =(BE106-$BA106) -> 0
H107: [*] 4375 (Landed Costs Absorbed) | N107: =IFERROR(M107/SUMIFS(M:M, $H:$H, "[+] Net Sales"),0) -> 0 | P107: =IFERROR(O107/SUMIFS(O:O, $H:$H, "[+] Net Sales"),0) -> 0 | R107: =IFERROR(Q107/SUMIFS(Q:Q, $H:$H, "[+] Net Sales"),0) -> 0 | T107: =IFERROR(S107/SUMIFS(S:S, $H:$H, "[+] Net Sales"),0) -> 0 | U107: =IFERROR(($O107-M107)/ABS(M107),0) -> 0 | V107: =IFERROR((O107-$M107), 0-$M107) -> 0 | W107: =IFERROR((Q107-$M107)/ABS($M107),0) -> 0 | X107: =IFERROR((Q107-$M107), 0 -$M107) -> 0 | Y107: =IFERROR((S107-$M107)/ABS($M107),0) -> 0 | Z107: =IFERROR((S107-$M107),0-$M107) -> 0 | AC107: 0 | AD107: 0 | AE107: 0 | AF107: =IFERROR((AD107-$AC107)/ABS($AC107),0) -> 0 | AG107: =(AD107-$AC107) -> 0 | AH107: =IFERROR((AE107-$AC107)/ABS($AC107),0) -> 0 | AI107: =(AE107-$AC107) -> 0 | AK107: 0 | AL107: =IFERROR(AK107/SUMIFS(AK:AK, $H:$H, "[+] Net Sales"),0) -> 0 | AM107: 0 | AN107: =IFERROR(AM107/SUMIFS(AM:AM, $H:$H, "[+] Net Sales"),0) -> 0 | AO107: 0 | AP107: =IFERROR(AO107/SUMIFS(AO:AO, $H:$H, "[+] Net Sales"),0) -> 0 | AQ107: 0 | AR107: =IFERROR(AQ107/SUMIFS(AQ:AQ, $H:$H, "[+] Net Sales"),0) -> 0 | AS107: =IFERROR((AM107-$AK107)/ABS($AK107),0) -> 0 | AT107: =(AM107-$AK107) -> 0 | AU107: =IFERROR((AO107-$AK107)/ABS($AO107),0) -> 0 | AV107: =(AO107-$AK107) -> 0 | AW107: =IFERROR((AQ107-$AK107)/ABS($AK107),0) -> 0 | AX107: =(AQ107-$AK107) -> 0 | BA107: 0 | BB107: =IFERROR(BA107/SUMIFS(BA:BA, $H:$H, "[+] Net Sales"),0) -> 0 | BC107: 0 | BD107: =IFERROR(BC107/SUMIFS(BC:BC, $H:$H, "[+] Net Sales"),0) -> 0 | BE107: 0 | BF107: =IFERROR(BE107/SUMIFS(BE:BE, $H:$H, "[+] Net Sales"),0) -> 0 | BG107: =IFERROR((BC107-$BA107)/ABS($BA107),0) -> 0 | BH107: =(BC107-$BA107) -> 0 | BI107: =IFERROR((BE107-$BA107)/ABS($BA107),0) -> 0 | BJ107: =(BE107-$BA107) -> 0
H108: [*] 4376 (Landed Costs Absorbed - Freight) | N108: =IFERROR(M108/SUMIFS(M:M, $H:$H, "[+] Net Sales"),0) -> 0 | P108: =IFERROR(O108/SUMIFS(O:O, $H:$H, "[+] Net Sales"),0) -> 0 | R108: =IFERROR(Q108/SUMIFS(Q:Q, $H:$H, "[+] Net Sales"),0) -> 0 | T108: =IFERROR(S108/SUMIFS(S:S, $H:$H, "[+] Net Sales"),0) -> 0 | U108: =IFERROR(($O108-M108)/ABS(M108),0) -> 0 | V108: =IFERROR((O108-$M108), 0-$M108) -> 0 | W108: =IFERROR((Q108-$M108)/ABS($M108),0) -> 0 | X108: =IFERROR((Q108-$M108), 0 -$M108) -> 0 | Y108: =IFERROR((S108-$M108)/ABS($M108),0) -> 0 | Z108: =IFERROR((S108-$M108),0-$M108) -> 0 | AC108: 0 | AD108: 0 | AE108: 0 | AF108: =IFERROR((AD108-$AC108)/ABS($AC108),0) -> 0 | AG108: =(AD108-$AC108) -> 0 | AH108: =IFERROR((AE108-$AC108)/ABS($AC108),0) -> 0 | AI108: =(AE108-$AC108) -> 0 | AK108: 0 | AL108: =IFERROR(AK108/SUMIFS(AK:AK, $H:$H, "[+] Net Sales"),0) -> 0 | AM108: 0 | AN108: =IFERROR(AM108/SUMIFS(AM:AM, $H:$H, "[+] Net Sales"),0) -> 0 | AO108: 0 | AP108: =IFERROR(AO108/SUMIFS(AO:AO, $H:$H, "[+] Net Sales"),0) -> 0 | AQ108: 0 | AR108: =IFERROR(AQ108/SUMIFS(AQ:AQ, $H:$H, "[+] Net Sales"),0) -> 0 | AS108: =IFERROR((AM108-$AK108)/ABS($AK108),0) -> 0 | AT108: =(AM108-$AK108) -> 0 | AU108: =IFERROR((AO108-$AK108)/ABS($AO108),0) -> 0 | AV108: =(AO108-$AK108) -> 0 | AW108: =IFERROR((AQ108-$AK108)/ABS($AK108),0) -> 0 | AX108: =(AQ108-$AK108) -> 0 | BA108: 0 | BB108: =IFERROR(BA108/SUMIFS(BA:BA, $H:$H, "[+] Net Sales"),0) -> 0 | BC108: 0 | BD108: =IFERROR(BC108/SUMIFS(BC:BC, $H:$H, "[+] Net Sales"),0) -> 0 | BE108: 0 | BF108: =IFERROR(BE108/SUMIFS(BE:BE, $H:$H, "[+] Net Sales"),0) -> 0 | BG108: =IFERROR((BC108-$BA108)/ABS($BA108),0) -> 0 | BH108: =(BC108-$BA108) -> 0 | BI108: =IFERROR((BE108-$BA108)/ABS($BA108),0) -> 0 | BJ108: =(BE108-$BA108) -> 0
H109: [+] Freight Out | M109: 0 | N109: =IFERROR(M109/SUMIFS(M:M, $H:$H, "[+] Net Sales"),0) -> 0 | O109: 0 | P109: =IFERROR(O109/SUMIFS(O:O, $H:$H, "[+] Net Sales"),0) -> 0 | Q109: 0 | R109: =IFERROR(Q109/SUMIFS(Q:Q, $H:$H, "[+] Net Sales"),0) -> 0 | S109: 0 | T109: =IFERROR(S109/SUMIFS(S:S, $H:$H, "[+] Net Sales"),0) -> 0 | U109: =IFERROR(($O109-M109)/ABS(M109),0) -> 0 | V109: =IFERROR((O109-$M109), 0-$M109) -> 0 | W109: =IFERROR((Q109-$M109)/ABS($M109),0) -> 0 | X109: =IFERROR((Q109-$M109), 0 -$M109) -> 0 | Y109: =IFERROR((S109-$M109)/ABS($M109),0) -> 0 | Z109: =IFERROR((S109-$M109),0-$M109) -> 0 | AC109: 0 | AD109: 0 | AE109: 0 | AF109: =IFERROR((AD109-$AC109)/ABS($AC109),0) -> 0 | AG109: =(AD109-$AC109) -> 0 | AH109: =IFERROR((AE109-$AC109)/ABS($AC109),0) -> 0 | AI109: =(AE109-$AC109) -> 0 | AK109: 0 | AL109: =IFERROR(AK109/SUMIFS(AK:AK, $H:$H, "[+] Net Sales"),0) -> 0 | AM109: 0 | AN109: =IFERROR(AM109/SUMIFS(AM:AM, $H:$H, "[+] Net Sales"),0) -> 0 | AO109: 0 | AP109: =IFERROR(AO109/SUMIFS(AO:AO, $H:$H, "[+] Net Sales"),0) -> 0 | AQ109: 0 | AR109: =IFERROR(AQ109/SUMIFS(AQ:AQ, $H:$H, "[+] Net Sales"),0) -> 0 | AS109: =IFERROR((AM109-$AK109)/ABS($AK109),0) -> 0 | AT109: =(AM109-$AK109) -> 0 | AU109: =IFERROR((AO109-$AK109)/ABS($AO109),0) -> 0 | AV109: =(AO109-$AK109) -> 0 | AW109: =IFERROR((AQ109-$AK109)/ABS($AK109),0) -> 0 | AX109: =(AQ109-$AK109) -> 0 | BA109: 0 | BB109: =IFERROR(BA109/SUMIFS(BA:BA, $H:$H, "[+] Net Sales"),0) -> 0 | BC109: 0 | BD109: =IFERROR(BC109/SUMIFS(BC:BC, $H:$H, "[+] Net Sales"),0) -> 0 | BE109: 0 | BF109: =IFERROR(BE109/SUMIFS(BE:BE, $H:$H, "[+] Net Sales"),0) -> 0 | BG109: =IFERROR((BC109-$BA109)/ABS($BA109),0) -> 0 | BH109: =(BC109-$BA109) -> 0 | BI109: =IFERROR((BE109-$BA109)/ABS($BA109),0) -> 0 | BJ109: =(BE109-$BA109) -> 0
H110: [*] 4325 (Freight Out Merchandise- Domestic) | N110: =IFERROR(M110/SUMIFS(M:M, $H:$H, "[+] Net Sales"),0) -> 0 | P110: =IFERROR(O110/SUMIFS(O:O, $H:$H, "[+] Net Sales"),0) -> 0 | R110: =IFERROR(Q110/SUMIFS(Q:Q, $H:$H, "[+] Net Sales"),0) -> 0 | T110: =IFERROR(S110/SUMIFS(S:S, $H:$H, "[+] Net Sales"),0) -> 0 | U110: =IFERROR(($O110-M110)/ABS(M110),0) -> 0 | V110: =IFERROR((O110-$M110), 0-$M110) -> 0 | W110: =IFERROR((Q110-$M110)/ABS($M110),0) -> 0 | X110: =IFERROR((Q110-$M110), 0 -$M110) -> 0 | Y110: =IFERROR((S110-$M110)/ABS($M110),0) -> 0 | Z110: =IFERROR((S110-$M110),0-$M110) -> 0 | AC110: 0 | AD110: 0 | AE110: 0 | AF110: =IFERROR((AD110-$AC110)/ABS($AC110),0) -> 0 | AG110: =(AD110-$AC110) -> 0 | AH110: =IFERROR((AE110-$AC110)/ABS($AC110),0) -> 0 | AI110: =(AE110-$AC110) -> 0 | AK110: 0 | AL110: =IFERROR(AK110/SUMIFS(AK:AK, $H:$H, "[+] Net Sales"),0) -> 0 | AM110: 0 | AN110: =IFERROR(AM110/SUMIFS(AM:AM, $H:$H, "[+] Net Sales"),0) -> 0 | AO110: 0 | AP110: =IFERROR(AO110/SUMIFS(AO:AO, $H:$H, "[+] Net Sales"),0) -> 0 | AQ110: 0 | AR110: =IFERROR(AQ110/SUMIFS(AQ:AQ, $H:$H, "[+] Net Sales"),0) -> 0 | AS110: =IFERROR((AM110-$AK110)/ABS($AK110),0) -> 0 | AT110: =(AM110-$AK110) -> 0 | AU110: =IFERROR((AO110-$AK110)/ABS($AO110),0) -> 0 | AV110: =(AO110-$AK110) -> 0 | AW110: =IFERROR((AQ110-$AK110)/ABS($AK110),0) -> 0 | AX110: =(AQ110-$AK110) -> 0 | BA110: 0 | BB110: =IFERROR(BA110/SUMIFS(BA:BA, $H:$H, "[+] Net Sales"),0) -> 0 | BC110: 0 | BD110: =IFERROR(BC110/SUMIFS(BC:BC, $H:$H, "[+] Net Sales"),0) -> 0 | BE110: 0 | BF110: =IFERROR(BE110/SUMIFS(BE:BE, $H:$H, "[+] Net Sales"),0) -> 0 | BG110: =IFERROR((BC110-$BA110)/ABS($BA110),0) -> 0 | BH110: =(BC110-$BA110) -> 0 | BI110: =IFERROR((BE110-$BA110)/ABS($BA110),0) -> 0 | BJ110: =(BE110-$BA110) -> 0
H111: [*] 4327 (Freight Out Merchandise - Paid) | N111: =IFERROR(M111/SUMIFS(M:M, $H:$H, "[+] Net Sales"),0) -> 0 | P111: =IFERROR(O111/SUMIFS(O:O, $H:$H, "[+] Net Sales"),0) -> 0 | R111: =IFERROR(Q111/SUMIFS(Q:Q, $H:$H, "[+] Net Sales"),0) -> 0 | T111: =IFERROR(S111/SUMIFS(S:S, $H:$H, "[+] Net Sales"),0) -> 0 | U111: =IFERROR(($O111-M111)/ABS(M111),0) -> 0 | V111: =IFERROR((O111-$M111), 0-$M111) -> 0 | W111: =IFERROR((Q111-$M111)/ABS($M111),0) -> 0 | X111: =IFERROR((Q111-$M111), 0 -$M111) -> 0 | Y111: =IFERROR((S111-$M111)/ABS($M111),0) -> 0 | Z111: =IFERROR((S111-$M111),0-$M111) -> 0 | AC111: 0 | AD111: 0 | AE111: 0 | AF111: =IFERROR((AD111-$AC111)/ABS($AC111),0) -> 0 | AG111: =(AD111-$AC111) -> 0 | AH111: =IFERROR((AE111-$AC111)/ABS($AC111),0) -> 0 | AI111: =(AE111-$AC111) -> 0 | AK111: 0 | AL111: =IFERROR(AK111/SUMIFS(AK:AK, $H:$H, "[+] Net Sales"),0) -> 0 | AM111: 0 | AN111: =IFERROR(AM111/SUMIFS(AM:AM, $H:$H, "[+] Net Sales"),0) -> 0 | AO111: 0 | AP111: =IFERROR(AO111/SUMIFS(AO:AO, $H:$H, "[+] Net Sales"),0) -> 0 | AQ111: 0 | AR111: =IFERROR(AQ111/SUMIFS(AQ:AQ, $H:$H, "[+] Net Sales"),0) -> 0 | AS111: =IFERROR((AM111-$AK111)/ABS($AK111),0) -> 0 | AT111: =(AM111-$AK111) -> 0 | AU111: =IFERROR((AO111-$AK111)/ABS($AO111),0) -> 0 | AV111: =(AO111-$AK111) -> 0 | AW111: =IFERROR((AQ111-$AK111)/ABS($AK111),0) -> 0 | AX111: =(AQ111-$AK111) -> 0 | BA111: 0 | BB111: =IFERROR(BA111/SUMIFS(BA:BA, $H:$H, "[+] Net Sales"),0) -> 0 | BC111: 0 | BD111: =IFERROR(BC111/SUMIFS(BC:BC, $H:$H, "[+] Net Sales"),0) -> 0 | BE111: 0 | BF111: =IFERROR(BE111/SUMIFS(BE:BE, $H:$H, "[+] Net Sales"),0) -> 0 | BG111: =IFERROR((BC111-$BA111)/ABS($BA111),0) -> 0 | BH111: =(BC111-$BA111) -> 0 | BI111: =IFERROR((BE111-$BA111)/ABS($BA111),0) -> 0 | BJ111: =(BE111-$BA111) -> 0
H112: [*] 4330 (Foreign Export Costs) | N112: =IFERROR(M112/SUMIFS(M:M, $H:$H, "[+] Net Sales"),0) -> 0 | P112: =IFERROR(O112/SUMIFS(O:O, $H:$H, "[+] Net Sales"),0) -> 0 | R112: =IFERROR(Q112/SUMIFS(Q:Q, $H:$H, "[+] Net Sales"),0) -> 0 | T112: =IFERROR(S112/SUMIFS(S:S, $H:$H, "[+] Net Sales"),0) -> 0 | U112: =IFERROR(($O112-M112)/ABS(M112),0) -> 0 | V112: =IFERROR((O112-$M112), 0-$M112) -> 0 | W112: =IFERROR((Q112-$M112)/ABS($M112),0) -> 0 | X112: =IFERROR((Q112-$M112), 0 -$M112) -> 0 | Y112: =IFERROR((S112-$M112)/ABS($M112),0) -> 0 | Z112: =IFERROR((S112-$M112),0-$M112) -> 0 | AC112: 0 | AD112: 0 | AE112: 0 | AF112: =IFERROR((AD112-$AC112)/ABS($AC112),0) -> 0 | AG112: =(AD112-$AC112) -> 0 | AH112: =IFERROR((AE112-$AC112)/ABS($AC112),0) -> 0 | AI112: =(AE112-$AC112) -> 0 | AK112: 0 | AL112: =IFERROR(AK112/SUMIFS(AK:AK, $H:$H, "[+] Net Sales"),0) -> 0 | AM112: 0 | AN112: =IFERROR(AM112/SUMIFS(AM:AM, $H:$H, "[+] Net Sales"),0) -> 0 | AO112: 0 | AP112: =IFERROR(AO112/SUMIFS(AO:AO, $H:$H, "[+] Net Sales"),0) -> 0 | AQ112: 0 | AR112: =IFERROR(AQ112/SUMIFS(AQ:AQ, $H:$H, "[+] Net Sales"),0) -> 0 | AS112: =IFERROR((AM112-$AK112)/ABS($AK112),0) -> 0 | AT112: =(AM112-$AK112) -> 0 | AU112: =IFERROR((AO112-$AK112)/ABS($AO112),0) -> 0 | AV112: =(AO112-$AK112) -> 0 | AW112: =IFERROR((AQ112-$AK112)/ABS($AK112),0) -> 0 | AX112: =(AQ112-$AK112) -> 0 | BA112: 0 | BB112: =IFERROR(BA112/SUMIFS(BA:BA, $H:$H, "[+] Net Sales"),0) -> 0 | BC112: 0 | BD112: =IFERROR(BC112/SUMIFS(BC:BC, $H:$H, "[+] Net Sales"),0) -> 0 | BE112: 0 | BF112: =IFERROR(BE112/SUMIFS(BE:BE, $H:$H, "[+] Net Sales"),0) -> 0 | BG112: =IFERROR((BC112-$BA112)/ABS($BA112),0) -> 0 | BH112: =(BC112-$BA112) -> 0 | BI112: =IFERROR((BE112-$BA112)/ABS($BA112),0) -> 0 | BJ112: =(BE112-$BA112) -> 0
H113: [*] 4331 (Foreign Export Costs - Air) | N113: =IFERROR(M113/SUMIFS(M:M, $H:$H, "[+] Net Sales"),0) -> 0 | P113: =IFERROR(O113/SUMIFS(O:O, $H:$H, "[+] Net Sales"),0) -> 0 | R113: =IFERROR(Q113/SUMIFS(Q:Q, $H:$H, "[+] Net Sales"),0) -> 0 | T113: =IFERROR(S113/SUMIFS(S:S, $H:$H, "[+] Net Sales"),0) -> 0 | U113: =IFERROR(($O113-M113)/ABS(M113),0) -> 0 | V113: =IFERROR((O113-$M113), 0-$M113) -> 0 | W113: =IFERROR((Q113-$M113)/ABS($M113),0) -> 0 | X113: =IFERROR((Q113-$M113), 0 -$M113) -> 0 | Y113: =IFERROR((S113-$M113)/ABS($M113),0) -> 0 | Z113: =IFERROR((S113-$M113),0-$M113) -> 0 | AC113: 0 | AD113: 0 | AE113: 0 | AF113: =IFERROR((AD113-$AC113)/ABS($AC113),0) -> 0 | AG113: =(AD113-$AC113) -> 0 | AH113: =IFERROR((AE113-$AC113)/ABS($AC113),0) -> 0 | AI113: =(AE113-$AC113) -> 0 | AK113: 0 | AL113: =IFERROR(AK113/SUMIFS(AK:AK, $H:$H, "[+] Net Sales"),0) -> 0 | AM113: 0 | AN113: =IFERROR(AM113/SUMIFS(AM:AM, $H:$H, "[+] Net Sales"),0) -> 0 | AO113: 0 | AP113: =IFERROR(AO113/SUMIFS(AO:AO, $H:$H, "[+] Net Sales"),0) -> 0 | AQ113: 0 | AR113: =IFERROR(AQ113/SUMIFS(AQ:AQ, $H:$H, "[+] Net Sales"),0) -> 0 | AS113: =IFERROR((AM113-$AK113)/ABS($AK113),0) -> 0 | AT113: =(AM113-$AK113) -> 0 | AU113: =IFERROR((AO113-$AK113)/ABS($AO113),0) -> 0 | AV113: =(AO113-$AK113) -> 0 | AW113: =IFERROR((AQ113-$AK113)/ABS($AK113),0) -> 0 | AX113: =(AQ113-$AK113) -> 0 | BA113: 0 | BB113: =IFERROR(BA113/SUMIFS(BA:BA, $H:$H, "[+] Net Sales"),0) -> 0 | BC113: 0 | BD113: =IFERROR(BC113/SUMIFS(BC:BC, $H:$H, "[+] Net Sales"),0) -> 0 | BE113: 0 | BF113: =IFERROR(BE113/SUMIFS(BE:BE, $H:$H, "[+] Net Sales"),0) -> 0 | BG113: =IFERROR((BC113-$BA113)/ABS($BA113),0) -> 0 | BH113: =(BC113-$BA113) -> 0 | BI113: =IFERROR((BE113-$BA113)/ABS($BA113),0) -> 0 | BJ113: =(BE113-$BA113) -> 0
H114: [*] 4333 (Foreign Export Costs - Customs Duty) | N114: =IFERROR(M114/SUMIFS(M:M, $H:$H, "[+] Net Sales"),0) -> 0 | P114: =IFERROR(O114/SUMIFS(O:O, $H:$H, "[+] Net Sales"),0) -> 0 | R114: =IFERROR(Q114/SUMIFS(Q:Q, $H:$H, "[+] Net Sales"),0) -> 0 | T114: =IFERROR(S114/SUMIFS(S:S, $H:$H, "[+] Net Sales"),0) -> 0 | U114: =IFERROR(($O114-M114)/ABS(M114),0) -> 0 | V114: =IFERROR((O114-$M114), 0-$M114) -> 0 | W114: =IFERROR((Q114-$M114)/ABS($M114),0) -> 0 | X114: =IFERROR((Q114-$M114), 0 -$M114) -> 0 | Y114: =IFERROR((S114-$M114)/ABS($M114),0) -> 0 | Z114: =IFERROR((S114-$M114),0-$M114) -> 0 | AC114: 0 | AD114: 0 | AE114: 0 | AF114: =IFERROR((AD114-$AC114)/ABS($AC114),0) -> 0 | AG114: =(AD114-$AC114) -> 0 | AH114: =IFERROR((AE114-$AC114)/ABS($AC114),0) -> 0 | AI114: =(AE114-$AC114) -> 0 | AK114: 0 | AL114: =IFERROR(AK114/SUMIFS(AK:AK, $H:$H, "[+] Net Sales"),0) -> 0 | AM114: 0 | AN114: =IFERROR(AM114/SUMIFS(AM:AM, $H:$H, "[+] Net Sales"),0) -> 0 | AO114: 0 | AP114: =IFERROR(AO114/SUMIFS(AO:AO, $H:$H, "[+] Net Sales"),0) -> 0 | AQ114: 0 | AR114: =IFERROR(AQ114/SUMIFS(AQ:AQ, $H:$H, "[+] Net Sales"),0) -> 0 | AS114: =IFERROR((AM114-$AK114)/ABS($AK114),0) -> 0 | AT114: =(AM114-$AK114) -> 0 | AU114: =IFERROR((AO114-$AK114)/ABS($AO114),0) -> 0 | AV114: =(AO114-$AK114) -> 0 | AW114: =IFERROR((AQ114-$AK114)/ABS($AK114),0) -> 0 | AX114: =(AQ114-$AK114) -> 0 | BA114: 0 | BB114: =IFERROR(BA114/SUMIFS(BA:BA, $H:$H, "[+] Net Sales"),0) -> 0 | BC114: 0 | BD114: =IFERROR(BC114/SUMIFS(BC:BC, $H:$H, "[+] Net Sales"),0) -> 0 | BE114: 0 | BF114: =IFERROR(BE114/SUMIFS(BE:BE, $H:$H, "[+] Net Sales"),0) -> 0 | BG114: =IFERROR((BC114-$BA114)/ABS($BA114),0) -> 0 | BH114: =(BC114-$BA114) -> 0 | BI114: =IFERROR((BE114-$BA114)/ABS($BA114),0) -> 0 | BJ114: =(BE114-$BA114) -> 0
H115: [*] 4339 (Foreign Export Costs - Misc) | N115: =IFERROR(M115/SUMIFS(M:M, $H:$H, "[+] Net Sales"),0) -> 0 | P115: =IFERROR(O115/SUMIFS(O:O, $H:$H, "[+] Net Sales"),0) -> 0 | R115: =IFERROR(Q115/SUMIFS(Q:Q, $H:$H, "[+] Net Sales"),0) -> 0 | T115: =IFERROR(S115/SUMIFS(S:S, $H:$H, "[+] Net Sales"),0) -> 0 | U115: =IFERROR(($O115-M115)/ABS(M115),0) -> 0 | V115: =IFERROR((O115-$M115), 0-$M115) -> 0 | W115: =IFERROR((Q115-$M115)/ABS($M115),0) -> 0 | X115: =IFERROR((Q115-$M115), 0 -$M115) -> 0 | Y115: =IFERROR((S115-$M115)/ABS($M115),0) -> 0 | Z115: =IFERROR((S115-$M115),0-$M115) -> 0 | AC115: 0 | AD115: 0 | AE115: 0 | AF115: =IFERROR((AD115-$AC115)/ABS($AC115),0) -> 0 | AG115: =(AD115-$AC115) -> 0 | AH115: =IFERROR((AE115-$AC115)/ABS($AC115),0) -> 0 | AI115: =(AE115-$AC115) -> 0 | AK115: 0 | AL115: =IFERROR(AK115/SUMIFS(AK:AK, $H:$H, "[+] Net Sales"),0) -> 0 | AM115: 0 | AN115: =IFERROR(AM115/SUMIFS(AM:AM, $H:$H, "[+] Net Sales"),0) -> 0 | AO115: 0 | AP115: =IFERROR(AO115/SUMIFS(AO:AO, $H:$H, "[+] Net Sales"),0) -> 0 | AQ115: 0 | AR115: =IFERROR(AQ115/SUMIFS(AQ:AQ, $H:$H, "[+] Net Sales"),0) -> 0 | AS115: =IFERROR((AM115-$AK115)/ABS($AK115),0) -> 0 | AT115: =(AM115-$AK115) -> 0 | AU115: =IFERROR((AO115-$AK115)/ABS($AO115),0) -> 0 | AV115: =(AO115-$AK115) -> 0 | AW115: =IFERROR((AQ115-$AK115)/ABS($AK115),0) -> 0 | AX115: =(AQ115-$AK115) -> 0 | BA115: 0 | BB115: =IFERROR(BA115/SUMIFS(BA:BA, $H:$H, "[+] Net Sales"),0) -> 0 | BC115: 0 | BD115: =IFERROR(BC115/SUMIFS(BC:BC, $H:$H, "[+] Net Sales"),0) -> 0 | BE115: 0 | BF115: =IFERROR(BE115/SUMIFS(BE:BE, $H:$H, "[+] Net Sales"),0) -> 0 | BG115: =IFERROR((BC115-$BA115)/ABS($BA115),0) -> 0 | BH115: =(BC115-$BA115) -> 0 | BI115: =IFERROR((BE115-$BA115)/ABS($BA115),0) -> 0 | BJ115: =(BE115-$BA115) -> 0
H116: [*] 4390 (Freight Allocation) | N116: =IFERROR(M116/SUMIFS(M:M, $H:$H, "[+] Net Sales"),0) -> 0 | P116: =IFERROR(O116/SUMIFS(O:O, $H:$H, "[+] Net Sales"),0) -> 0 | R116: =IFERROR(Q116/SUMIFS(Q:Q, $H:$H, "[+] Net Sales"),0) -> 0 | T116: =IFERROR(S116/SUMIFS(S:S, $H:$H, "[+] Net Sales"),0) -> 0 | U116: =IFERROR(($O116-M116)/ABS(M116),0) -> 0 | V116: =IFERROR((O116-$M116), 0-$M116) -> 0 | W116: =IFERROR((Q116-$M116)/ABS($M116),0) -> 0 | X116: =IFERROR((Q116-$M116), 0 -$M116) -> 0 | Y116: =IFERROR((S116-$M116)/ABS($M116),0) -> 0 | Z116: =IFERROR((S116-$M116),0-$M116) -> 0 | AC116: 0 | AD116: 0 | AE116: 0 | AF116: =IFERROR((AD116-$AC116)/ABS($AC116),0) -> 0 | AG116: =(AD116-$AC116) -> 0 | AH116: =IFERROR((AE116-$AC116)/ABS($AC116),0) -> 0 | AI116: =(AE116-$AC116) -> 0 | AK116: 0 | AL116: =IFERROR(AK116/SUMIFS(AK:AK, $H:$H, "[+] Net Sales"),0) -> 0 | AM116: 0 | AN116: =IFERROR(AM116/SUMIFS(AM:AM, $H:$H, "[+] Net Sales"),0) -> 0 | AO116: 0 | AP116: =IFERROR(AO116/SUMIFS(AO:AO, $H:$H, "[+] Net Sales"),0) -> 0 | AQ116: 0 | AR116: =IFERROR(AQ116/SUMIFS(AQ:AQ, $H:$H, "[+] Net Sales"),0) -> 0 | AS116: =IFERROR((AM116-$AK116)/ABS($AK116),0) -> 0 | AT116: =(AM116-$AK116) -> 0 | AU116: =IFERROR((AO116-$AK116)/ABS($AO116),0) -> 0 | AV116: =(AO116-$AK116) -> 0 | AW116: =IFERROR((AQ116-$AK116)/ABS($AK116),0) -> 0 | AX116: =(AQ116-$AK116) -> 0 | BA116: 0 | BB116: =IFERROR(BA116/SUMIFS(BA:BA, $H:$H, "[+] Net Sales"),0) -> 0 | BC116: 0 | BD116: =IFERROR(BC116/SUMIFS(BC:BC, $H:$H, "[+] Net Sales"),0) -> 0 | BE116: 0 | BF116: =IFERROR(BE116/SUMIFS(BE:BE, $H:$H, "[+] Net Sales"),0) -> 0 | BG116: =IFERROR((BC116-$BA116)/ABS($BA116),0) -> 0 | BH116: =(BC116-$BA116) -> 0 | BI116: =IFERROR((BE116-$BA116)/ABS($BA116),0) -> 0 | BJ116: =(BE116-$BA116) -> 0
H117: [+] Other | M117: 0 | N117: =IFERROR(M117/SUMIFS(M:M, $H:$H, "[+] Net Sales"),0) -> 0 | O117: 0 | P117: =IFERROR(O117/SUMIFS(O:O, $H:$H, "[+] Net Sales"),0) -> 0 | Q117: 0 | R117: =IFERROR(Q117/SUMIFS(Q:Q, $H:$H, "[+] Net Sales"),0) -> 0 | S117: 0 | T117: =IFERROR(S117/SUMIFS(S:S, $H:$H, "[+] Net Sales"),0) -> 0 | U117: =IFERROR(($O117-M117)/ABS(M117),0) -> 0 | V117: =IFERROR((O117-$M117), 0-$M117) -> 0 | W117: =IFERROR((Q117-$M117)/ABS($M117),0) -> 0 | X117: =IFERROR((Q117-$M117), 0 -$M117) -> 0 | Y117: =IFERROR((S117-$M117)/ABS($M117),0) -> 0 | Z117: =IFERROR((S117-$M117),0-$M117) -> 0 | AC117: 0 | AD117: 0 | AE117: 0 | AF117: =IFERROR((AD117-$AC117)/ABS($AC117),0) -> 0 | AG117: =(AD117-$AC117) -> 0 | AH117: =IFERROR((AE117-$AC117)/ABS($AC117),0) -> 0 | AI117: =(AE117-$AC117) -> 0 | AK117: 0 | AL117: =IFERROR(AK117/SUMIFS(AK:AK, $H:$H, "[+] Net Sales"),0) -> 0 | AM117: 0 | AN117: =IFERROR(AM117/SUMIFS(AM:AM, $H:$H, "[+] Net Sales"),0) -> 0 | AO117: 0 | AP117: =IFERROR(AO117/SUMIFS(AO:AO, $H:$H, "[+] Net Sales"),0) -> 0 | AQ117: 0 | AR117: =IFERROR(AQ117/SUMIFS(AQ:AQ, $H:$H, "[+] Net Sales"),0) -> 0 | AS117: =IFERROR((AM117-$AK117)/ABS($AK117),0) -> 0 | AT117: =(AM117-$AK117) -> 0 | AU117: =IFERROR((AO117-$AK117)/ABS($AO117),0) -> 0 | AV117: =(AO117-$AK117) -> 0 | AW117: =IFERROR((AQ117-$AK117)/ABS($AK117),0) -> 0 | AX117: =(AQ117-$AK117) -> 0 | BA117: 0 | BB117: =IFERROR(BA117/SUMIFS(BA:BA, $H:$H, "[+] Net Sales"),0) -> 0 | BC117: 0 | BD117: =IFERROR(BC117/SUMIFS(BC:BC, $H:$H, "[+] Net Sales"),0) -> 0 | BE117: 0 | BF117: =IFERROR(BE117/SUMIFS(BE:BE, $H:$H, "[+] Net Sales"),0) -> 0 | BG117: =IFERROR((BC117-$BA117)/ABS($BA117),0) -> 0 | BH117: =(BC117-$BA117) -> 0 | BI117: =IFERROR((BE117-$BA117)/ABS($BA117),0) -> 0 | BJ117: =(BE117-$BA117) -> 0
H118: [*] 4505 (Change in Finished Goods) | N118: =IFERROR(M118/SUMIFS(M:M, $H:$H, "[+] Net Sales"),0) -> 0 | P118: =IFERROR(O118/SUMIFS(O:O, $H:$H, "[+] Net Sales"),0) -> 0 | R118: =IFERROR(Q118/SUMIFS(Q:Q, $H:$H, "[+] Net Sales"),0) -> 0 | T118: =IFERROR(S118/SUMIFS(S:S, $H:$H, "[+] Net Sales"),0) -> 0 | U118: =IFERROR(($O118-M118)/ABS(M118),0) -> 0 | V118: =IFERROR((O118-$M118), 0-$M118) -> 0 | W118: =IFERROR((Q118-$M118)/ABS($M118),0) -> 0 | X118: =IFERROR((Q118-$M118), 0 -$M118) -> 0 | Y118: =IFERROR((S118-$M118)/ABS($M118),0) -> 0 | Z118: =IFERROR((S118-$M118),0-$M118) -> 0 | AC118: 0 | AD118: 0 | AE118: 0 | AF118: =IFERROR((AD118-$AC118)/ABS($AC118),0) -> 0 | AG118: =(AD118-$AC118) -> 0 | AH118: =IFERROR((AE118-$AC118)/ABS($AC118),0) -> 0 | AI118: =(AE118-$AC118) -> 0 | AK118: 0 | AL118: =IFERROR(AK118/SUMIFS(AK:AK, $H:$H, "[+] Net Sales"),0) -> 0 | AM118: 0 | AN118: =IFERROR(AM118/SUMIFS(AM:AM, $H:$H, "[+] Net Sales"),0) -> 0 | AO118: 0 | AP118: =IFERROR(AO118/SUMIFS(AO:AO, $H:$H, "[+] Net Sales"),0) -> 0 | AQ118: 0 | AR118: =IFERROR(AQ118/SUMIFS(AQ:AQ, $H:$H, "[+] Net Sales"),0) -> 0 | AS118: =IFERROR((AM118-$AK118)/ABS($AK118),0) -> 0 | AT118: =(AM118-$AK118) -> 0 | AU118: =IFERROR((AO118-$AK118)/ABS($AO118),0) -> 0 | AV118: =(AO118-$AK118) -> 0 | AW118: =IFERROR((AQ118-$AK118)/ABS($AK118),0) -> 0 | AX118: =(AQ118-$AK118) -> 0 | BA118: 0 | BB118: =IFERROR(BA118/SUMIFS(BA:BA, $H:$H, "[+] Net Sales"),0) -> 0 | BC118: 0 | BD118: =IFERROR(BC118/SUMIFS(BC:BC, $H:$H, "[+] Net Sales"),0) -> 0 | BE118: 0 | BF118: =IFERROR(BE118/SUMIFS(BE:BE, $H:$H, "[+] Net Sales"),0) -> 0 | BG118: =IFERROR((BC118-$BA118)/ABS($BA118),0) -> 0 | BH118: =(BC118-$BA118) -> 0 | BI118: =IFERROR((BE118-$BA118)/ABS($BA118),0) -> 0 | BJ118: =(BE118-$BA118) -> 0
...

Sheet 609 IS Var
B1: #hidecolumn
B2: #hiderow | C2: #hidecolumn | D2: #hidecolumn | E2: #hidecolumn | F2: #hidecolumn | G2: #hidecolumn | I2: #hidecolumn | J2: #hidecolumn | L2: #hidecolumn | O2: =IF(VALUE(TRIM(LEFT(Scenario!$A$4,2)))<4, "#hidecolumn", "#showcolumn") -> #hidecolumn | P2: =O2 -> #hidecolumn | Q2: =IF(VALUE(TRIM(LEFT(Scenario!$A$4,2)))<4, "#showcolumn", "#hidecolumn") -> #showcolumn | R2: =Q2 -> #showcolumn | U2: =V2 -> #hidecolumn | V2: =IF(VALUE(TRIM(LEFT(Scenario!$A$4,2)))<4, "#hidecolumn", "#showcolumn") -> #hidecolumn | W2: =X2 -> #showcolumn | X2: =IF(VALUE(TRIM(LEFT(Scenario!$A$4,2)))<4, "#showcolumn", "#hidecolumn") -> #showcolumn | AB2: #hidecolumn | AC2: #hidecolumn | AD2: #hidecolumn | AE2: #hidecolumn | AF2: #hidecolumn | AG2: #hidecolumn | AH2: #hidecolumn | AI2: #hidecolumn | AM2: =IF(VALUE(TRIM(LEFT(Scenario!$A$4,2)))<4, "#hidecolumn", "#showcolumn") -> #hidecolumn | AN2: =AM2 -> #hidecolumn | AO2: =IF(VALUE(TRIM(LEFT(Scenario!$A$4,2)))<4, "#showcolumn", "#hidecolumn") -> #showcolumn | AP2: =AO2 -> #showcolumn | AS2: =AT2 -> #hidecolumn | AT2: =IF(VALUE(TRIM(LEFT(Scenario!$A$4,2)))<4, "#hidecolumn", "#showcolumn") -> #hidecolumn | AU2: =AV2 -> #showcolumn | AV2: =IF(VALUE(TRIM(LEFT(Scenario!$A$4,2)))<4, "#showcolumn", "#hidecolumn") -> #showcolumn | BC2: =IF(VALUE(TRIM(LEFT(Scenario!$A$4,2)))>=4, "#showcolumn", "#hidecolumn") -> #hidecolumn | BD2: =BC2 -> #hidecolumn | BG2: =BC2 -> #hidecolumn | BH2: =BD2 -> #hidecolumn | BK2: #hidecolumn
B3: #hiderow | C3: =_xlfn.CONCAT("Section: ", LEFT(E6,3)) -> Section: 609
B4: #hiderow | C4: Dimension | D4: Position | L4: =VALUE(TRIM(LEFT(Scenario!$A$4,2))) -> 1 | M4: =Scenario!$A$1 -> 2026 | O4: =Scenario!$A$1 -> 2026 | Q4: =Scenario!$A$1 -> 2026 | S4: =Scenario!$A$1-1 -> 2025 | AC4: =Scenario!$A$1 -> 2026 | AD4: =Scenario!$A$1-1 -> 2025 | AE4: =Scenario!$A$1 -> 2026 | AK4: =Scenario!$A$1 -> 2026 | AM4: =Scenario!$A$1 -> 2026 | AO4: =Scenario!$A$1 -> 2026 | AQ4: =Scenario!$A$1-1 -> 2025 | BA4: =AK4 -> 2026 | BC4: =AO4 -> 2026 | BE4: =BA4-1 -> 2025
B5: #hiderow | C5: Account | D5: Row | M5: =VALUE(TRIM(LEFT(Scenario!$A$4,2))) -> 1 | O5: =VALUE(TRIM(LEFT(Scenario!$A$4,2))) -> 1 | Q5: =VALUE(TRIM(LEFT(Scenario!$A$4,2))) -> 1 | S5: =VALUE(TRIM(LEFT(Scenario!$A$4,2))) -> 1 | AC5: =VALUE(TRIM(LEFT(Scenario!$A$4,2)))&" QTD" -> 1 QTD | AD5: =VALUE(TRIM(LEFT(Scenario!$A$4,2)))&" QTD" -> 1 QTD | AE5: =VALUE(TRIM(LEFT(Scenario!$A$4,2)))&" QTD" -> 1 QTD | AK5: =VALUE(TRIM(LEFT(Scenario!$A$4,2)))&" YTD" -> 1 YTD | AM5: =VALUE(TRIM(LEFT(Scenario!$A$4,2)))&" YTD" -> 1 YTD | AO5: =VALUE(TRIM(LEFT(Scenario!$A$4,2)))&" YTD" -> 1 YTD | AQ5: =VALUE(TRIM(LEFT(Scenario!$A$4,2)))&" YTD" -> 1 YTD | BA5: 12 YTD | BC5: 12 YTD | BE5: 12 YTD
B6: #hiderow | C6: Department | D6: Page | E6: 609 (Brooklyn Navy Yard) | M6: ="Actual" -> Actual | O6: =Scenario!$A$2 -> Plan | Q6: Plan | S6: ="Actual" -> Actual | AC6: ="Actual" -> Actual | AD6: ="Actual" -> Actual | AE6: Plan | AK6: ="Actual" -> Actual | AM6: =Scenario!$A$2 -> Plan | AO6: Plan | AQ6: ="Actual" -> Actual | BA6: =IF(VALUE(TRIM(LEFT(Scenario!$A$4,2)))<4, "Plan", Scenario!$A$2) -> Plan | BC6: Plan | BE6: ="Actual" -> Actual
B7: #hiderow | C7: Year | D7: Column
B8: #hiderow | C8: Period | D8: Column
B9: #hiderow | C9: Scenario | D9: Column
B10: #hiderow | C10: Currency | D10: Page | E10: Local
B11: #hiderow | C11: Measure | D11: Page | E11: Value
E12: Undefined (Not Entity Specific)
E13: Undefined (Not Placeholder 1 Specific)
E14: Undefined (Not Placeholder 2 Specific)
E15: Undefined (Not Placeholder 3 Specific)
E16: Undefined (Not Placeholder 4 Specific)
B17: #hiderow
H18: Income Statement Variance
H19: =E6 -> 609 (Brooklyn Navy Yard) | M19: =_xlfn.XLOOKUP(M$5,'Month Name'!$D:$D, 'Month Name'!$C:$C)&" "&RIGHT(M4,2) -> Jan 26 | N19: Actual | P19: Forecast | R19: Plan | T19: Prior Year | AF19: =_xlfn.CONCAT(TEXT((TRIM(MID(M5,4,3))),"mmm")," QTD ",RIGHT(M4,2)) -> QTD 26 | AK19: =_xlfn.XLOOKUP(M$5,'Month Name'!$D:$D, 'Month Name'!$C:$C)&" YTD "&RIGHT(M4,2) -> Jan YTD 26 | AL19: Actual | AN19: Forecast | AP19: Plan | AR19: Prior Year | BB19: Forecast | BD19: Plan | BF19: Prior Year
M20: =_xlfn.XLOOKUP(M$5,'Month Name'!$D:$D, 'Month Name'!$C:$C)&" "&RIGHT(M4,2) -> Jan 26 | N20: % of | O20: =_xlfn.XLOOKUP(O$5,'Month Name'!$D:$D, 'Month Name'!$C:$C)&" "&RIGHT(O4,2) -> Jan 26 | P20: % of | Q20: =_xlfn.XLOOKUP(Q$5,'Month Name'!$D:$D, 'Month Name'!$C:$C)&" "&RIGHT(Q4,2) -> Jan 26 | R20: % of | S20: =_xlfn.XLOOKUP(S$5,'Month Name'!$D:$D, 'Month Name'!$C:$C)&" "&RIGHT(S4,2) -> Jan 25 | T20: % of | U20: % Var | V20: $ Var | W20: =Y20 -> % Var | X20: =Z20 -> $ Var | Y20: % Var | Z20: $ Var | AC20: =AF19 -> QTD 26 | AD20: =_xlfn.CONCAT(TEXT((TRIM(MID(M5,4,3))),"mmm")," QTD ",RIGHT(S4,2)) -> QTD 25 | AE20: =AC20 -> QTD 26 | AF20: % Var | AG20: $ Var | AH20: =AF20 -> % Var | AI20: =AG20 -> $ Var | AK20: =_xlfn.XLOOKUP(M$5,'Month Name'!$D:$D, 'Month Name'!$C:$C)&" YTD "&RIGHT(M4,2) -> Jan YTD 26 | AL20: % of | AM20: =_xlfn.XLOOKUP(O$5,'Month Name'!$D:$D, 'Month Name'!$C:$C)&" YTD "&RIGHT(O4,2) -> Jan YTD 26 | AN20: % of | AO20: =_xlfn.XLOOKUP(Q$5,'Month Name'!$D:$D, 'Month Name'!$C:$C)&" YTD "&RIGHT(Q4,2) -> Jan YTD 26 | AP20: % of | AQ20: =_xlfn.XLOOKUP(S$5,'Month Name'!$D:$D, 'Month Name'!$C:$C)&" YTD "&RIGHT(S4,2) -> Jan YTD 25 | AR20: % of | AS20: % Var | AT20: $ Var | AU20: =AW20 -> % Var | AV20: =AX20 -> $ Var | AW20: % Var | AX20: $ Var | BA20: ="Full Year "&BA4 -> Full Year 2026 | BB20: % of | BC20: ="Full Year "&BC4 -> Full Year 2026 | BD20: % of | BE20: ="Full Year "&BE4 -> Full Year 2025 | BF20: % of | BG20: =BI20 -> % Var | BH20: =BJ20 -> $ Var | BI20: % Var | BJ20: $ Var
G21: ="in "&$G$5&" currency" -> in currency | M21: =M6 -> Actual | N21: Net Sales | O21: =O6 -> Plan | P21: Net Sales | Q21: =IF(Q6="Plan", "Budget", Q6) -> Budget | R21: Net Sales | S21: ="PY "&S6 -> PY Actual | T21: Net Sales | U21: =O21 -> Plan | V21: =O21 -> Plan | W21: =Q21 -> Budget | X21: =Q21 -> Budget | Y21: PY | Z21: PY | AA21: Commentary | AC21: =AC6 -> Actual | AD21: ="PY "&AD6 -> PY Actual | AE21: Budget | AF21: PY | AG21: PY | AH21: =AE21 -> Budget | AI21: =AH21 -> Budget | AK21: =AK6 -> Actual | AL21: Net Sales | AM21: =AM6 -> Plan | AN21: Net Sales | AO21: =IF(AO6="Plan", "Budget", AO6) -> Budget | AP21: Net Sales | AQ21: ="PY "&AQ6 -> PY Actual | AR21: Net Sales | AS21: =AM21 -> Plan | AT21: =AM21 -> Plan | AU21: =AO21 -> Budget | AV21: =AO21 -> Budget | AW21: PY | AX21: PY | AY21: Commentary | BA21: =IF(BA6="Plan", "Budget", BA6) -> Budget | BB21: Net Sales | BC21: =IF(BC6="Plan", "Budget", BC6) -> Budget | BD21: Net Sales | BE21: =BE6 -> Actual | BF21: Net Sales | BG21: =BC21 -> Budget | BH21: =BC21 -> Budget | BI21: PY | BJ21: PY | BK21: Commentary
B23: #hiderow | H23: Current Year | I23: =YEAR(TODAY()-20) -> 2026
B24: #hiderow | H24: Current Month | I24: =MONTH(TODAY() - 20) -> 2
B25: #hiderow | H25: Current QTD | I25: =_xlfn.CONCAT(I24," QTD") -> 2 QTD
B26: #hiderow | H26: Current YTD | I26: =_xlfn.CONCAT(I24," YTD") -> 2 YTD
B27: #hiderow
B28: #hiderow
B29: #hiderow | G29: Add Description | H29: Add Description | I29: Line-Item Detail | U29: =IFERROR(($O29-M29)/ABS(M29),0) -> 0 | V29: =($O29-M29) -> 0 | W29: =IFERROR(($M29-Q29)/ABS(Q29),0) -> 0 | X29: =($M29-Q29) -> 0 | Y29: =IFERROR(($M29-S29)/ABS(S29),0) -> 0 | Z29: =($M29-S29) -> 0 | AF29: =IFERROR(($AC29-AD29)/ABS(AD29),0) -> 0 | AG29: =($AC29-AD29) -> 0 | AH29: =IFERROR(($AC29-AE29)/ABS(AE29),0) -> 0 | AI29: =($AC29-AE29) -> 0 | AS29: =IFERROR(($O29-AK29)/ABS(AK29),0) -> 0 | AT29: =($O29-AK29) -> 0 | AU29: =IFERROR(($M29-AO29)/ABS(AO29),0) -> 0 | AV29: =($M29-AO29) -> 0 | AW29: =IFERROR(($M29-AQ29)/ABS(AQ29),0) -> 0 | AX29: =($M29-AQ29) -> 0 | BG29: =IFERROR(($BA29-BC29)/ABS(BC29),0) -> 0 | BH29: =($BA29-BC29) -> 0 | BI29: =IFERROR(($BA29-BE29)/ABS(BE29),0) -> 0 | BJ29: =($BA29-BE29) -> 0
H30: Revenue
B31: #hiderow | H31: Revenue | M31: 529233.54 | O31: 531599.26 | Q31: 531599.26 | S31: 182427.75 | AC31: 529233.54 | AD31: 182427.75 | AE31: 531599.26 | AK31: 529233.54 | AM31: 531599.26 | AO31: 531599.26 | AQ31: 182427.75 | BA31: 6910790.3 | BC31: 6910790.3 | BE31: 4773077.6
B32: =IF(LEFT(H32,3)="Mul", "#hiderow", "#showrow") -> #showrow | H32: Net Sales | M32: 529233.54 | N32: =IFERROR(M32/SUMIFS(M:M, $H:$H, "Net Sales"),0) -> 1 | O32: 531599.26 | P32: =IFERROR(O32/SUMIFS(O:O, $H:$H, "Net Sales"),0) -> 1 | Q32: 531599.26 | R32: =IFERROR(Q32/SUMIFS(Q:Q, $H:$H, "Net Sales"),0) -> 1 | S32: 182427.75 | T32: =IFERROR(S32/SUMIFS(S:S, $H:$H, "Net Sales"),0) -> 1 | U32: =IFERROR(($M32-O32)/ABS(O32),0) -> -0.0044501867 | V32: =IFERROR((M32-$O32), $M32-0) -> -2365.7159 | W32: =IFERROR((M32-$Q32)/ABS($Q32),0) -> -0.0044501867 | X32: =IFERROR((M32-$Q32), $M32-0) -> -2365.7159 | Y32: =IFERROR((M32-$S32)/ABS($S32),0) -> 1.9010583 | Z32: =IFERROR((M32-$S32),$M32-0) -> 346805.79 | AC32: 529233.54 | AD32: 182427.75 | AE32: 531599.26 | AF32: =IFERROR(($AC32-AD32)/ABS(AD32),0) -> 1.9010583 | AG32: =($AC32-AD32) -> 346805.79 | AH32: =IFERROR(($AC32-AE32)/ABS(AE32),0) -> -0.0044501867 | AI32: =($AC32-AE32) -> -2365.7159 | AK32: 529233.54 | AL32: =IFERROR(AK32/SUMIFS(AK:AK, $H:$H, "Net Sales"),0) -> 1 | AM32: 531599.26 | AN32: =IFERROR(AM32/SUMIFS(AM:AM, $H:$H, "Net Sales"),0) -> 1 | AO32: 531599.26 | AP32: =IFERROR(AO32/SUMIFS(AO:AO, $H:$H, "Net Sales"),0) -> 1 | AQ32: 182427.75 | AR32: =IFERROR(AQ32/SUMIFS(AQ:AQ, $H:$H, "Net Sales"),0) -> 1 | AS32: =IFERROR((AK32-$AM32)/ABS($AM32),0) -> -0.0044501867 | AT32: =(AK32-$AM32) -> -2365.7159 | AU32: =IFERROR((AK32-$AO32)/ABS($AO32),0) -> -0.0044501867 | AV32: =(AK32-$AO32) -> -2365.7159 | AW32: =IFERROR((AK32-$AQ32)/ABS($AQ32),0) -> 1.9010583 | AX32: =(AK32-$AQ32) -> 346805.79 | BA32: 6910790.3 | BB32: =IFERROR(BA32/SUMIFS(BA:BA, $H:$H, "Net Sales"),0) -> 1 | BC32: 6910790.3 | BD32: =IFERROR(BC32/SUMIFS(BC:BC, $H:$H, "Net Sales"),0) -> 1 | BE32: 4773077.6 | BF32: =IFERROR(BE32/SUMIFS(BE:BE, $H:$H, "Net Sales"),0) -> 1 | BG32: =IFERROR((BA32-$BC32)/ABS($BC32),0) -> 0 | BH32: =(BA32-$BC32) -> 0 | BI32: =IFERROR((BA32-$BE32)/ABS($BE32),0) -> 0.44786884 | BJ32: =(BA32-$BE32) -> 2137712.7
B33: =IF(LEFT(H33,3)="Mul", "#hiderow", "#showrow") -> #hiderow | H33: MultiDynamic: Account | N33: =IFERROR(M33/SUMIFS(M:M, $H:$H, "Net Sales"),0) -> 0 | P33: =IFERROR(O33/SUMIFS(O:O, $H:$H, "Net Sales"),0) -> 0 | R33: =IFERROR(Q33/SUMIFS(Q:Q, $H:$H, "Net Sales"),0) -> 0 | T33: =IFERROR(S33/SUMIFS(S:S, $H:$H, "Net Sales"),0) -> 0 | U33: =IFERROR(($M33-O33)/ABS(O33),0) -> 0 | V33: =IFERROR((M33-$O33), $M33-0) -> 0 | W33: =IFERROR((M33-$Q33)/ABS($Q33),0) -> 0 | X33: =IFERROR((M33-$Q33), $M33-0) -> 0 | Y33: =IFERROR((M33-$S33)/ABS($S33),0) -> 0 | Z33: =IFERROR((M33-$S33),$M33-0) -> 0 | AL33: =IFERROR(AK33/SUMIFS(AK:AK, $H:$H, "Net Sales"),0) -> 0 | AN33: =IFERROR(AM33/SUMIFS(AM:AM, $H:$H, "Net Sales"),0) -> 0 | AP33: =IFERROR(AO33/SUMIFS(AO:AO, $H:$H, "Net Sales"),0) -> 0 | AR33: =IFERROR(AQ33/SUMIFS(AQ:AQ, $H:$H, "Net Sales"),0) -> 0 | AS33: =IFERROR((AK33-$AM33)/ABS($AM33),0) -> 0 | AT33: =(AK33-$AM33) -> 0 | AU33: =IFERROR((AK33-$AO33)/ABS($AO33),0) -> 0 | AV33: =(AK33-$AO33) -> 0 | AW33: =IFERROR((AK33-$AQ33)/ABS($AQ33),0) -> 0 | AX33: =(AK33-$AQ33) -> 0 | BB33: =IFERROR(BA33/SUMIFS(BA:BA, $H:$H, "Net Sales"),0) -> 0 | BD33: =IFERROR(BC33/SUMIFS(BC:BC, $H:$H, "Net Sales"),0) -> 0 | BF33: =IFERROR(BE33/SUMIFS(BE:BE, $H:$H, "Net Sales"),0) -> 0 | BG33: =IFERROR((BA33-$BC33)/ABS($BC33),0) -> 0 | BH33: =(BA33-$BC33) -> 0 | BI33: =IFERROR((BA33-$BE33)/ABS($BE33),0) -> 0 | BJ33: =(BA33-$BE33) -> 0
B34: =IF(LEFT(H34,3)="Mul", "#hiderow", "#showrow") -> #showrow | H34: 3020 (Sales - 3rd Party) | M34: 19365.5 | N34: =IFERROR(M34/SUMIFS(M:M, $H:$H, "Net Sales"),0) -> 0.036591596 | O34: 37431.298 | P34: =IFERROR(O34/SUMIFS(O:O, $H:$H, "Net Sales"),0) -> 0.070412623 | Q34: 37431.298 | R34: =IFERROR(Q34/SUMIFS(Q:Q, $H:$H, "Net Sales"),0) -> 0.070412623 | S34: -13713 | T34: =IFERROR(S34/SUMIFS(S:S, $H:$H, "Net Sales"),0) -> -0.075169485 | U34: =IFERROR(($M34-O34)/ABS(O34),0) -> -0.48263883 | V34: =IFERROR((M34-$O34), $M34-0) -> -18065.798 | W34: =IFERROR((M34-$Q34)/ABS($Q34),0) -> -0.48263883 | X34: =IFERROR((M34-$Q34), $M34-0) -> -18065.798 | Y34: =IFERROR((M34-$S34)/ABS($S34),0) -> 2.4122001 | Z34: =IFERROR((M34-$S34),$M34-0) -> 33078.5 | AC34: 19365.5 | AD34: -13713 | AE34: 37431.298 | AK34: 19365.5 | AL34: =IFERROR(AK34/SUMIFS(AK:AK, $H:$H, "Net Sales"),0) -> 0.036591596 | AM34: 37431.298 | AN34: =IFERROR(AM34/SUMIFS(AM:AM, $H:$H, "Net Sales"),0) -> 0.070412623 | AO34: 37431.298 | AP34: =IFERROR(AO34/SUMIFS(AO:AO, $H:$H, "Net Sales"),0) -> 0.070412623 | AQ34: -13713 | AR34: =IFERROR(AQ34/SUMIFS(AQ:AQ, $H:$H, "Net Sales"),0) -> -0.075169485 | AS34: =IFERROR((AK34-$AM34)/ABS($AM34),0) -> -0.48263883 | AT34: =(AK34-$AM34) -> -18065.798 | AU34: =IFERROR((AK34-$AO34)/ABS($AO34),0) -> -0.48263883 | AV34: =(AK34-$AO34) -> -18065.798 | AW34: =IFERROR((AK34-$AQ34)/ABS($AQ34),0) -> 2.4122001 | AX34: =(AK34-$AQ34) -> 33078.5 | BA34: 486606.87 | BB34: =IFERROR(BA34/SUMIFS(BA:BA, $H:$H, "Net Sales"),0) -> 0.070412623 | BC34: 486606.87 | BD34: =IFERROR(BC34/SUMIFS(BC:BC, $H:$H, "Net Sales"),0) -> 0.070412623 | BE34: 488243.05 | BF34: =IFERROR(BE34/SUMIFS(BE:BE, $H:$H, "Net Sales"),0) -> 0.10229104 | BG34: =IFERROR((BA34-$BC34)/ABS($BC34),0) -> 0 | BH34: =(BA34-$BC34) -> 0 | BI34: =IFERROR((BA34-$BE34)/ABS($BE34),0) -> -0.0033511505 | BJ34: =(BA34-$BE34) -> -1636.1759
B35: =IF(LEFT(H35,3)="Mul", "#hiderow", "#showrow") -> #showrow | H35: 3025 (Sales - Intercompany) | M35: 509868.04 | N35: =IFERROR(M35/SUMIFS(M:M, $H:$H, "Net Sales"),0) -> 0.9634084 | O35: 494167.96 | P35: =IFERROR(O35/SUMIFS(O:O, $H:$H, "Net Sales"),0) -> 0.92958738 | Q35: 494167.96 | R35: =IFERROR(Q35/SUMIFS(Q:Q, $H:$H, "Net Sales"),0) -> 0.92958738 | S35: 196140.75 | T35: =IFERROR(S35/SUMIFS(S:S, $H:$H, "Net Sales"),0) -> 1.0751695 | U35: =IFERROR(($M35-O35)/ABS(O35),0) -> 0.031770741 | V35: =IFERROR((M35-$O35), $M35-0) -> 15700.082 | W35: =IFERROR((M35-$Q35)/ABS($Q35),0) -> 0.031770741 | X35: =IFERROR((M35-$Q35), $M35-0) -> 15700.082 | Y35: =IFERROR((M35-$S35)/ABS($S35),0) -> 1.5995008 | Z35: =IFERROR((M35-$S35),$M35-0) -> 313727.29 | AC35: 509868.04 | AD35: 196140.75 | AE35: 494167.96 | AK35: 509868.04 | AL35: =IFERROR(AK35/SUMIFS(AK:AK, $H:$H, "Net Sales"),0) -> 0.9634084 | AM35: 494167.96 | AN35: =IFERROR(AM35/SUMIFS(AM:AM, $H:$H, "Net Sales"),0) -> 0.92958738 | AO35: 494167.96 | AP35: =IFERROR(AO35/SUMIFS(AO:AO, $H:$H, "Net Sales"),0) -> 0.92958738 | AQ35: 196140.75 | AR35: =IFERROR(AQ35/SUMIFS(AQ:AQ, $H:$H, "Net Sales"),0) -> 1.0751695 | AS35: =IFERROR((AK35-$AM35)/ABS($AM35),0) -> 0.031770741 | AT35: =(AK35-$AM35) -> 15700.082 | AU35: =IFERROR((AK35-$AO35)/ABS($AO35),0) -> 0.031770741 | AV35: =(AK35-$AO35) -> 15700.082 | AW35: =IFERROR((AK35-$AQ35)/ABS($AQ35),0) -> 1.5995008 | AX35: =(AK35-$AQ35) -> 313727.29 | BA35: 6424183.5 | BB35: =IFERROR(BA35/SUMIFS(BA:BA, $H:$H, "Net Sales"),0) -> 0.92958738 | BC35: 6424183.5 | BD35: =IFERROR(BC35/SUMIFS(BC:BC, $H:$H, "Net Sales"),0) -> 0.92958738 | BE35: 4284834.6 | BF35: =IFERROR(BE35/SUMIFS(BE:BE, $H:$H, "Net Sales"),0) -> 0.89770896 | BG35: =IFERROR((BA35-$BC35)/ABS($BC35),0) -> 0 | BH35: =(BA35-$BC35) -> 0 | BI35: =IFERROR((BA35-$BE35)/ABS($BE35),0) -> 0.4992839 | BJ35: =(BA35-$BE35) -> 2139348.9
B36: =IF(LEFT(H36,3)="Mul", "#hiderow", "#showrow") -> #showrow | H36: Freight Revenue | M36: 0 | N36: =IFERROR(M36/SUMIFS(M:M, $H:$H, "Net Sales"),0) -> 0 | O36: 0 | P36: =IFERROR(O36/SUMIFS(O:O, $H:$H, "Net Sales"),0) -> 0 | Q36: 0 | R36: =IFERROR(Q36/SUMIFS(Q:Q, $H:$H, "Net Sales"),0) -> 0 | S36: 0 | T36: =IFERROR(S36/SUMIFS(S:S, $H:$H, "Net Sales"),0) -> 0 | U36: =IFERROR(($M36-O36)/ABS(O36),0) -> 0 | V36: =IFERROR((M36-$O36), $M36-0) -> 0 | W36: =IFERROR((M36-$Q36)/ABS($Q36),0) -> 0 | X36: =IFERROR((M36-$Q36), $M36-0) -> 0 | Y36: =IFERROR((M36-$S36)/ABS($S36),0) -> 0 | Z36: =IFERROR((M36-$S36),$M36-0) -> 0 | AC36: 0 | AD36: 0 | AE36: 0 | AK36: 0 | AL36: =IFERROR(AK36/SUMIFS(AK:AK, $H:$H, "Net Sales"),0) -> 0 | AM36: 0 | AN36: =IFERROR(AM36/SUMIFS(AM:AM, $H:$H, "Net Sales"),0) -> 0 | AO36: 0 | AP36: =IFERROR(AO36/SUMIFS(AO:AO, $H:$H, "Net Sales"),0) -> 0 | AQ36: 0 | AR36: =IFERROR(AQ36/SUMIFS(AQ:AQ, $H:$H, "Net Sales"),0) -> 0 | AS36: =IFERROR((AK36-$AM36)/ABS($AM36),0) -> 0 | AT36: =(AK36-$AM36) -> 0 | AU36: =IFERROR((AK36-$AO36)/ABS($AO36),0) -> 0 | AV36: =(AK36-$AO36) -> 0 | AW36: =IFERROR((AK36-$AQ36)/ABS($AQ36),0) -> 0 | AX36: =(AK36-$AQ36) -> 0 | BA36: 0 | BB36: =IFERROR(BA36/SUMIFS(BA:BA, $H:$H, "Net Sales"),0) -> 0 | BC36: 0 | BD36: =IFERROR(BC36/SUMIFS(BC:BC, $H:$H, "Net Sales"),0) -> 0 | BE36: 0 | BF36: =IFERROR(BE36/SUMIFS(BE:BE, $H:$H, "Net Sales"),0) -> 0 | BG36: =IFERROR((BA36-$BC36)/ABS($BC36),0) -> 0 | BH36: =(BA36-$BC36) -> 0 | BI36: =IFERROR((BA36-$BE36)/ABS($BE36),0) -> 0 | BJ36: =(BA36-$BE36) -> 0
B37: =IF(LEFT(H37,3)="Mul", "#hiderow", "#showrow") -> #hiderow | H37: MultiDynamic: Account | N37: =IFERROR(M37/SUMIFS(M:M, $H:$H, "Net Sales"),0) -> 0 | P37: =IFERROR(O37/SUMIFS(O:O, $H:$H, "Net Sales"),0) -> 0 | R37: =IFERROR(Q37/SUMIFS(Q:Q, $H:$H, "Net Sales"),0) -> 0 | T37: =IFERROR(S37/SUMIFS(S:S, $H:$H, "Net Sales"),0) -> 0 | U37: =IFERROR(($M37-O37)/ABS(O37),0) -> 0 | V37: =IFERROR((M37-$O37), $M37-0) -> 0 | W37: =IFERROR((M37-$Q37)/ABS($Q37),0) -> 0 | X37: =IFERROR((M37-$Q37), $M37-0) -> 0 | Y37: =IFERROR((M37-$S37)/ABS($S37),0) -> 0 | Z37: =IFERROR((M37-$S37),$M37-0) -> 0 | AL37: =IFERROR(AK37/SUMIFS(AK:AK, $H:$H, "Net Sales"),0) -> 0 | AN37: =IFERROR(AM37/SUMIFS(AM:AM, $H:$H, "Net Sales"),0) -> 0 | AP37: =IFERROR(AO37/SUMIFS(AO:AO, $H:$H, "Net Sales"),0) -> 0 | AR37: =IFERROR(AQ37/SUMIFS(AQ:AQ, $H:$H, "Net Sales"),0) -> 0 | AS37: =IFERROR((AK37-$AM37)/ABS($AM37),0) -> 0 | AT37: =(AK37-$AM37) -> 0 | AU37: =IFERROR((AK37-$AO37)/ABS($AO37),0) -> 0 | AV37: =(AK37-$AO37) -> 0 | AW37: =IFERROR((AK37-$AQ37)/ABS($AQ37),0) -> 0 | AX37: =(AK37-$AQ37) -> 0 | BB37: =IFERROR(BA37/SUMIFS(BA:BA, $H:$H, "Net Sales"),0) -> 0 | BD37: =IFERROR(BC37/SUMIFS(BC:BC, $H:$H, "Net Sales"),0) -> 0 | BF37: =IFERROR(BE37/SUMIFS(BE:BE, $H:$H, "Net Sales"),0) -> 0 | BG37: =IFERROR((BA37-$BC37)/ABS($BC37),0) -> 0 | BH37: =(BA37-$BC37) -> 0 | BI37: =IFERROR((BA37-$BE37)/ABS($BE37),0) -> 0 | BJ37: =(BA37-$BE37) -> 0
B38: =IF(LEFT(H38,3)="Mul", "#hiderow", "#showrow") -> #showrow | H38: Other Revenue | M38: 0 | N38: =IFERROR(M38/SUMIFS(M:M, $H:$H, "Net Sales"),0) -> 0 | O38: 0 | P38: =IFERROR(O38/SUMIFS(O:O, $H:$H, "Net Sales"),0) -> 0 | Q38: 0 | R38: =IFERROR(Q38/SUMIFS(Q:Q, $H:$H, "Net Sales"),0) -> 0 | S38: 0 | T38: =IFERROR(S38/SUMIFS(S:S, $H:$H, "Net Sales"),0) -> 0 | U38: =IFERROR(($M38-O38)/ABS(O38),0) -> 0 | V38: =IFERROR((M38-$O38), $M38-0) -> 0 | W38: =IFERROR((M38-$Q38)/ABS($Q38),0) -> 0 | X38: =IFERROR((M38-$Q38), $M38-0) -> 0 | Y38: =IFERROR((M38-$S38)/ABS($S38),0) -> 0 | Z38: =IFERROR((M38-$S38),$M38-0) -> 0 | AC38: 0 | AD38: 0 | AE38: 0 | AK38: 0 | AL38: =IFERROR(AK38/SUMIFS(AK:AK, $H:$H, "Net Sales"),0) -> 0 | AM38: 0 | AN38: =IFERROR(AM38/SUMIFS(AM:AM, $H:$H, "Net Sales"),0) -> 0 | AO38: 0 | AP38: =IFERROR(AO38/SUMIFS(AO:AO, $H:$H, "Net Sales"),0) -> 0 | AQ38: 0 | AR38: =IFERROR(AQ38/SUMIFS(AQ:AQ, $H:$H, "Net Sales"),0) -> 0 | AS38: =IFERROR((AK38-$AM38)/ABS($AM38),0) -> 0 | AT38: =(AK38-$AM38) -> 0 | AU38: =IFERROR((AK38-$AO38)/ABS($AO38),0) -> 0 | AV38: =(AK38-$AO38) -> 0 | AW38: =IFERROR((AK38-$AQ38)/ABS($AQ38),0) -> 0 | AX38: =(AK38-$AQ38) -> 0 | BA38: 0 | BB38: =IFERROR(BA38/SUMIFS(BA:BA, $H:$H, "Net Sales"),0) -> 0 | BC38: 0 | BD38: =IFERROR(BC38/SUMIFS(BC:BC, $H:$H, "Net Sales"),0) -> 0 | BE38: 0 | BF38: =IFERROR(BE38/SUMIFS(BE:BE, $H:$H, "Net Sales"),0) -> 0 | BG38: =IFERROR((BA38-$BC38)/ABS($BC38),0) -> 0 | BH38: =(BA38-$BC38) -> 0 | BI38: =IFERROR((BA38-$BE38)/ABS($BE38),0) -> 0 | BJ38: =(BA38-$BE38) -> 0
B39: =IF(LEFT(H39,3)="Mul", "#hiderow", "#showrow") -> #hiderow | H39: MultiDynamic: Account | N39: =IFERROR(M39/SUMIFS(M:M, $H:$H, "Net Sales"),0) -> 0 | P39: =IFERROR(O39/SUMIFS(O:O, $H:$H, "Net Sales"),0) -> 0 | R39: =IFERROR(Q39/SUMIFS(Q:Q, $H:$H, "Net Sales"),0) -> 0 | T39: =IFERROR(S39/SUMIFS(S:S, $H:$H, "Net Sales"),0) -> 0 | U39: =IFERROR(($M39-O39)/ABS(O39),0) -> 0 | V39: =IFERROR((M39-$O39), $M39-0) -> 0 | W39: =IFERROR((M39-$Q39)/ABS($Q39),0) -> 0 | X39: =IFERROR((M39-$Q39), $M39-0) -> 0 | Y39: =IFERROR((M39-$S39)/ABS($S39),0) -> 0 | Z39: =IFERROR((M39-$S39),$M39-0) -> 0 | AL39: =IFERROR(AK39/SUMIFS(AK:AK, $H:$H, "Net Sales"),0) -> 0 | AN39: =IFERROR(AM39/SUMIFS(AM:AM, $H:$H, "Net Sales"),0) -> 0 | AP39: =IFERROR(AO39/SUMIFS(AO:AO, $H:$H, "Net Sales"),0) -> 0 | AR39: =IFERROR(AQ39/SUMIFS(AQ:AQ, $H:$H, "Net Sales"),0) -> 0 | AS39: =IFERROR((AK39-$AM39)/ABS($AM39),0) -> 0 | AT39: =(AK39-$AM39) -> 0 | AU39: =IFERROR((AK39-$AO39)/ABS($AO39),0) -> 0 | AV39: =(AK39-$AO39) -> 0 | AW39: =IFERROR((AK39-$AQ39)/ABS($AQ39),0) -> 0 | AX39: =(AK39-$AQ39) -> 0 | BB39: =IFERROR(BA39/SUMIFS(BA:BA, $H:$H, "Net Sales"),0) -> 0 | BD39: =IFERROR(BC39/SUMIFS(BC:BC, $H:$H, "Net Sales"),0) -> 0 | BF39: =IFERROR(BE39/SUMIFS(BE:BE, $H:$H, "Net Sales"),0) -> 0 | BG39: =IFERROR((BA39-$BC39)/ABS($BC39),0) -> 0 | BH39: =(BA39-$BC39) -> 0 | BI39: =IFERROR((BA39-$BE39)/ABS($BE39),0) -> 0 | BJ39: =(BA39-$BE39) -> 0
H40: Total Revenue | L40: 1 | M40: =SUMIFS(M31:M39,$I31:$I39,"<>"&$I$29,$E31:$E39,"<>*[-]*",$F31:$F39,"<>*[-]*",$G31:$G39,"<>*[-]*",$H31:$H39,"Revenue") -> 529233.54 | N40: =IFERROR(M40/SUMIFS(M:M, $H:$H, "Net Sales"),0) -> 1 | O40: =SUMIFS(O31:O39,$I31:$I39,"<>"&$I$29,$E31:$E39,"<>*[-]*",$F31:$F39,"<>*[-]*",$G31:$G39,"<>*[-]*",$H31:$H39,"Revenue") -> 531599.26 | P40: =IFERROR(O40/SUMIFS(O:O, $H:$H, "Net Sales"),0) -> 1 | Q40: =SUMIFS(Q31:Q39,$I31:$I39,"<>"&$I$29,$E31:$E39,"<>*[-]*",$F31:$F39,"<>*[-]*",$G31:$G39,"<>*[-]*",$H31:$H39,"Revenue") -> 531599.26 | R40: =IFERROR(Q40/SUMIFS(Q:Q, $H:$H, "Net Sales"),0) -> 1 | S40: =SUMIFS(S31:S39,$I31:$I39,"<>"&$I$29,$E31:$E39,"<>*[-]*",$F31:$F39,"<>*[-]*",$G31:$G39,"<>*[-]*",$H31:$H39,"Revenue") -> 182427.75 | T40: =IFERROR(S40/SUMIFS(S:S, $H:$H, "Net Sales"),0) -> 1 | U40: =IFERROR(($M40-O40)/ABS(O40),0) -> -0.0044501867 | V40: =IFERROR((M40-$O40), $M40-0) -> -2365.7159 | W40: =IFERROR((M40-$Q40)/ABS($Q40),0) -> -0.0044501867 | X40: =IFERROR((M40-$Q40), $M40-0) -> -2365.7159 | Y40: =IFERROR((M40-$S40)/ABS($S40),0) -> 1.9010583 | Z40: =IFERROR((M40-$S40),$M40-0) -> 346805.79 | AC40: =SUMIFS(AC31:AC39,$I31:$I39,"<>"&$I$29,$E31:$E39,"<>*[-]*",$F31:$F39,"<>*[-]*",$G31:$G39,"<>*[-]*",$H31:$H39,"Revenue") -> 529233.54 | AD40: =SUMIFS(AD31:AD39,$I31:$I39,"<>"&$I$29,$E31:$E39,"<>*[-]*",$F31:$F39,"<>*[-]*",$G31:$G39,"<>*[-]*",$H31:$H39,"Revenue") -> 182427.75 | AE40: =SUMIFS(AE31:AE39,$I31:$I39,"<>"&$I$29,$E31:$E39,"<>*[-]*",$F31:$F39,"<>*[-]*",$G31:$G39,"<>*[-]*",$H31:$H39,"Revenue") -> 531599.26 | AF40: =IFERROR((AC40-$AD40)/ABS($AD40),0) -> 1.9010583 | AG40: =(AC40-$AD40) -> 346805.79 | AH40: =IFERROR((AC40-$AE40)/ABS($AE40),0) -> -0.0044501867 | AI40: =(AC40-$AE40) -> -2365.7159 | AK40: =SUMIFS(AK31:AK39,$I31:$I39,"<>"&$I$29,$E31:$E39,"<>*[-]*",$F31:$F39,"<>*[-]*",$G31:$G39,"<>*[-]*",$H31:$H39,"Revenue") -> 529233.54 | AL40: =IFERROR(AK40/SUMIFS(AK:AK, $H:$H, "Net Sales"),0) -> 1 | AM40: =SUMIFS(AM31:AM39,$I31:$I39,"<>"&$I$29,$E31:$E39,"<>*[-]*",$F31:$F39,"<>*[-]*",$G31:$G39,"<>*[-]*",$H31:$H39,"Revenue") -> 531599.26 | AN40: =IFERROR(AM40/SUMIFS(AM:AM, $H:$H, "Net Sales"),0) -> 1 | AO40: =SUMIFS(AO31:AO39,$I31:$I39,"<>"&$I$29,$E31:$E39,"<>*[-]*",$F31:$F39,"<>*[-]*",$G31:$G39,"<>*[-]*",$H31:$H39,"Revenue") -> 531599.26 | AP40: =IFERROR(AO40/SUMIFS(AO:AO, $H:$H, "Net Sales"),0) -> 1 | AQ40: =SUMIFS(AQ31:AQ39,$I31:$I39,"<>"&$I$29,$E31:$E39,"<>*[-]*",$F31:$F39,"<>*[-]*",$G31:$G39,"<>*[-]*",$H31:$H39,"Revenue") -> 182427.75 | AR40: =IFERROR(AQ40/SUMIFS(AQ:AQ, $H:$H, "Net Sales"),0) -> 1 | AS40: =IFERROR((AK40-$AM40)/ABS($AM40),0) -> -0.0044501867 | AT40: =(AK40-$AM40) -> -2365.7159 | AU40: =IFERROR((AK40-$AO40)/ABS($AO40),0) -> -0.0044501867 | AV40: =(AK40-$AO40) -> -2365.7159 | AW40: =IFERROR((AK40-$AQ40)/ABS($AQ40),0) -> 1.9010583 | AX40: =(AK40-$AQ40) -> 346805.79 | BA40: =SUMIFS(BA31:BA39,$I31:$I39,"<>"&$I$29,$E31:$E39,"<>*[-]*",$F31:$F39,"<>*[-]*",$G31:$G39,"<>*[-]*",$H31:$H39,"Revenue") -> 6910790.3 | BB40: =IFERROR(BA40/SUMIFS(BA:BA, $H:$H, "Net Sales"),0) -> 1 | BC40: =SUMIFS(BC31:BC39,$I31:$I39,"<>"&$I$29,$E31:$E39,"<>*[-]*",$F31:$F39,"<>*[-]*",$G31:$G39,"<>*[-]*",$H31:$H39,"Revenue") -> 6910790.3 | BD40: =IFERROR(BC40/SUMIFS(BC:BC, $H:$H, "Net Sales"),0) -> 1 | BE40: =SUMIFS(BE31:BE39,$I31:$I39,"<>"&$I$29,$E31:$E39,"<>*[-]*",$F31:$F39,"<>*[-]*",$G31:$G39,"<>*[-]*",$H31:$H39,"Revenue") -> 4773077.6 | BF40: =IFERROR(BE40/SUMIFS(BE:BE, $H:$H, "Net Sales"),0) -> 1 | BG40: =IFERROR((BA40-$BC40)/ABS($BC40),0) -> 0 | BH40: =(BA40-$BC40) -> 0 | BI40: =IFERROR((BA40-$BE40)/ABS($BE40),0) -> 0.44786884 | BJ40: =(BA40-$BE40) -> 2137712.7
B42: =IF(COUNTBLANK(B44:B60)>0,"#showrow","#hiderow") -> #showrow | H42: Cost of Goods Sold
B43: #hiderow | H43: Cost of Goods Sold | M43: 275240.21 | O43: 319089.4 | Q43: 319089.4 | S43: 138633.02 | AC43: 275240.21 | AD43: 138633.02 | AE43: 319089.4 | AK43: 275240.21 | AM43: 319089.4 | AO43: 319089.4 | AQ43: 138633.02 | BA43: 4093041.3 | BC43: 4093041.3 | BE43: 3290341.2
H44: Material | M44: 275240.21 | N44: =IFERROR(M44/SUMIFS(M:M, $H:$H, "Net Sales"),0) -> 0.52007326 | O44: 319089.4 | P44: =IFERROR(O44/SUMIFS(O:O, $H:$H, "Net Sales"),0) -> 0.60024427 | Q44: 319089.4 | R44: =IFERROR(Q44/SUMIFS(Q:Q, $H:$H, "Net Sales"),0) -> 0.60024427 | S44: 138633.02 | T44: =IFERROR(S44/SUMIFS(S:S, $H:$H, "Net Sales"),0) -> 0.75993384 | U44: =IFERROR(($O44-M44)/ABS(M44),0) -> 0.15931246 | V44: =IFERROR((O44-$M44), 0-$M44) -> 43849.195 | W44: =IFERROR((Q44-$M44)/ABS($M44),0) -> 0.15931246 | X44: =IFERROR((Q44-$M44), 0 -$M44) -> 43849.195 | Y44: =IFERROR((S44-$M44)/ABS($M44),0) -> -0.49631989 | Z44: =IFERROR((S44-$M44),0-$M44) -> -136607.19 | AC44: 275240.21 | AD44: 138633.02 | AE44: 319089.4 | AF44: =IFERROR((AD44-$AC44)/ABS($AC44),0) -> -0.49631989 | AG44: =(AD44-$AC44) -> -136607.19 | AH44: =IFERROR((AE44-$AC44)/ABS($AC44),0) -> 0.15931246 | AI44: =(AE44-$AC44) -> 43849.195 | AK44: 275240.21 | AL44: =IFERROR(AK44/SUMIFS(AK:AK, $H:$H, "Net Sales"),0) -> 0.52007326 | AM44: 319089.4 | AN44: =IFERROR(AM44/SUMIFS(AM:AM, $H:$H, "Net Sales"),0) -> 0.60024427 | AO44: 319089.4 | AP44: =IFERROR(AO44/SUMIFS(AO:AO, $H:$H, "Net Sales"),0) -> 0.60024427 | AQ44: 138633.02 | AR44: =IFERROR(AQ44/SUMIFS(AQ:AQ, $H:$H, "Net Sales"),0) -> 0.75993384 | AS44: =IFERROR((AM44-$AK44)/ABS($AK44),0) -> 0.15931246 | AT44: =(AM44-$AK44) -> 43849.195 | AU44: =IFERROR((AO44-$AK44)/ABS($AO44),0) -> 0.13741978 | AV44: =(AO44-$AK44) -> 43849.195 | AW44: =IFERROR((AQ44-$AK44)/ABS($AK44),0) -> -0.49631989 | AX44: =(AQ44-$AK44) -> -136607.19 | BA44: 4093041.3 | BB44: =IFERROR(BA44/SUMIFS(BA:BA, $H:$H, "Net Sales"),0) -> 0.59226819 | BC44: 4093041.3 | BD44: =IFERROR(BC44/SUMIFS(BC:BC, $H:$H, "Net Sales"),0) -> 0.59226819 | BE44: 3290341.2 | BF44: =IFERROR(BE44/SUMIFS(BE:BE, $H:$H, "Net Sales"),0) -> 0.68935422 | BG44: =IFERROR((BC44-$BA44)/ABS($BA44),0) -> 0 | BH44: =(BC44-$BA44) -> 0 | BI44: =IFERROR((BE44-$BA44)/ABS($BA44),0) -> -0.19611336 | BJ44: =(BE44-$BA44) -> -802700.09
B45: =IF(LEFT(H45,3)="Mul", "#hiderow", "#showrow") -> #hiderow | H45: MultiDynamic: Account | N45: =IFERROR(M45/SUMIFS(M:M, $H:$H, "Net Sales"),0) -> 0 | P45: =IFERROR(O45/SUMIFS(O:O, $H:$H, "Net Sales"),0) -> 0 | R45: =IFERROR(Q45/SUMIFS(Q:Q, $H:$H, "Net Sales"),0) -> 0 | T45: =IFERROR(S45/SUMIFS(S:S, $H:$H, "Net Sales"),0) -> 0 | U45: =IFERROR(($O45-M45)/ABS(M45),0) -> 0 | V45: =IFERROR((O45-$M45), 0-$M45) -> 0 | W45: =IFERROR((Q45-$M45)/ABS($M45),0) -> 0 | X45: =IFERROR((Q45-$M45), 0 -$M45) -> 0 | Y45: =IFERROR((S45-$M45)/ABS($M45),0) -> 0 | Z45: =IFERROR((S45-$M45),0-$M45) -> 0 | AL45: =IFERROR(AK45/SUMIFS(AK:AK, $H:$H, "Net Sales"),0) -> 0 | AN45: =IFERROR(AM45/SUMIFS(AM:AM, $H:$H, "Net Sales"),0) -> 0 | AP45: =IFERROR(AO45/SUMIFS(AO:AO, $H:$H, "Net Sales"),0) -> 0 | AR45: =IFERROR(AQ45/SUMIFS(AQ:AQ, $H:$H, "Net Sales"),0) -> 0 | AS45: =IFERROR((AM45-$AK45)/ABS($AK45),0) -> 0 | AT45: =(AM45-$AK45) -> 0 | AU45: =IFERROR((AO45-$AK45)/ABS($AO45),0) -> 0 | AV45: =(AO45-$AK45) -> 0 | AW45: =IFERROR((AQ45-$AK45)/ABS($AK45),0) -> 0 | AX45: =(AQ45-$AK45) -> 0 | BB45: =IFERROR(BA45/SUMIFS(BA:BA, $H:$H, "Net Sales"),0) -> 0 | BD45: =IFERROR(BC45/SUMIFS(BC:BC, $H:$H, "Net Sales"),0) -> 0 | BF45: =IFERROR(BE45/SUMIFS(BE:BE, $H:$H, "Net Sales"),0) -> 0 | BG45: =IFERROR((BC45-$BA45)/ABS($BA45),0) -> 0 | BH45: =(BC45-$BA45) -> 0 | BI45: =IFERROR((BE45-$BA45)/ABS($BA45),0) -> 0 | BJ45: =(BE45-$BA45) -> 0
B46: =IF(LEFT(H46,3)="Mul", "#hiderow", "#showrow") -> #showrow | H46: 4104 (COGS - Material Cost - 3rd Party) | M46: 3219.01 | N46: =IFERROR(M46/SUMIFS(M:M, $H:$H, "Net Sales"),0) -> 0.0060823998 | O46: 13358.07 | P46: =IFERROR(O46/SUMIFS(O:O, $H:$H, "Net Sales"),0) -> 0.025128082 | Q46: 13358.07 | R46: =IFERROR(Q46/SUMIFS(Q:Q, $H:$H, "Net Sales"),0) -> 0.025128082 | T46: =IFERROR(S46/SUMIFS(S:S, $H:$H, "Net Sales"),0) -> 0 | U46: =IFERROR(($O46-M46)/ABS(M46),0) -> 3.1497447 | V46: =IFERROR((O46-$M46), 0-$M46) -> 10139.06 | W46: =IFERROR((Q46-$M46)/ABS($M46),0) -> 3.1497447 | X46: =IFERROR((Q46-$M46), 0 -$M46) -> 10139.06 | Y46: =IFERROR((S46-$M46)/ABS($M46),0) -> -1 | Z46: =IFERROR((S46-$M46),0-$M46) -> -3219.01 | AC46: 3219.01 | AD46: 0 | AE46: 13358.07 | AK46: 3219.01 | AL46: =IFERROR(AK46/SUMIFS(AK:AK, $H:$H, "Net Sales"),0) -> 0.0060823998 | AM46: 13358.07 | AN46: =IFERROR(AM46/SUMIFS(AM:AM, $H:$H, "Net Sales"),0) -> 0.025128082 | AO46: 13358.07 | AP46: =IFERROR(AO46/SUMIFS(AO:AO, $H:$H, "Net Sales"),0) -> 0.025128082 | AQ46: 0 | AR46: =IFERROR(AQ46/SUMIFS(AQ:AQ, $H:$H, "Net Sales"),0) -> 0 | AS46: =IFERROR((AM46-$AK46)/ABS($AK46),0) -> 3.1497447 | AT46: =(AM46-$AK46) -> 10139.06 | AU46: =IFERROR((AO46-$AK46)/ABS($AO46),0) -> 0.75902132 | AV46: =(AO46-$AK46) -> 10139.06 | AW46: =IFERROR((AQ46-$AK46)/ABS($AK46),0) -> -1 | AX46: =(AQ46-$AK46) -> -3219.01 | BA46: 173654.91 | BB46: =IFERROR(BA46/SUMIFS(BA:BA, $H:$H, "Net Sales"),0) -> 0.025128082 | BC46: 173654.91 | BD46: =IFERROR(BC46/SUMIFS(BC:BC, $H:$H, "Net Sales"),0) -> 0.025128082 | BE46: 285438.69 | BF46: =IFERROR(BE46/SUMIFS(BE:BE, $H:$H, "Net Sales"),0) -> 0.059801812 | BG46: =IFERROR((BC46-$BA46)/ABS($BA46),0) -> 0 | BH46: =(BC46-$BA46) -> 0 | BI46: =IFERROR((BE46-$BA46)/ABS($BA46),0) -> 0.64371222 | BJ46: =(BE46-$BA46) -> 111783.78
B47: =IF(LEFT(H47,3)="Mul", "#hiderow", "#showrow") -> #showrow | H47: 4105 (COGS - Material Cost - Intercompany) | M47: 42386.22 | N47: =IFERROR(M47/SUMIFS(M:M, $H:$H, "Net Sales"),0) -> 0.080089822 | O47: 176353.22 | P47: =IFERROR(O47/SUMIFS(O:O, $H:$H, "Net Sales"),0) -> 0.33174091 | Q47: 176353.22 | R47: =IFERROR(Q47/SUMIFS(Q:Q, $H:$H, "Net Sales"),0) -> 0.33174091 | S47: 138633.02 | T47: =IFERROR(S47/SUMIFS(S:S, $H:$H, "Net Sales"),0) -> 0.75993384 | U47: =IFERROR(($O47-M47)/ABS(M47),0) -> 3.1606263 | V47: =IFERROR((O47-$M47), 0-$M47) -> 133967 | W47: =IFERROR((Q47-$M47)/ABS($M47),0) -> 3.1606263 | X47: =IFERROR((Q47-$M47), 0 -$M47) -> 133967 | Y47: =IFERROR((S47-$M47)/ABS($M47),0) -> 2.2707097 | Z47: =IFERROR((S47-$M47),0-$M47) -> 96246.8 | AC47: 42386.22 | AD47: 138633.02 | AE47: 176353.22 | AK47: 42386.22 | AL47: =IFERROR(AK47/SUMIFS(AK:AK, $H:$H, "Net Sales"),0) -> 0.080089822 | AM47: 176353.22 | AN47: =IFERROR(AM47/SUMIFS(AM:AM, $H:$H, "Net Sales"),0) -> 0.33174091 | AO47: 176353.22 | AP47: =IFERROR(AO47/SUMIFS(AO:AO, $H:$H, "Net Sales"),0) -> 0.33174091 | AQ47: 138633.02 | AR47: =IFERROR(AQ47/SUMIFS(AQ:AQ, $H:$H, "Net Sales"),0) -> 0.75993384 | AS47: =IFERROR((AM47-$AK47)/ABS($AK47),0) -> 3.1606263 | AT47: =(AM47-$AK47) -> 133967 | AU47: =IFERROR((AO47-$AK47)/ABS($AO47),0) -> 0.75965157 | AV47: =(AO47-$AK47) -> 133967 | AW47: =IFERROR((AQ47-$AK47)/ABS($AK47),0) -> 2.2707097 | AX47: =(AQ47-$AK47) -> 96246.8 | BA47: 2292591.9 | BB47: =IFERROR(BA47/SUMIFS(BA:BA, $H:$H, "Net Sales"),0) -> 0.33174091 | BC47: 2292591.9 | BD47: =IFERROR(BC47/SUMIFS(BC:BC, $H:$H, "Net Sales"),0) -> 0.33174091 | BE47: 1767289.1 | BF47: =IFERROR(BE47/SUMIFS(BE:BE, $H:$H, "Net Sales"),0) -> 0.37026197 | BG47: =IFERROR((BC47-$BA47)/ABS($BA47),0) -> 0 | BH47: =(BC47-$BA47) -> 0 | BI47: =IFERROR((BE47-$BA47)/ABS($BA47),0) -> -0.22913052 | BJ47: =(BE47-$BA47) -> -525302.77
B48: =IF(LEFT(H48,3)="Mul", "#hiderow", "#showrow") -> #showrow | H48: 4108 (COGS - Labor - 3rd Party) | M48: 2368.01 | N48: =IFERROR(M48/SUMIFS(M:M, $H:$H, "Net Sales"),0) -> 0.0044744141 | O48: 5228.6382 | P48: =IFERROR(O48/SUMIFS(O:O, $H:$H, "Net Sales"),0) -> 0.0098356762 | Q48: 5228.6382 | R48: =IFERROR(Q48/SUMIFS(Q:Q, $H:$H, "Net Sales"),0) -> 0.0098356762 | T48: =IFERROR(S48/SUMIFS(S:S, $H:$H, "Net Sales"),0) -> 0 | U48: =IFERROR(($O48-M48)/ABS(M48),0) -> 1.2080304 | V48: =IFERROR((O48-$M48), 0-$M48) -> 2860.6282 | W48: =IFERROR((Q48-$M48)/ABS($M48),0) -> 1.2080304 | X48: =IFERROR((Q48-$M48), 0 -$M48) -> 2860.6282 | Y48: =IFERROR((S48-$M48)/ABS($M48),0) -> -1 | Z48: =IFERROR((S48-$M48),0-$M48) -> -2368.01 | AC48: 2368.01 | AD48: 0 | AE48: 5228.6382 | AK48: 2368.01 | AL48: =IFERROR(AK48/SUMIFS(AK:AK, $H:$H, "Net Sales"),0) -> 0.0044744141 | AM48: 5228.6382 | AN48: =IFERROR(AM48/SUMIFS(AM:AM, $H:$H, "Net Sales"),0) -> 0.0098356762 | AO48: 5228.6382 | AP48: =IFERROR(AO48/SUMIFS(AO:AO, $H:$H, "Net Sales"),0) -> 0.0098356762 | AQ48: 0 | AR48: =IFERROR(AQ48/SUMIFS(AQ:AQ, $H:$H, "Net Sales"),0) -> 0 | AS48: =IFERROR((AM48-$AK48)/ABS($AK48),0) -> 1.2080304 | AT48: =(AM48-$AK48) -> 2860.6282 | AU48: =IFERROR((AO48-$AK48)/ABS($AO48),0) -> 0.54710769 | AV48: =(AO48-$AK48) -> 2860.6282 | AW48: =IFERROR((AQ48-$AK48)/ABS($AK48),0) -> -1 | AX48: =(AQ48-$AK48) -> -2368.01 | BA48: 67972.296 | BB48: =IFERROR(BA48/SUMIFS(BA:BA, $H:$H, "Net Sales"),0) -> 0.0098356762 | BC48: 67972.296 | BD48: =IFERROR(BC48/SUMIFS(BC:BC, $H:$H, "Net Sales"),0) -> 0.0098356762 | BE48: 38340.42 | BF48: =IFERROR(BE48/SUMIFS(BE:BE, $H:$H, "Net Sales"),0) -> 0.0080326412 | BG48: =IFERROR((BC48-$BA48)/ABS($BA48),0) -> 0 | BH48: =(BC48-$BA48) -> 0 | BI48: =IFERROR((BE48-$BA48)/ABS($BA48),0) -> -0.43594049 | BJ48: =(BE48-$BA48) -> -29631.876
B49: =IF(LEFT(H49,3)="Mul", "#hiderow", "#showrow") -> #showrow | H49: 4109 (COGS - Labor - Intercompany) | M49: 62458.1 | N49: =IFERROR(M49/SUMIFS(M:M, $H:$H, "Net Sales"),0) -> 0.11801614 | O49: 69028.476 | P49: =IFERROR(O49/SUMIFS(O:O, $H:$H, "Net Sales"),0) -> 0.12985059 | Q49: 69028.476 | R49: =IFERROR(Q49/SUMIFS(Q:Q, $H:$H, "Net Sales"),0) -> 0.12985059 | T49: =IFERROR(S49/SUMIFS(S:S, $H:$H, "Net Sales"),0) -> 0 | U49: =IFERROR(($O49-M49)/ABS(M49),0) -> 0.10519653 | V49: =IFERROR((O49-$M49), 0-$M49) -> 6570.3756 | W49: =IFERROR((Q49-$M49)/ABS($M49),0) -> 0.10519653 | X49: =IFERROR((Q49-$M49), 0 -$M49) -> 6570.3756 | Y49: =IFERROR((S49-$M49)/ABS($M49),0) -> -1 | Z49: =IFERROR((S49-$M49),0-$M49) -> -62458.1 | AC49: 62458.1 | AD49: 0 | AE49: 69028.476 | AK49: 62458.1 | AL49: =IFERROR(AK49/SUMIFS(AK:AK, $H:$H, "Net Sales"),0) -> 0.11801614 | AM49: 69028.476 | AN49: =IFERROR(AM49/SUMIFS(AM:AM, $H:$H, "Net Sales"),0) -> 0.12985059 | AO49: 69028.476 | AP49: =IFERROR(AO49/SUMIFS(AO:AO, $H:$H, "Net Sales"),0) -> 0.12985059 | AQ49: 0 | AR49: =IFERROR(AQ49/SUMIFS(AQ:AQ, $H:$H, "Net Sales"),0) -> 0 | AS49: =IFERROR((AM49-$AK49)/ABS($AK49),0) -> 0.10519653 | AT49: =(AM49-$AK49) -> 6570.3756 | AU49: =IFERROR((AO49-$AK49)/ABS($AO49),0) -> 0.095183553 | AV49: =(AO49-$AK49) -> 6570.3756 | AW49: =IFERROR((AQ49-$AK49)/ABS($AK49),0) -> -1 | AX49: =(AQ49-$AK49) -> -62458.1 | BA49: 897370.18 | BB49: =IFERROR(BA49/SUMIFS(BA:BA, $H:$H, "Net Sales"),0) -> 0.12985059 | BC49: 897370.18 | BD49: =IFERROR(BC49/SUMIFS(BC:BC, $H:$H, "Net Sales"),0) -> 0.12985059 | BE49: 475136.54 | BF49: =IFERROR(BE49/SUMIFS(BE:BE, $H:$H, "Net Sales"),0) -> 0.099545111 | BG49: =IFERROR((BC49-$BA49)/ABS($BA49),0) -> 0 | BH49: =(BC49-$BA49) -> 0 | BI49: =IFERROR((BE49-$BA49)/ABS($BA49),0) -> -0.47052337 | BJ49: =(BE49-$BA49) -> -422233.64
B50: =IF(LEFT(H50,3)="Mul", "#hiderow", "#showrow") -> #showrow | H50: 4111 (COGS - WIP - Intercompany) | M50: 63782.77 | N50: =IFERROR(M50/SUMIFS(M:M, $H:$H, "Net Sales"),0) -> 0.12051914 | P50: =IFERROR(O50/SUMIFS(O:O, $H:$H, "Net Sales"),0) -> 0 | R50: =IFERROR(Q50/SUMIFS(Q:Q, $H:$H, "Net Sales"),0) -> 0 | T50: =IFERROR(S50/SUMIFS(S:S, $H:$H, "Net Sales"),0) -> 0 | U50: =IFERROR(($O50-M50)/ABS(M50),0) -> -1 | V50: =IFERROR((O50-$M50), 0-$M50) -> -63782.77 | W50: =IFERROR((Q50-$M50)/ABS($M50),0) -> -1 | X50: =IFERROR((Q50-$M50), 0 -$M50) -> -63782.77 | Y50: =IFERROR((S50-$M50)/ABS($M50),0) -> -1 | Z50: =IFERROR((S50-$M50),0-$M50) -> -63782.77 | AC50: 63782.77 | AD50: 0 | AE50: 0 | AK50: 63782.77 | AL50: =IFERROR(AK50/SUMIFS(AK:AK, $H:$H, "Net Sales"),0) -> 0.12051914 | AM50: 0 | AN50: =IFERROR(AM50/SUMIFS(AM:AM, $H:$H, "Net Sales"),0) -> 0 | AO50: 0 | AP50: =IFERROR(AO50/SUMIFS(AO:AO, $H:$H, "Net Sales"),0) -> 0 | AQ50: 0 | AR50: =IFERROR(AQ50/SUMIFS(AQ:AQ, $H:$H, "Net Sales"),0) -> 0 | AS50: =IFERROR((AM50-$AK50)/ABS($AK50),0) -> -1 | AT50: =(AM50-$AK50) -> -63782.77 | AU50: =IFERROR((AO50-$AK50)/ABS($AO50),0) -> 0 | AV50: =(AO50-$AK50) -> -63782.77 | AW50: =IFERROR((AQ50-$AK50)/ABS($AK50),0) -> -1 | AX50: =(AQ50-$AK50) -> -63782.77 | BA50: 0 | BB50: =IFERROR(BA50/SUMIFS(BA:BA, $H:$H, "Net Sales"),0) -> 0 | BC50: 0 | BD50: =IFERROR(BC50/SUMIFS(BC:BC, $H:$H, "Net Sales"),0) -> 0 | BE50: -57233.14 | BF50: =IFERROR(BE50/SUMIFS(BE:BE, $H:$H, "Net Sales"),0) -> -0.011990825 | BG50: =IFERROR((BC50-$BA50)/ABS($BA50),0) -> 0 | BH50: =(BC50-$BA50) -> 0 | BI50: =IFERROR((BE50-$BA50)/ABS($BA50),0) -> 0 | BJ50: =(BE50-$BA50) -> -57233.14
B51: =IF(LEFT(H51,3)="Mul", "#hiderow", "#showrow") -> #showrow | H51: 4112 (COGS - WIP - 3rd Party) | M51: 2418.23 | N51: =IFERROR(M51/SUMIFS(M:M, $H:$H, "Net Sales"),0) -> 0.004569306 | P51: =IFERROR(O51/SUMIFS(O:O, $H:$H, "Net Sales"),0) -> 0 | R51: =IFERROR(Q51/SUMIFS(Q:Q, $H:$H, "Net Sales"),0) -> 0 | T51: =IFERROR(S51/SUMIFS(S:S, $H:$H, "Net Sales"),0) -> 0 | U51: =IFERROR(($O51-M51)/ABS(M51),0) -> -1 | V51: =IFERROR((O51-$M51), 0-$M51) -> -2418.23 | W51: =IFERROR((Q51-$M51)/ABS($M51),0) -> -1 | X51: =IFERROR((Q51-$M51), 0 -$M51) -> -2418.23 | Y51: =IFERROR((S51-$M51)/ABS($M51),0) -> -1 | Z51: =IFERROR((S51-$M51),0-$M51) -> -2418.23 | AC51: 2418.23 | AD51: 0 | AE51: 0 | AK51: 2418.23 | AL51: =IFERROR(AK51/SUMIFS(AK:AK, $H:$H, "Net Sales"),0) -> 0.004569306 | AM51: 0 | AN51: =IFERROR(AM51/SUMIFS(AM:AM, $H:$H, "Net Sales"),0) -> 0 | AO51: 0 | AP51: =IFERROR(AO51/SUMIFS(AO:AO, $H:$H, "Net Sales"),0) -> 0 | AQ51: 0 | AR51: =IFERROR(AQ51/SUMIFS(AQ:AQ, $H:$H, "Net Sales"),0) -> 0 | AS51: =IFERROR((AM51-$AK51)/ABS($AK51),0) -> -1 | AT51: =(AM51-$AK51) -> -2418.23 | AU51: =IFERROR((AO51-$AK51)/ABS($AO51),0) -> 0 | AV51: =(AO51-$AK51) -> -2418.23 | AW51: =IFERROR((AQ51-$AK51)/ABS($AK51),0) -> -1 | AX51: =(AQ51-$AK51) -> -2418.23 | BA51: 0 | BB51: =IFERROR(BA51/SUMIFS(BA:BA, $H:$H, "Net Sales"),0) -> 0 | BC51: 0 | BD51: =IFERROR(BC51/SUMIFS(BC:BC, $H:$H, "Net Sales"),0) -> 0 | BE51: -4206.81 | BF51: =IFERROR(BE51/SUMIFS(BE:BE, $H:$H, "Net Sales"),0) -> -0.00088136216 | BG51: =IFERROR((BC51-$BA51)/ABS($BA51),0) -> 0 | BH51: =(BC51-$BA51) -> 0 | BI51: =IFERROR((BE51-$BA51)/ABS($BA51),0) -> 0 | BJ51: =(BE51-$BA51) -> -4206.81
B52: =IF(LEFT(H52,3)="Mul", "#hiderow", "#showrow") -> #showrow | H52: 4113 (COGS - Other - Intercompany) | M52: 95005.86 | N52: =IFERROR(M52/SUMIFS(M:M, $H:$H, "Net Sales"),0) -> 0.17951595 | O52: 51239.786 | P52: =IFERROR(O52/SUMIFS(O:O, $H:$H, "Net Sales"),0) -> 0.096387994 | Q52: 51239.786 | R52: =IFERROR(Q52/SUMIFS(Q:Q, $H:$H, "Net Sales"),0) -> 0.096387994 | T52: =IFERROR(S52/SUMIFS(S:S, $H:$H, "Net Sales"),0) -> 0 | U52: =IFERROR(($O52-M52)/ABS(M52),0) -> -0.4606671 | V52: =IFERROR((O52-$M52), 0-$M52) -> -43766.074 | W52: =IFERROR((Q52-$M52)/ABS($M52),0) -> -0.4606671 | X52: =IFERROR((Q52-$M52), 0 -$M52) -> -43766.074 | Y52: =IFERROR((S52-$M52)/ABS($M52),0) -> -1 | Z52: =IFERROR((S52-$M52),0-$M52) -> -95005.86 | AC52: 95005.86 | AD52: 0 | AE52: 51239.786 | AK52: 95005.86 | AL52: =IFERROR(AK52/SUMIFS(AK:AK, $H:$H, "Net Sales"),0) -> 0.17951595 | AM52: 51239.786 | AN52: =IFERROR(AM52/SUMIFS(AM:AM, $H:$H, "Net Sales"),0) -> 0.096387994 | AO52: 51239.786 | AP52: =IFERROR(AO52/SUMIFS(AO:AO, $H:$H, "Net Sales"),0) -> 0.096387994 | AQ52: 0 | AR52: =IFERROR(AQ52/SUMIFS(AQ:AQ, $H:$H, "Net Sales"),0) -> 0 | AS52: =IFERROR((AM52-$AK52)/ABS($AK52),0) -> -0.4606671 | AT52: =(AM52-$AK52) -> -43766.074 | AU52: =IFERROR((AO52-$AK52)/ABS($AO52),0) -> -0.85414241 | AV52: =(AO52-$AK52) -> -43766.074 | AW52: =IFERROR((AQ52-$AK52)/ABS($AK52),0) -> -1 | AX52: =(AQ52-$AK52) -> -95005.86 | BA52: 614877.43 | BB52: =IFERROR(BA52/SUMIFS(BA:BA, $H:$H, "Net Sales"),0) -> 0.088973533 | BC52: 614877.43 | BD52: =IFERROR(BC52/SUMIFS(BC:BC, $H:$H, "Net Sales"),0) -> 0.088973533 | BE52: 726485.74 | BF52: =IFERROR(BE52/SUMIFS(BE:BE, $H:$H, "Net Sales"),0) -> 0.15220489 | BG52: =IFERROR((BC52-$BA52)/ABS($BA52),0) -> 0 | BH52: =(BC52-$BA52) -> 0 | BI52: =IFERROR((BE52-$BA52)/ABS($BA52),0) -> 0.1815131 | BJ52: =(BE52-$BA52) -> 111608.31
B53: =IF(LEFT(H53,3)="Mul", "#hiderow", "#showrow") -> #showrow | H53: 4114 (COGS - Other - 3rd Party) | M53: 3602.01 | N53: =IFERROR(M53/SUMIFS(M:M, $H:$H, "Net Sales"),0) -> 0.0068060879 | O53: 3881.2142 | P53: =IFERROR(O53/SUMIFS(O:O, $H:$H, "Net Sales"),0) -> 0.0073010151 | Q53: 3881.2142 | R53: =IFERROR(Q53/SUMIFS(Q:Q, $H:$H, "Net Sales"),0) -> 0.0073010151 | T53: =IFERROR(S53/SUMIFS(S:S, $H:$H, "Net Sales"),0) -> 0 | U53: =IFERROR(($O53-M53)/ABS(M53),0) -> 0.077513442 | V53: =IFERROR((O53-$M53), 0-$M53) -> 279.20419 | W53: =IFERROR((Q53-$M53)/ABS($M53),0) -> 0.077513442 | X53: =IFERROR((Q53-$M53), 0 -$M53) -> 279.20419 | Y53: =IFERROR((S53-$M53)/ABS($M53),0) -> -1 | Z53: =IFERROR((S53-$M53),0-$M53) -> -3602.01 | AC53: 3602.01 | AD53: 0 | AE53: 3881.2142 | AK53: 3602.01 | AL53: =IFERROR(AK53/SUMIFS(AK:AK, $H:$H, "Net Sales"),0) -> 0.0068060879 | AM53: 3881.2142 | AN53: =IFERROR(AM53/SUMIFS(AM:AM, $H:$H, "Net Sales"),0) -> 0.0073010151 | AO53: 3881.2142 | AP53: =IFERROR(AO53/SUMIFS(AO:AO, $H:$H, "Net Sales"),0) -> 0.0073010151 | AQ53: 0 | AR53: =IFERROR(AQ53/SUMIFS(AQ:AQ, $H:$H, "Net Sales"),0) -> 0 | AS53: =IFERROR((AM53-$AK53)/ABS($AK53),0) -> 0.077513442 | AT53: =(AM53-$AK53) -> 279.20419 | AU53: =IFERROR((AO53-$AK53)/ABS($AO53),0) -> 0.071937332 | AV53: =(AO53-$AK53) -> 279.20419 | AW53: =IFERROR((AQ53-$AK53)/ABS($AK53),0) -> -1 | AX53: =(AQ53-$AK53) -> -3602.01 | BA53: 46574.57 | BB53: =IFERROR(BA53/SUMIFS(BA:BA, $H:$H, "Net Sales"),0) -> 0.0067393986 | BC53: 46574.57 | BD53: =IFERROR(BC53/SUMIFS(BC:BC, $H:$H, "Net Sales"),0) -> 0.0067393986 | BE53: 59090.62 | BF53: =IFERROR(BE53/SUMIFS(BE:BE, $H:$H, "Net Sales"),0) -> 0.012379983 | BG53: =IFERROR((BC53-$BA53)/ABS($BA53),0) -> 0 | BH53: =(BC53-$BA53) -> 0 | BI53: =IFERROR((BE53-$BA53)/ABS($BA53),0) -> 0.2687314 | BJ53: =(BE53-$BA53) -> 12516.05
H54: Freight | M54: 0 | N54: =IFERROR(M54/SUMIFS(M:M, $H:$H, "Net Sales"),0) -> 0 | O54: 0 | P54: =IFERROR(O54/SUMIFS(O:O, $H:$H, "Net Sales"),0) -> 0 | Q54: 0 | R54: =IFERROR(Q54/SUMIFS(Q:Q, $H:$H, "Net Sales"),0) -> 0 | S54: 0 | T54: =IFERROR(S54/SUMIFS(S:S, $H:$H, "Net Sales"),0) -> 0 | U54: =IFERROR(($O54-M54)/ABS(M54),0) -> 0 | V54: =IFERROR((O54-$M54), 0-$M54) -> 0 | W54: =IFERROR((Q54-$M54)/ABS($M54),0) -> 0 | X54: =IFERROR((Q54-$M54), 0 -$M54) -> 0 | Y54: =IFERROR((S54-$M54)/ABS($M54),0) -> 0 | Z54: =IFERROR((S54-$M54),0-$M54) -> 0 | AC54: 0 | AD54: 0 | AE54: 0 | AK54: 0 | AL54: =IFERROR(AK54/SUMIFS(AK:AK, $H:$H, "Net Sales"),0) -> 0 | AM54: 0 | AN54: =IFERROR(AM54/SUMIFS(AM:AM, $H:$H, "Net Sales"),0) -> 0 | AO54: 0 | AP54: =IFERROR(AO54/SUMIFS(AO:AO, $H:$H, "Net Sales"),0) -> 0 | AQ54: 0 | AR54: =IFERROR(AQ54/SUMIFS(AQ:AQ, $H:$H, "Net Sales"),0) -> 0 | AS54: =IFERROR((AM54-$AK54)/ABS($AK54),0) -> 0 | AT54: =(AM54-$AK54) -> 0 | AU54: =IFERROR((AO54-$AK54)/ABS($AO54),0) -> 0 | AV54: =(AO54-$AK54) -> 0 | AW54: =IFERROR((AQ54-$AK54)/ABS($AK54),0) -> 0 | AX54: =(AQ54-$AK54) -> 0 | BA54: 0 | BB54: =IFERROR(BA54/SUMIFS(BA:BA, $H:$H, "Net Sales"),0) -> 0 | BC54: 0 | BD54: =IFERROR(BC54/SUMIFS(BC:BC, $H:$H, "Net Sales"),0) -> 0 | BE54: 0 | BF54: =IFERROR(BE54/SUMIFS(BE:BE, $H:$H, "Net Sales"),0) -> 0 | BG54: =IFERROR((BC54-$BA54)/ABS($BA54),0) -> 0 | BH54: =(BC54-$BA54) -> 0 | BI54: =IFERROR((BE54-$BA54)/ABS($BA54),0) -> 0 | BJ54: =(BE54-$BA54) -> 0
H55: Freight In | M55: 0 | N55: =IFERROR(M55/SUMIFS(M:M, $H:$H, "Net Sales"),0) -> 0 | O55: 0 | P55: =IFERROR(O55/SUMIFS(O:O, $H:$H, "Net Sales"),0) -> 0 | Q55: 0 | R55: =IFERROR(Q55/SUMIFS(Q:Q, $H:$H, "Net Sales"),0) -> 0 | S55: 0 | T55: =IFERROR(S55/SUMIFS(S:S, $H:$H, "Net Sales"),0) -> 0 | U55: =IFERROR(($O55-M55)/ABS(M55),0) -> 0 | V55: =IFERROR((O55-$M55), 0-$M55) -> 0 | W55: =IFERROR((Q55-$M55)/ABS($M55),0) -> 0 | X55: =IFERROR((Q55-$M55), 0 -$M55) -> 0 | Y55: =IFERROR((S55-$M55)/ABS($M55),0) -> 0 | Z55: =IFERROR((S55-$M55),0-$M55) -> 0 | AC55: 0 | AD55: 0 | AE55: 0 | AK55: 0 | AL55: =IFERROR(AK55/SUMIFS(AK:AK, $H:$H, "Net Sales"),0) -> 0 | AM55: 0 | AN55: =IFERROR(AM55/SUMIFS(AM:AM, $H:$H, "Net Sales"),0) -> 0 | AO55: 0 | AP55: =IFERROR(AO55/SUMIFS(AO:AO, $H:$H, "Net Sales"),0) -> 0 | AQ55: 0 | AR55: =IFERROR(AQ55/SUMIFS(AQ:AQ, $H:$H, "Net Sales"),0) -> 0 | AS55: =IFERROR((AM55-$AK55)/ABS($AK55),0) -> 0 | AT55: =(AM55-$AK55) -> 0 | AU55: =IFERROR((AO55-$AK55)/ABS($AO55),0) -> 0 | AV55: =(AO55-$AK55) -> 0 | AW55: =IFERROR((AQ55-$AK55)/ABS($AK55),0) -> 0 | AX55: =(AQ55-$AK55) -> 0 | BA55: 0 | BB55: =IFERROR(BA55/SUMIFS(BA:BA, $H:$H, "Net Sales"),0) -> 0 | BC55: 0 | BD55: =IFERROR(BC55/SUMIFS(BC:BC, $H:$H, "Net Sales"),0) -> 0 | BE55: 0 | BF55: =IFERROR(BE55/SUMIFS(BE:BE, $H:$H, "Net Sales"),0) -> 0 | BG55: =IFERROR((BC55-$BA55)/ABS($BA55),0) -> 0 | BH55: =(BC55-$BA55) -> 0 | BI55: =IFERROR((BE55-$BA55)/ABS($BA55),0) -> 0 | BJ55: =(BE55-$BA55) -> 0
B56: =IF(LEFT(H56,3)="Mul", "#hiderow", "#showrow") -> #hiderow | H56: MultiDynamic: Account | N56: =IFERROR(M56/SUMIFS(M:M, $H:$H, "Net Sales"),0) -> 0 | P56: =IFERROR(O56/SUMIFS(O:O, $H:$H, "Net Sales"),0) -> 0 | R56: =IFERROR(Q56/SUMIFS(Q:Q, $H:$H, "Net Sales"),0) -> 0 | T56: =IFERROR(S56/SUMIFS(S:S, $H:$H, "Net Sales"),0) -> 0 | U56: =IFERROR(($O56-M56)/ABS(M56),0) -> 0 | V56: =IFERROR((O56-$M56), 0-$M56) -> 0 | W56: =IFERROR((Q56-$M56)/ABS($M56),0) -> 0 | X56: =IFERROR((Q56-$M56), 0 -$M56) -> 0 | Y56: =IFERROR((S56-$M56)/ABS($M56),0) -> 0 | Z56: =IFERROR((S56-$M56),0-$M56) -> 0 | AL56: =IFERROR(AK56/SUMIFS(AK:AK, $H:$H, "Net Sales"),0) -> 0 | AN56: =IFERROR(AM56/SUMIFS(AM:AM, $H:$H, "Net Sales"),0) -> 0 | AP56: =IFERROR(AO56/SUMIFS(AO:AO, $H:$H, "Net Sales"),0) -> 0 | AR56: =IFERROR(AQ56/SUMIFS(AQ:AQ, $H:$H, "Net Sales"),0) -> 0 | AS56: =IFERROR((AM56-$AK56)/ABS($AK56),0) -> 0 | AT56: =(AM56-$AK56) -> 0 | AU56: =IFERROR((AO56-$AK56)/ABS($AO56),0) -> 0 | AV56: =(AO56-$AK56) -> 0 | AW56: =IFERROR((AQ56-$AK56)/ABS($AK56),0) -> 0 | AX56: =(AQ56-$AK56) -> 0 | BB56: =IFERROR(BA56/SUMIFS(BA:BA, $H:$H, "Net Sales"),0) -> 0 | BD56: =IFERROR(BC56/SUMIFS(BC:BC, $H:$H, "Net Sales"),0) -> 0 | BF56: =IFERROR(BE56/SUMIFS(BE:BE, $H:$H, "Net Sales"),0) -> 0 | BG56: =IFERROR((BC56-$BA56)/ABS($BA56),0) -> 0 | BH56: =(BC56-$BA56) -> 0 | BI56: =IFERROR((BE56-$BA56)/ABS($BA56),0) -> 0 | BJ56: =(BE56-$BA56) -> 0
H57: Freight Out | M57: 0 | N57: =IFERROR(M57/SUMIFS(M:M, $H:$H, "Net Sales"),0) -> 0 | O57: 0 | P57: =IFERROR(O57/SUMIFS(O:O, $H:$H, "Net Sales"),0) -> 0 | Q57: 0 | R57: =IFERROR(Q57/SUMIFS(Q:Q, $H:$H, "Net Sales"),0) -> 0 | S57: 0 | T57: =IFERROR(S57/SUMIFS(S:S, $H:$H, "Net Sales"),0) -> 0 | U57: =IFERROR(($O57-M57)/ABS(M57),0) -> 0 | V57: =IFERROR((O57-$M57), 0-$M57) -> 0 | W57: =IFERROR((Q57-$M57)/ABS($M57),0) -> 0 | X57: =IFERROR((Q57-$M57), 0 -$M57) -> 0 | Y57: =IFERROR((S57-$M57)/ABS($M57),0) -> 0 | Z57: =IFERROR((S57-$M57),0-$M57) -> 0 | AC57: 0 | AD57: 0 | AE57: 0 | AK57: 0 | AL57: =IFERROR(AK57/SUMIFS(AK:AK, $H:$H, "Net Sales"),0) -> 0 | AM57: 0 | AN57: =IFERROR(AM57/SUMIFS(AM:AM, $H:$H, "Net Sales"),0) -> 0 | AO57: 0 | AP57: =IFERROR(AO57/SUMIFS(AO:AO, $H:$H, "Net Sales"),0) -> 0 | AQ57: 0 | AR57: =IFERROR(AQ57/SUMIFS(AQ:AQ, $H:$H, "Net Sales"),0) -> 0 | AS57: =IFERROR((AM57-$AK57)/ABS($AK57),0) -> 0 | AT57: =(AM57-$AK57) -> 0 | AU57: =IFERROR((AO57-$AK57)/ABS($AO57),0) -> 0 | AV57: =(AO57-$AK57) -> 0 | AW57: =IFERROR((AQ57-$AK57)/ABS($AK57),0) -> 0 | AX57: =(AQ57-$AK57) -> 0 | BA57: 0 | BB57: =IFERROR(BA57/SUMIFS(BA:BA, $H:$H, "Net Sales"),0) -> 0 | BC57: 0 | BD57: =IFERROR(BC57/SUMIFS(BC:BC, $H:$H, "Net Sales"),0) -> 0 | BE57: 0 | BF57: =IFERROR(BE57/SUMIFS(BE:BE, $H:$H, "Net Sales"),0) -> 0 | BG57: =IFERROR((BC57-$BA57)/ABS($BA57),0) -> 0 | BH57: =(BC57-$BA57) -> 0 | BI57: =IFERROR((BE57-$BA57)/ABS($BA57),0) -> 0 | BJ57: =(BE57-$BA57) -> 0
B58: =IF(LEFT(H58,3)="Mul", "#hiderow", "#showrow") -> #hiderow | H58: MultiDynamic: Account | N58: =IFERROR(M58/SUMIFS(M:M, $H:$H, "Net Sales"),0) -> 0 | P58: =IFERROR(O58/SUMIFS(O:O, $H:$H, "Net Sales"),0) -> 0 | R58: =IFERROR(Q58/SUMIFS(Q:Q, $H:$H, "Net Sales"),0) -> 0 | T58: =IFERROR(S58/SUMIFS(S:S, $H:$H, "Net Sales"),0) -> 0 | U58: =IFERROR(($O58-M58)/ABS(M58),0) -> 0 | V58: =IFERROR((O58-$M58), 0-$M58) -> 0 | W58: =IFERROR((Q58-$M58)/ABS($M58),0) -> 0 | X58: =IFERROR((Q58-$M58), 0 -$M58) -> 0 | Y58: =IFERROR((S58-$M58)/ABS($M58),0) -> 0 | Z58: =IFERROR((S58-$M58),0-$M58) -> 0 | AL58: =IFERROR(AK58/SUMIFS(AK:AK, $H:$H, "Net Sales"),0) -> 0 | AN58: =IFERROR(AM58/SUMIFS(AM:AM, $H:$H, "Net Sales"),0) -> 0 | AP58: =IFERROR(AO58/SUMIFS(AO:AO, $H:$H, "Net Sales"),0) -> 0 | AR58: =IFERROR(AQ58/SUMIFS(AQ:AQ, $H:$H, "Net Sales"),0) -> 0 | AS58: =IFERROR((AM58-$AK58)/ABS($AK58),0) -> 0 | AT58: =(AM58-$AK58) -> 0 | AU58: =IFERROR((AO58-$AK58)/ABS($AO58),0) -> 0 | AV58: =(AO58-$AK58) -> 0 | AW58: =IFERROR((AQ58-$AK58)/ABS($AK58),0) -> 0 | AX58: =(AQ58-$AK58) -> 0 | BB58: =IFERROR(BA58/SUMIFS(BA:BA, $H:$H, "Net Sales"),0) -> 0 | BD58: =IFERROR(BC58/SUMIFS(BC:BC, $H:$H, "Net Sales"),0) -> 0 | BF58: =IFERROR(BE58/SUMIFS(BE:BE, $H:$H, "Net Sales"),0) -> 0 | BG58: =IFERROR((BC58-$BA58)/ABS($BA58),0) -> 0 | BH58: =(BC58-$BA58) -> 0 | BI58: =IFERROR((BE58-$BA58)/ABS($BA58),0) -> 0 | BJ58: =(BE58-$BA58) -> 0
H59: Other | M59: 0 | N59: =IFERROR(M59/SUMIFS(M:M, $H:$H, "Net Sales"),0) -> 0 | O59: 0 | P59: =IFERROR(O59/SUMIFS(O:O, $H:$H, "Net Sales"),0) -> 0 | Q59: 0 | R59: =IFERROR(Q59/SUMIFS(Q:Q, $H:$H, "Net Sales"),0) -> 0 | S59: 0 | T59: =IFERROR(S59/SUMIFS(S:S, $H:$H, "Net Sales"),0) -> 0 | U59: =IFERROR(($O59-M59)/ABS(M59),0) -> 0 | V59: =IFERROR((O59-$M59), 0-$M59) -> 0 | W59: =IFERROR((Q59-$M59)/ABS($M59),0) -> 0 | X59: =IFERROR((Q59-$M59), 0 -$M59) -> 0 | Y59: =IFERROR((S59-$M59)/ABS($M59),0) -> 0 | Z59: =IFERROR((S59-$M59),0-$M59) -> 0 | AC59: 0 | AD59: 0 | AE59: 0 | AK59: 0 | AL59: =IFERROR(AK59/SUMIFS(AK:AK, $H:$H, "Net Sales"),0) -> 0 | AM59: 0 | AN59: =IFERROR(AM59/SUMIFS(AM:AM, $H:$H, "Net Sales"),0) -> 0 | AO59: 0 | AP59: =IFERROR(AO59/SUMIFS(AO:AO, $H:$H, "Net Sales"),0) -> 0 | AQ59: 0 | AR59: =IFERROR(AQ59/SUMIFS(AQ:AQ, $H:$H, "Net Sales"),0) -> 0 | AS59: =IFERROR((AM59-$AK59)/ABS($AK59),0) -> 0 | AT59: =(AM59-$AK59) -> 0 | AU59: =IFERROR((AO59-$AK59)/ABS($AO59),0) -> 0 | AV59: =(AO59-$AK59) -> 0 | AW59: =IFERROR((AQ59-$AK59)/ABS($AK59),0) -> 0 | AX59: =(AQ59-$AK59) -> 0 | BA59: 0 | BB59: =IFERROR(BA59/SUMIFS(BA:BA, $H:$H, "Net Sales"),0) -> 0 | BC59: 0 | BD59: =IFERROR(BC59/SUMIFS(BC:BC, $H:$H, "Net Sales"),0) -> 0 | BE59: 0 | BF59: =IFERROR(BE59/SUMIFS(BE:BE, $H:$H, "Net Sales"),0) -> 0 | BG59: =IFERROR((BC59-$BA59)/ABS($BA59),0) -> 0 | BH59: =(BC59-$BA59) -> 0 | BI59: =IFERROR((BE59-$BA59)/ABS($BA59),0) -> 0 | BJ59: =(BE59-$BA59) -> 0
B60: =IF(LEFT(H60,3)="Mul", "#hiderow", "#showrow") -> #hiderow | H60: MultiDynamic: Account | N60: =IFERROR(M60/SUMIFS(M:M, $H:$H, "Net Sales"),0) -> 0 | P60: =IFERROR(O60/SUMIFS(O:O, $H:$H, "Net Sales"),0) -> 0 | R60: =IFERROR(Q60/SUMIFS(Q:Q, $H:$H, "Net Sales"),0) -> 0 | T60: =IFERROR(S60/SUMIFS(S:S, $H:$H, "Net Sales"),0) -> 0 | U60: =IFERROR(($O60-M60)/ABS(M60),0) -> 0 | V60: =IFERROR((O60-$M60), 0-$M60) -> 0 | W60: =IFERROR((Q60-$M60)/ABS($M60),0) -> 0 | X60: =IFERROR((Q60-$M60), 0 -$M60) -> 0 | Y60: =IFERROR((S60-$M60)/ABS($M60),0) -> 0 | Z60: =IFERROR((S60-$M60),0-$M60) -> 0 | AL60: =IFERROR(AK60/SUMIFS(AK:AK, $H:$H, "Net Sales"),0) -> 0 | AN60: =IFERROR(AM60/SUMIFS(AM:AM, $H:$H, "Net Sales"),0) -> 0 | AP60: =IFERROR(AO60/SUMIFS(AO:AO, $H:$H, "Net Sales"),0) -> 0 | AR60: =IFERROR(AQ60/SUMIFS(AQ:AQ, $H:$H, "Net Sales"),0) -> 0 | AS60: =IFERROR((AM60-$AK60)/ABS($AK60),0) -> 0 | AT60: =(AM60-$AK60) -> 0 | AU60: =IFERROR((AO60-$AK60)/ABS($AO60),0) -> 0 | AV60: =(AO60-$AK60) -> 0 | AW60: =IFERROR((AQ60-$AK60)/ABS($AK60),0) -> 0 | AX60: =(AQ60-$AK60) -> 0 | BB60: =IFERROR(BA60/SUMIFS(BA:BA, $H:$H, "Net Sales"),0) -> 0 | BD60: =IFERROR(BC60/SUMIFS(BC:BC, $H:$H, "Net Sales"),0) -> 0 | BF60: =IFERROR(BE60/SUMIFS(BE:BE, $H:$H, "Net Sales"),0) -> 0 | BG60: =IFERROR((BC60-$BA60)/ABS($BA60),0) -> 0 | BH60: =(BC60-$BA60) -> 0 | BI60: =IFERROR((BE60-$BA60)/ABS($BA60),0) -> 0 | BJ60: =(BE60-$BA60) -> 0
B61: =B42 -> #showrow | H61: Total Cost of Goods Sold | L61: -1 | M61: =SUMIFS(M43:M60,$I43:$I60,"<>"&$I$29,$E43:$E60,"<>*[-]*",$F43:$F60,"<>*[-]*",$G43:$G60,"<>*[-]*",$H43:$H60,"Cost of Goods Sold") -> 275240.21 | N61: =IFERROR(M61/SUMIFS(M:M, $H:$H, "Net Sales"),0) -> 0.52007326 | O61: =SUMIFS(O43:O60,$I43:$I60,"<>"&$I$29,$E43:$E60,"<>*[-]*",$F43:$F60,"<>*[-]*",$G43:$G60,"<>*[-]*",$H43:$H60,"Cost of Goods Sold") -> 319089.4 | P61: =IFERROR(O61/SUMIFS(O:O, $H:$H, "Net Sales"),0) -> 0.60024427 | Q61: =SUMIFS(Q43:Q60,$I43:$I60,"<>"&$I$29,$E43:$E60,"<>*[-]*",$F43:$F60,"<>*[-]*",$G43:$G60,"<>*[-]*",$H43:$H60,"Cost of Goods Sold") -> 319089.4 | R61: =IFERROR(Q61/SUMIFS(Q:Q, $H:$H, "Net Sales"),0) -> 0.60024427 | S61: =SUMIFS(S43:S60,$I43:$I60,"<>"&$I$29,$E43:$E60,"<>*[-]*",$F43:$F60,"<>*[-]*",$G43:$G60,"<>*[-]*",$H43:$H60,"Cost of Goods Sold") -> 138633.02 | T61: =IFERROR(S61/SUMIFS(S:S, $H:$H, "Net Sales"),0) -> 0.75993384 | U61: =IFERROR(($O61-M61)/ABS(M61),0) -> 0.15931246 | V61: =IFERROR((O61-$M61), 0-$M61) -> 43849.195 | W61: =IFERROR((Q61-$M61)/ABS($M61),0) -> 0.15931246 | X61: =IFERROR((Q61-$M61), 0 -$M61) -> 43849.195 | Y61: =IFERROR((S61-$M61)/ABS($M61),0) -> -0.49631989 | Z61: =IFERROR((S61-$M61),0-$M61) -> -136607.19 | AC61: =SUMIFS(AC43:AC60,$I43:$I60,"<>"&$I$29,$E43:$E60,"<>*[-]*",$F43:$F60,"<>*[-]*",$G43:$G60,"<>*[-]*",$H43:$H60,"Cost of Goods Sold") -> 275240.21 | AD61: =SUMIFS(AD43:AD60,$I43:$I60,"<>"&$I$29,$E43:$E60,"<>*[-]*",$F43:$F60,"<>*[-]*",$G43:$G60,"<>*[-]*",$H43:$H60,"Cost of Goods Sold") -> 138633.02 | AE61: =SUMIFS(AE43:AE60,$I43:$I60,"<>"&$I$29,$E43:$E60,"<>*[-]*",$F43:$F60,"<>*[-]*",$G43:$G60,"<>*[-]*",$H43:$H60,"Cost of Goods Sold") -> 319089.4 | AF61: =IFERROR((AD61-$AC61)/ABS($AC61),0) -> -0.49631989 | AG61: =(AD61-$AC61) -> -136607.19 | AH61: =IFERROR((AE61-$AC61)/ABS($AC61),0) -> 0.15931246 | AI61: =(AE61-$AC61) -> 43849.195 | AK61: =SUMIFS(AK43:AK60,$I43:$I60,"<>"&$I$29,$E43:$E60,"<>*[-]*",$F43:$F60,"<>*[-]*",$G43:$G60,"<>*[-]*",$H43:$H60,"Cost of Goods Sold") -> 275240.21 | AL61: =IFERROR(AK61/SUMIFS(AK:AK, $H:$H, "Net Sales"),0) -> 0.52007326 | AM61: =SUMIFS(AM43:AM60,$I43:$I60,"<>"&$I$29,$E43:$E60,"<>*[-]*",$F43:$F60,"<>*[-]*",$G43:$G60,"<>*[-]*",$H43:$H60,"Cost of Goods Sold") -> 319089.4 | AN61: =IFERROR(AM61/SUMIFS(AM:AM, $H:$H, "Net Sales"),0) -> 0.60024427 | AO61: =SUMIFS(AO43:AO60,$I43:$I60,"<>"&$I$29,$E43:$E60,"<>*[-]*",$F43:$F60,"<>*[-]*",$G43:$G60,"<>*[-]*",$H43:$H60,"Cost of Goods Sold") -> 319089.4 | AP61: =IFERROR(AO61/SUMIFS(AO:AO, $H:$H, "Net Sales"),0) -> 0.60024427 | AQ61: =SUMIFS(AQ43:AQ60,$I43:$I60,"<>"&$I$29,$E43:$E60,"<>*[-]*",$F43:$F60,"<>*[-]*",$G43:$G60,"<>*[-]*",$H43:$H60,"Cost of Goods Sold") -> 138633.02 | AR61: =IFERROR(AQ61/SUMIFS(AQ:AQ, $H:$H, "Net Sales"),0) -> 0.75993384 | AS61: =IFERROR((AM61-$AK61)/ABS($AK61),0) -> 0.15931246 | AT61: =(AM61-$AK61) -> 43849.195 | AU61: =IFERROR((AO61-$AK61)/ABS($AO61),0) -> 0.13741978 | AV61: =(AO61-$AK61) -> 43849.195 | AW61: =IFERROR((AQ61-$AK61)/ABS($AK61),0) -> -0.49631989 | AX61: =(AQ61-$AK61) -> -136607.19 | BA61: =SUMIFS(BA43:BA60,$I43:$I60,"<>"&$I$29,$E43:$E60,"<>*[-]*",$F43:$F60,"<>*[-]*",$G43:$G60,"<>*[-]*",$H43:$H60,"Cost of Goods Sold") -> 4093041.3 | BB61: =IFERROR(BA61/SUMIFS(BA:BA, $H:$H, "Net Sales"),0) -> 0.59226819 | BC61: =SUMIFS(BC43:BC60,$I43:$I60,"<>"&$I$29,$E43:$E60,"<>*[-]*",$F43:$F60,"<>*[-]*",$G43:$G60,"<>*[-]*",$H43:$H60,"Cost of Goods Sold") -> 4093041.3 | BD61: =IFERROR(BC61/SUMIFS(BC:BC, $H:$H, "Net Sales"),0) -> 0.59226819 | BE61: =SUMIFS(BE43:BE60,$I43:$I60,"<>"&$I$29,$E43:$E60,"<>*[-]*",$F43:$F60,"<>*[-]*",$G43:$G60,"<>*[-]*",$H43:$H60,"Cost of Goods Sold") -> 3290341.2 | BF61: =IFERROR(BE61/SUMIFS(BE:BE, $H:$H, "Net Sales"),0) -> 0.68935422 | BG61: =IFERROR((BC61-$BA61)/ABS($BA61),0) -> 0 | BH61: =(BC61-$BA61) -> 0 | BI61: =IFERROR((BE61-$BA61)/ABS($BA61),0) -> -0.19611336 | BJ61: =(BE61-$BA61) -> -802700.09
B62: =B42 -> #showrow | H62: Gross Margin | M62: =M40-M61 -> 253993.33 | N62: =IFERROR(M62/SUMIFS(M:M, $H:$H, "Net Sales"),0) -> 0.47992674 | O62: =O40-O61 -> 212509.85 | P62: =IFERROR(O62/SUMIFS(O:O, $H:$H, "Net Sales"),0) -> 0.39975573 | Q62: =Q40-Q61 -> 212509.85 | R62: =IFERROR(Q62/SUMIFS(Q:Q, $H:$H, "Net Sales"),0) -> 0.39975573 | S62: =S40-S61 -> 43794.73 | T62: =IFERROR(S62/SUMIFS(S:S, $H:$H, "Net Sales"),0) -> 0.24006616 | V62: =($M62-O62) -> 41483.479 | X62: =($M62-Q62) -> 41483.479 | Z62: =($M62-S62) -> 210198.6 | AC62: =AC40-AC61 -> 253993.33 | AD62: =AD40-AD61 -> 43794.73 | AE62: =AE40-AE61 -> 212509.85 | AF62: =AF40-AF61 -> 2.3973782 | AK62: =AK40-AK61 -> 253993.33 | AL62: =IFERROR(AK62/SUMIFS(AK:AK, $H:$H, "Net Sales"),0) -> 0.47992674 | AM62: =AM40-AM61 -> 212509.85 | AN62: =IFERROR(AM62/SUMIFS(AM:AM, $H:$H, "Net Sales"),0) -> 0.39975573 | AO62: =AO40-AO61 -> 212509.85 | AP62: =IFERROR(AO62/SUMIFS(AO:AO, $H:$H, "Net Sales"),0) -> 0.39975573 | AQ62: =AQ40-AQ61 -> 43794.73 | AR62: =IFERROR(AQ62/SUMIFS(AQ:AQ, $H:$H, "Net Sales"),0) -> 0.24006616 | AT62: =($AK62-AM62) -> 41483.479 | AV62: =($AK62-AO62) -> 41483.479 | AX62: =($AK62-AQ62) -> 210198.6 | BA62: =BA40-BA61 -> 2817749.1 | BB62: =IFERROR(BA62/SUMIFS(BA:BA, $H:$H, "Net Sales"),0) -> 0.40773181 | BC62: =BC40-BC61 -> 2817749.1 | BD62: =IFERROR(BC62/SUMIFS(BC:BC, $H:$H, "Net Sales"),0) -> 0.40773181 | BE62: =BE40-BE61 -> 1482736.4 | BF62: =IFERROR(BE62/SUMIFS(BE:BE, $H:$H, "Net Sales"),0) -> 0.31064578 | BH62: =($BA62-BC62) -> 0 | BJ62: =($BA62-BE62) -> 1335012.6
B63: =B42 -> #showrow | H63: Gross Margin % | M63: =IFERROR((M40-M61)/M40,0) -> 0.47992674 | O63: =IFERROR((O40-O61)/O40,0) -> 0.39975573 | Q63: =IFERROR((Q40-Q61)/Q40,0) -> 0.39975573 | S63: =IFERROR((S40-S61)/S40,0) -> 0.24006616 | AC63: =IFERROR((AC40-AC61)/AC40,0) -> 0.47992674 | AD63: =IFERROR((AD40-AD61)/AD40,0) -> 0.24006616 | AE63: =IFERROR((AE40-AE61)/AE40,0) -> 0.39975573 | AF63: =IFERROR((AF40-AF61)/AF40,0) -> 1.2610756 | AK63: =IFERROR((AK40-AK61)/AK40,0) -> 0.47992674 | AM63: =IFERROR((AM40-AM61)/AM40,0) -> 0.39975573 | AO63: =IFERROR((AO40-AO61)/AO40,0) -> 0.39975573 | AQ63: =IFERROR((AQ40-AQ61)/AQ40,0) -> 0.24006616 | BA63: =IFERROR((BA40-BA61)/BA40,0) -> 0.40773181 | BC63: =IFERROR((BC40-BC61)/BC40,0) -> 0.40773181 | BE63: =IFERROR((BE40-BE61)/BE40,0) -> 0.31064578
B65: =IF(COUNTBLANK(B66:B133)>0,"#showrow","#hiderow") -> #showrow | H65: Operating Expenses
H66: Operating Expenses | M66: 0 | N66: =IFERROR(M66/SUMIFS(M:M, $H:$H, "Net Sales"),0) -> 0 | O66: -2.17e-10 | P66: =IFERROR(O66/SUMIFS(O:O, $H:$H, "Net Sales"),0) -> -4.0820223e-16 | Q66: -2.17e-10 | R66: =IFERROR(Q66/SUMIFS(Q:Q, $H:$H, "Net Sales"),0) -> -4.0820223e-16 | S66: 0 | T66: =IFERROR(S66/SUMIFS(S:S, $H:$H, "Net Sales"),0) -> 0 | U66: =IFERROR(($O66-M66)/ABS(M66),0) -> 0 | V66: =IFERROR((O66-$M66), 0-$M66) -> -2.17e-10 | W66: =IFERROR((Q66-$M66)/ABS($M66),0) -> 0 | X66: =IFERROR((Q66-$M66), 0 -$M66) -> -2.17e-10 | Y66: =IFERROR((S66-$M66)/ABS($M66),0) -> 0 | Z66: =IFERROR((S66-$M66),0-$M66) -> 0 | AC66: 0 | AD66: 0 | AE66: -2.17e-10 | AF66: =IFERROR((AD66-$AC66)/ABS($AC66),0) -> 0 | AG66: =(AD66-$AC66) -> 0 | AH66: =IFERROR((AE66-$AC66)/ABS($AC66),0) -> 0 | AI66: =(AE66-$AC66) -> -2.17e-10 | AK66: 0 | AL66: =IFERROR(AK66/SUMIFS(AK:AK, $H:$H, "Net Sales"),0) -> 0 | AM66: -2.17e-10 | AN66: =IFERROR(AM66/SUMIFS(AM:AM, $H:$H, "Net Sales"),0) -> -4.0820223e-16 | AO66: -2.17e-10 | AP66: =IFERROR(AO66/SUMIFS(AO:AO, $H:$H, "Net Sales"),0) -> -4.0820223e-16 | AQ66: 0 | AR66: =IFERROR(AQ66/SUMIFS(AQ:AQ, $H:$H, "Net Sales"),0) -> 0 | AS66: =IFERROR((AM66-$AK66)/ABS($AK66),0) -> 0 | AT66: =(AM66-$AK66) -> -2.17e-10 | AU66: =IFERROR((AO66-$AK66)/ABS($AO66),0) -> -1 | AV66: =(AO66-$AK66) -> -2.17e-10 | AW66: =IFERROR((AQ66-$AK66)/ABS($AK66),0) -> 0 | AX66: =(AQ66-$AK66) -> 0 | BA66: -3.136e-09 | BB66: =IFERROR(BA66/SUMIFS(BA:BA, $H:$H, "Net Sales"),0) -> -4.5378312e-16 | BC66: -3.136e-09 | BD66: =IFERROR(BC66/SUMIFS(BC:BC, $H:$H, "Net Sales"),0) -> -4.5378312e-16 | BE66: 34.98 | BF66: =IFERROR(BE66/SUMIFS(BE:BE, $H:$H, "Net Sales"),0) -> 7.3286049e-06 | BG66: =IFERROR((BC66-$BA66)/ABS($BA66),0) -> 0 | BH66: =(BC66-$BA66) -> 0 | BI66: =IFERROR((BE66-$BA66)/ABS($BA66),0) -> 1.1154337e+10 | BJ66: =(BE66-$BA66) -> 34.98
H67: Salaries & Fringes | M67: 64826.11 | N67: =IFERROR(M67/SUMIFS(M:M, $H:$H, "Net Sales"),0) -> 0.12249055 | O67: 74257.114 | P67: =IFERROR(O67/SUMIFS(O:O, $H:$H, "Net Sales"),0) -> 0.13968626 | Q67: 74257.114 | R67: =IFERROR(Q67/SUMIFS(Q:Q, $H:$H, "Net Sales"),0) -> 0.13968626 | S67: 65541.35 | T67: =IFERROR(S67/SUMIFS(S:S, $H:$H, "Net Sales"),0) -> 0.35927292 | U67: =IFERROR(($O67-M67)/ABS(M67),0) -> 0.14548156 | V67: =IFERROR((O67-$M67), 0-$M67) -> 9431.0037 | W67: =IFERROR((Q67-$M67)/ABS($M67),0) -> 0.14548156 | X67: =IFERROR((Q67-$M67), 0 -$M67) -> 9431.0037 | Y67: =IFERROR((S67-$M67)/ABS($M67),0) -> 0.011033209 | Z67: =IFERROR((S67-$M67),0-$M67) -> 715.24 | AC67: 64826.11 | AD67: 65541.35 | AE67: 74257.114 | AK67: 64826.11 | AL67: =IFERROR(AK67/SUMIFS(AK:AK, $H:$H, "Net Sales"),0) -> 0.12249055 | AM67: 74257.114 | AN67: =IFERROR(AM67/SUMIFS(AM:AM, $H:$H, "Net Sales"),0) -> 0.13968626 | AO67: 74257.114 | AP67: =IFERROR(AO67/SUMIFS(AO:AO, $H:$H, "Net Sales"),0) -> 0.13968626 | AQ67: 65541.35 | AR67: =IFERROR(AQ67/SUMIFS(AQ:AQ, $H:$H, "Net Sales"),0) -> 0.35927292 | AS67: =IFERROR((AM67-$AK67)/ABS($AK67),0) -> 0.14548156 | AT67: =(AM67-$AK67) -> 9431.0037 | AU67: =IFERROR((AO67-$AK67)/ABS($AO67),0) -> 0.12700472 | AV67: =(AO67-$AK67) -> 9431.0037 | AW67: =IFERROR((AQ67-$AK67)/ABS($AK67),0) -> 0.011033209 | AX67: =(AQ67-$AK67) -> 715.24 | BA67: 965342.48 | BB67: =IFERROR(BA67/SUMIFS(BA:BA, $H:$H, "Net Sales"),0) -> 0.13968626 | BC67: 965342.48 | BD67: =IFERROR(BC67/SUMIFS(BC:BC, $H:$H, "Net Sales"),0) -> 0.13968626 | BE67: 903143.51 | BF67: =IFERROR(BE67/SUMIFS(BE:BE, $H:$H, "Net Sales"),0) -> 0.18921618 | BG67: =IFERROR((BC67-$BA67)/ABS($BA67),0) -> 0 | BH67: =(BC67-$BA67) -> 0 | BI67: =IFERROR((BE67-$BA67)/ABS($BA67),0) -> -0.064432023 | BJ67: =(BE67-$BA67) -> -62198.969
B68: =IF(LEFT(H68,3)="Mul", "#hiderow", "#showrow") -> #hiderow | H68: MultiDynamic: Account | N68: =IFERROR(M68/SUMIFS(M:M, $H:$H, "Net Sales"),0) -> 0 | P68: =IFERROR(O68/SUMIFS(O:O, $H:$H, "Net Sales"),0) -> 0 | R68: =IFERROR(Q68/SUMIFS(Q:Q, $H:$H, "Net Sales"),0) -> 0 | T68: =IFERROR(S68/SUMIFS(S:S, $H:$H, "Net Sales"),0) -> 0 | U68: =IFERROR(($O68-M68)/ABS(M68),0) -> 0 | V68: =IFERROR((O68-$M68), 0-$M68) -> 0 | W68: =IFERROR((Q68-$M68)/ABS($M68),0) -> 0 | X68: =IFERROR((Q68-$M68), 0 -$M68) -> 0 | Y68: =IFERROR((S68-$M68)/ABS($M68),0) -> 0 | Z68: =IFERROR((S68-$M68),0-$M68) -> 0 | AL68: =IFERROR(AK68/SUMIFS(AK:AK, $H:$H, "Net Sales"),0) -> 0 | AN68: =IFERROR(AM68/SUMIFS(AM:AM, $H:$H, "Net Sales"),0) -> 0 | AP68: =IFERROR(AO68/SUMIFS(AO:AO, $H:$H, "Net Sales"),0) -> 0 | AR68: =IFERROR(AQ68/SUMIFS(AQ:AQ, $H:$H, "Net Sales"),0) -> 0 | AS68: =IFERROR((AM68-$AK68)/ABS($AK68),0) -> 0 | AT68: =(AM68-$AK68) -> 0 | AU68: =IFERROR((AO68-$AK68)/ABS($AO68),0) -> 0 | AV68: =(AO68-$AK68) -> 0 | AW68: =IFERROR((AQ68-$AK68)/ABS($AK68),0) -> 0 | AX68: =(AQ68-$AK68) -> 0 | BB68: =IFERROR(BA68/SUMIFS(BA:BA, $H:$H, "Net Sales"),0) -> 0 | BD68: =IFERROR(BC68/SUMIFS(BC:BC, $H:$H, "Net Sales"),0) -> 0 | BF68: =IFERROR(BE68/SUMIFS(BE:BE, $H:$H, "Net Sales"),0) -> 0 | BG68: =IFERROR((BC68-$BA68)/ABS($BA68),0) -> 0 | BH68: =(BC68-$BA68) -> 0 | BI68: =IFERROR((BE68-$BA68)/ABS($BA68),0) -> 0 | BJ68: =(BE68-$BA68) -> 0
B69: =IF(LEFT(H69,3)="Mul", "#hiderow", "#showrow") -> #showrow | H69: 6115 (Salary Expense) | M69: 47925.58 | N69: =IFERROR(M69/SUMIFS(M:M, $H:$H, "Net Sales"),0) -> 0.090556581 | O69: 61333.945 | P69: =IFERROR(O69/SUMIFS(O:O, $H:$H, "Net Sales"),0) -> 0.11537628 | Q69: 61333.945 | R69: =IFERROR(Q69/SUMIFS(Q:Q, $H:$H, "Net Sales"),0) -> 0.11537628 | S69: 40722.51 | T69: =IFERROR(S69/SUMIFS(S:S, $H:$H, "Net Sales"),0) -> 0.22322541 | U69: =IFERROR(($O69-M69)/ABS(M69),0) -> 0.27977471 | V69: =IFERROR((O69-$M69), 0-$M69) -> 13408.365 | W69: =IFERROR((Q69-$M69)/ABS($M69),0) -> 0.27977471 | X69: =IFERROR((Q69-$M69), 0 -$M69) -> 13408.365 | Y69: =IFERROR((S69-$M69)/ABS($M69),0) -> -0.15029698 | Z69: =IFERROR((S69-$M69),0-$M69) -> -7203.07 | AC69: 47925.58 | AD69: 40722.51 | AE69: 61333.945 | AK69: 47925.58 | AL69: =IFERROR(AK69/SUMIFS(AK:AK, $H:$H, "Net Sales"),0) -> 0.090556581 | AM69: 61333.945 | AN69: =IFERROR(AM69/SUMIFS(AM:AM, $H:$H, "Net Sales"),0) -> 0.11537628 | AO69: 61333.945 | AP69: =IFERROR(AO69/SUMIFS(AO:AO, $H:$H, "Net Sales"),0) -> 0.11537628 | AQ69: 40722.51 | AR69: =IFERROR(AQ69/SUMIFS(AQ:AQ, $H:$H, "Net Sales"),0) -> 0.22322541 | AS69: =IFERROR((AM69-$AK69)/ABS($AK69),0) -> 0.27977471 | AT69: =(AM69-$AK69) -> 13408.365 | AU69: =IFERROR((AO69-$AK69)/ABS($AO69),0) -> 0.21861247 | AV69: =(AO69-$AK69) -> 13408.365 | AW69: =IFERROR((AQ69-$AK69)/ABS($AK69),0) -> -0.15029698 | AX69: =(AQ69-$AK69) -> -7203.07 | BA69: 797341.29 | BB69: =IFERROR(BA69/SUMIFS(BA:BA, $H:$H, "Net Sales"),0) -> 0.11537628 | BC69: 797341.29 | BD69: =IFERROR(BC69/SUMIFS(BC:BC, $H:$H, "Net Sales"),0) -> 0.11537628 | BE69: 607481.56 | BF69: =IFERROR(BE69/SUMIFS(BE:BE, $H:$H, "Net Sales"),0) -> 0.12727251 | BG69: =IFERROR((BC69-$BA69)/ABS($BA69),0) -> 0 | BH69: =(BC69-$BA69) -> 0 | BI69: =IFERROR((BE69-$BA69)/ABS($BA69),0) -> -0.23811601 | BJ69: =(BE69-$BA69) -> -189859.73
